Workbook

Sheet 行为概览
F2: 等级下限 | G2: 等级上限 | H2: 平均每日耗时(m) | I2: 每日耗时(h) | J2: 经验效率 | K2: 宠物经验效率 | L2: 银币权重 | M2: 金币权重 | N2: 符石 | O2: 公会DKP | P2: 职业贡献 | Q2: 声望值 | R2: 荣誉值 | S2: 节日积分 | T2: 每日活跃度 | U2: 每日活跃度 | W2: 消耗类属性
A3: 单人 | B3: 师门任务 | C3: 日常活动 | D3: 职业日常 | E3: 每日2轮 | F3: 15 | G3: 150 | H3: 20 | I3: =H3/60 -> 0.33333333 | J3: 50 | K3: 3 | L3: 4 | M3: 8 | W3: 经验
A4: 多人(至少3人) | B4: 抓鬼 | D4: 日常副本 | E4: 每日5轮普通 | F4: 20 | G4: 150 | H4: 120 | I4: =H4/60 -> 2 | J4: 3.3 | K4: 0.55 | L4: 1.65 | W4: 宠物经验
A5: 单人 | B5: 平定安邦 | D5: 英雄试炼 | E5: 每日1次 | F5: 20 | G5: 150 | H5: 5 | I5: =H5/60 -> 0.083333333 | J5: 30 | L5: 0.5 | W5: 银币
A6: 单人 | B6: 秘境降妖 | D6: 冰封王座 | E6: 每日25关 | F6: 40 | G6: 150 | H6: 60 | I6: =H6/60 -> 1 | J6: 15 | K6: 1.5 | L6: 1 | M6: 10 | W6: 金币
A7: 单人 | B7: 宝图 | D7: 考古 | E7: 每日10张图15次 | F7: 25 | G7: 150 | H7: 20 | I7: =H7/60 -> 0.33333333 | K7: 2 | W7: 符石
B8: 运镖 | D8: 运镖 | F8: 30 | G8: 150 | H8: 0 | I8: =H8/60 -> 0 | W8: 公会DKP | X8: 帮贡
A9: 多人(至少3人) | B9: 副本 | D9: 卡拉赞系列 | E9: 每日1次 | F9: 40 | G9: 150 | H9: 0 | I9: =H9/60 -> 0 | W9: 职业贡献 | X9: 门贡
A10: 多人(至少3人) | B10: 精英副本 | D10: 卡拉赞精英 | E10: 每周1次 | F10: 40 | G10: 150 | H10: 0 | I10: =H10/60 -> 0 | W10: 声望值 | X10: 侠义
B11: 前尘旧梦 | D11: 精英副本 | E11: 每日2次 | F11: 30 | G11: 150 | H11: 30 | I11: =H11/60 -> 0.5 | J11: 20 | K11: 2 | L11: 1 | M11: 10 | W11: 荣誉值 | X11: 武勋
A12: 单人 | B12: 帮派任务 | D12: 公会任务(周7轮) | E12: 每周7轮 | F12: 35 | G12: 150 | H12: 10 | I12: =H12/60 -> 0.16666667 | J12: 20 | L12: 1 | M12: 5 | W12: 节日积分
B13: 任务链 | D13: 暗夜马戏团(周20轮) | E13: 每周200次 | F13: 50 | G13: 150 | H13: 30 | I13: =H13/60 -> 0.5 | J13: 40
A14: 单人 | B14: 野外挂机/离线经验 | D14: 野外挂机/离线经验 | E14: 每日8小时 | F14: 10 | G14: 150 | H14: 720 | I14: =H14/60 -> 12 | J14: 1 | K14: 1 | W14: 每日活跃度
B15: 经验道具 | D15: 经验道具 | E15: 每日10个 | F15: 20 | G15: 150 | H15: 5 | I15: =H15/60 -> 0.083333333 | J15: 150 | W15: 活力
A16: 单人 | B16: 分享 | D16: 分享 | E16: 每日1次 | F16: 10 | G16: 150 | H16: 5 | I16: =H16/60 -> 0.083333333 | J16: 10 | L16: 0.5
B17: 双倍点数 | D17: 双倍点数 | E17: 每周1800点 | F17: 0 | G17: 150 | H17: 156 | I17: =H17/60 -> 2.6 | J17: 20 | K17: 2 | L17: 5 | M17: 10 | W17: 竞技场积分
B18: 援助战斗和道具 | D18: 援助战斗和道具 | E18: 每日获得奖励有上限 | F18: 30 | G18: 150 | H18: 60 | I18: =H18/60 -> 1 | J18: 6
A19: 单人或多人 | B19: 封妖 | C19: 限时活动 | D19: 古神爪牙 | E19: 每日10次 | F19: 25 | G19: 150 | H19: 20 | I19: =H19/60 -> 0.33333333 | J19: 20 | K19: 1.5 | L19: 1 | M19: 3
A20: 多人 | B20: 星宿护卫 | D20: 幼龙 | E20: 50级以下10次 | F20: 35 | G20: 49 | H20: 30 | I20: =H20/60 -> 0.5 | J20: 15 | K20: 1.5 | L20: 1
A21: 多人 | B21: 杀星 | D21: 屠龙 | E21: 50级以上5次 | F21: 50 | G21: 150 | H21: 20 | I21: =H21/60 -> 0.33333333 | J21: 15 | K21: 1.5 | L21: 1
A22: 多人 | B22: 妖王 | D22: 古神 | E22: 每日3次 | F22: 25 | G22: 150 | H22: 10 | I22: =H22/60 -> 0.16666667 | J22: 40 | K22: 2 | L22: 1.5 | M22: 4 | W22: (2+等级*0.075)*活跃度 | X22: 4000
A23: 单人 | B23: 三界奇缘 | D23: 艾泽拉斯地理探索 | E23: 每日1次 | F23: 30 | G23: 150 | H23: 10 | I23: =H23/60 -> 0.16666667 | J23: 15 | L23: 1
A24: 单人 | B24: 科举 | D24: 艾泽拉斯百科竞赛 | E24: 每日1次 决赛双倍，星期日没有 | F24: 30 | G24: 150 | H24: 10 | I24: =H24/60 -> 0.16666667 | J24: 30 | L24: 1 | W24: 20+等级*0.075*0.5
A25: 多人(最好每个职业一个) | B25: 门派闯关 | D25: 职业闯关(周2次) | E25: 每周2次 | F25: 40 | G25: 150 | H25: 15 | I25: =H25/60 -> 0.25 | J25: 25 | K25: 1 | L25: 1
A26: 单人 | B26: 竞技场 | D26: 竞技场（周5次） | E26: 每周2356，周日5v5 | F26: 40 | G26: 150 | H26: 35 | I26: =H26/60 -> 0.58333333 | J26: 15 | L26: 3 | M26: 10
A27: 多人 | B27: 帮派秘境 | D27: 公会副本(周1次) | E27: 每周1次 | F27: 40 | G27: 150 | H27: 10 | I27: =H27/60 -> 0.16666667 | J27: 15 | K27: 0.5 | L27: 0.5 | W27: 等级*0.075*0.5
A28: 多人 | B28: 帮派强盗 | D28: 帮派强盗 | E28: 每周2次 | F28: 40 | G28: 150 | H28: 0 | I28: =H28/60 -> 0
A29: 多人 | B29: 帮派采药 | D29: 帮派采药 | E29: 每周2次 | F29: 40 | G29: 150 | H29: 0 | I29: =H29/60 -> 0
A30: 看运营活动决定 | B30: 节日活动 | C30: 节日活动 | D30: 节日活动1 | F30: 20 | G30: 150 | H30: 0 | I30: =H30/60 -> 0
B31: 节日活动 | D31: 节日活动2 | F31: 40 | G31: 150 | H31: 0 | I31: =H31/60 -> 0
B32: 活跃度打卡 | D32: 活跃度打卡 | F32: 25 | G32: 150 | H32: 5 | I32: =H32/60 -> 0.083333333 | M32: 20
A33: 单人(打不过可找别人帮忙) | B33: 剧情任务 | C33: 一次性活动 | D33: 剧情任务
H34: 每日玩法时长 | I34: =SUM(I3:I33)-I5-I14-I15-I16-I21-I22-I32 -> 10.6
F39: 开启时间 | G39: 星期一 | H39: 星期二 | I39: 星期三 | J39: 星期四 | K39: 星期五 | L39: 星期六 | M39: 星期日
F40: 0.45833333 | G40: 人文探索 | H40: 人文探索 | I40: 人文探索 | J40: 人文探索 | K40: 人文探索 | L40: 人文探索 | M40: 人文探索
F41: 0.70833333 | G41: 智慧试炼初赛 | H41: 智慧试炼初赛 | I41: 智慧试炼初赛 | J41: 智慧试炼初赛 | K41: 智慧试炼初赛 | L41: 智慧试炼复赛 | M41: 公会副本
F42: 0.83333333 | G42: 冠军试炼 | H42: 1v1竞技场 | I42: 3v3竞技场 | J42: 冠军试炼 | K42: 1v1竞技场 | L42: 3v3竞技场 | M42: 奥山战场
G45: 等级下限 | H45: 等级上限 | I45: 经验 | J45: 宠物经验 | L45: 金币 | M45: 银币
F46: 职业日常 | G46: 15 | H46: 150 | I46: 40 | J46: 1.5 | L46: 10 | M46: 6
F47: 日常副本 | G47: 20 | H47: 150 | I47: 4 | J47: 0.5 | M47: 1.5
F48: 英雄试炼 | G48: 30 | H48: 150 | I48: 10 | M48: 0
F49: 冰封王座 | G49: 40 | H49: 150 | I49: 30 | J49: 4 | M49: 0 | O49: 33 | P49: 1740 | Q49: =O49^2*1.6 -> 1742.4 | R49: =50+10*O49 -> 380
F50: 考古 | G50: 25 | H50: 150 | M50: 0 | O50: 57 | P50: 28220 | Q50: =O50^2*1.6 -> 5198.4 | R50: =50+10*O50 -> 620
F51: 运镖 | G51: 31 | H51: 150 | O51: 58 | P51: 29950 | Q51: =O51^2*1.6 -> 5382.4 | R51: =50+10*O51 -> 630
F52: 卡拉赞系列 | G52: 40/60 | H52: 150 | I52: 20 | J52: 2 | M52: 6.3 | O52: 60 | P52: 55220 | Q52: =O52^2*1.6 -> 5760 | R52: =50+10*O52 -> 650
F53: 卡拉赞精英(周1次) | G53: 40/60 | H53: 150 | I53: 30 | J53: 2.5 | L53: D1000/7 | M53: 1.2 | O53: 61 | P53: 58023 | Q53: =O53^2*1.6 -> 5953.6 | R53: =50+10*O53 -> 660
F54: 精英副本 | G54: 35 | H54: 150
F55: 公会任务(周1次) | G55: 35 | H55: 150 | I55: 10 | L55: D300 | M55: 1.8
F56: 暗夜马戏团(周1次) | G56: 50 | H56: 150 | I56: 30 | M56: 0
F57: 野外挂机/离线经验 | G57: 10 | H57: 150 | I57: 1 | J57: 1 | M57: 0 | O57: 1 | P57: 60 | Q57: =50+10*O57 -> 60
F58: 经验道具 | G58: 30 | H58: 150 | I58: 10 | M58: 0 | O58: 2 | P58: 70 | Q58: =50+10*O58 -> 70
F59: 分享 | G59: 10 | H59: 150 | I59: 5 | M59: 0 | O59: 3 | P59: 80 | Q59: =50+10*O59 -> 80
F60: 双倍点数 | G60: 20 | H60: 150 | I60: 20 | J60: 2 | L60: D475 | M60: 22.5 | O60: 4 | P60: 90 | Q60: =50+10*O60 -> 90
F61: 援助战斗和道具 | G61: 30 | H61: 150 | I61: 10 | M61: 0 | O61: 5 | P61: 100 | Q61: =50+10*O61 -> 100
F62: 古神爪牙 | G62: 25 | H62: 150 | I62: 20 | J62: 1.5 | M62: 2 | O62: 6 | P62: 110 | Q62: =50+10*O62 -> 110
F63: 屠龙 | G63: 50 | H63: 150 | I63: 20 | J63: 1.5 | M63: 0 | O63: 7 | P63: 120 | Q63: =50+10*O63 -> 120
F64: 古神 | G64: 50 | H64: 150 | I64: 40 | J64: 2 | M64: 0 | O64: 8 | P64: 130 | Q64: =50+10*O64 -> 130
F65: 艾泽拉斯地理问答 | G65: 30 | H65: 150 | I65: 30 | M65: 6.75 | O65: 9 | P65: 140 | Q65: =50+10*O65 -> 140
F66: 艾泽拉斯百科竞赛 | G66: 30 | H66: 150 | I66: 30 | M66: 6.75 | O66: 10 | P66: 150 | Q66: =50+10*O66 -> 150
F67: 职业闯关(周2次) | G67: 45 | H67: 150 | I67: 25 | J67: 2 | M67: 0
F68: 竞技场 | G68: 45 | H68: 150 | I68: 20 | M68: 0
F69: 帮派秘境(周1次) | G69: 35 | H69: 150 | I69: 20 | J69: 1.5 | M69: 0
F70: 帮派强盗(周3次) | G70: 35 | H70: 150 | I70: 10 | J70: 1.5 | M70: 0
F71: 帮派采药(周3次) | G71: 35 | H71: 150 | I71: 10 | M71: 0
F72: 节日活动 | G72: 20/40 | H72: 150 | I72: 20

Sheet 玩法行为规划
B1: 日常活动 | R1: 定时活动 | AC1: 节日活动
A2: 角色等级 | B2: 职业日常 | C2: 日常副本 | D2: 英雄试炼 | E2: 冰封王座 | F2: 考古 | G2: 运镖 | H2: 卡拉赞系列 | I2: 卡拉赞精英 | J2: 精英副本 | K2: 公会任务(周7轮) | L2: 暗夜马戏团(周20轮) | M2: 野外挂机/离线经验 | N2: 经验道具 | O2: 分享 | P2: 双倍点数 | Q2: 援助战斗和道具 | R2: 古神爪牙 | S2: 幼龙 | T2: 屠龙 | U2: 古神 | V2: 艾泽拉斯地理探索 | W2: 艾泽拉斯百科竞赛 | X2: 职业闯关(周2次) | Y2: 竞技场（周5次） | Z2: 公会副本(周1次) | AA2: 帮派强盗 | AB2: 帮派采药 | AC2: 节日活动1 | AD2: 节日活动2 | AE2: 活跃度打卡 | AF2: 剧情任务
A3: 1 | B3: =ROUND(IF(OR($A3<VLOOKUP(B$2,行为概览!$D$3:$U$33,3,0),$A3>VLOOKUP(B$2,行为概览!$D$3:$U$33,4,0)),0,VLOOKUP(B$2,行为概览!$D$3:$U$33,6,0)),4) -> 0 | C3: =ROUND(IF(OR($A3<VLOOKUP(C$2,行为概览!$D$3:$U$33,3,0),$A3>VLOOKUP(C$2,行为概览!$D$3:$U$33,4,0)),0,VLOOKUP(C$2,行为概览!$D$3:$U$33,6,0)),4) -> 0 | D3: =ROUND(IF(OR($A3<VLOOKUP(D$2,行为概览!$D$3:$U$33,3,0),$A3>VLOOKUP(D$2,行为概览!$D$3:$U$33,4,0)),0,VLOOKUP(D$2,行为概览!$D$3:$U$33,6,0)),4) -> 0 | E3: =ROUND(IF(OR($A3<VLOOKUP(E$2,行为概览!$D$3:$U$33,3,0),$A3>VLOOKUP(E$2,行为概览!$D$3:$U$33,4,0)),0,VLOOKUP(E$2,行为概览!$D$3:$U$33,6,0)),4) -> 0 | F3: =ROUND(IF(OR($A3<VLOOKUP(F$2,行为概览!$D$3:$U$33,3,0),$A3>VLOOKUP(F$2,行为概览!$D$3:$U$33,4,0)),0,VLOOKUP(F$2,行为概览!$D$3:$U$33,6,0)),4) -> 0 | G3: =ROUND(IF(OR($A3<VLOOKUP(G$2,行为概览!$D$3:$U$33,3,0),$A3>VLOOKUP(G$2,行为概览!$D$3:$U$33,4,0)),0,VLOOKUP(G$2,行为概览!$D$3:$U$33,6,0)),4) -> 0 | H3: =ROUND(IF(OR($A3<VLOOKUP(H$2,行为概览!$D$3:$U$33,3,0),$A3>VLOOKUP(H$2,行为概览!$D$3:$U$33,4,0)),0,VLOOKUP(H$2,行为概览!$D$3:$U$33,6,0)),4) -> 0 | I3: =ROUND(IF(OR($A3<VLOOKUP(I$2,行为概览!$D$3:$U$33,3,0),$A3>VLOOKUP(I$2,行为概览!$D$3:$U$33,4,0)),0,VLOOKUP(I$2,行为概览!$D$3:$U$33,6,0)),4) -> 0 | ... AF3: =ROUND(IF(OR($A3<VLOOKUP(AF$2,行为概览!$D$3:$U$33,3,0),$A3>VLOOKUP(AF$2,行为概览!$D$3:$U$33,4,0)),0,VLOOKUP(AF$2,行为概览!$D$3:$U$33,6,0)),4) -> 0
A4: 2 | B4: =ROUND(IF(OR($A4<VLOOKUP(B$2,行为概览!$D$3:$U$33,3,0),$A4>VLOOKUP(B$2,行为概览!$D$3:$U$33,4,0)),0,VLOOKUP(B$2,行为概览!$D$3:$U$33,6,0)),4) -> 0 | C4: =ROUND(IF(OR($A4<VLOOKUP(C$2,行为概览!$D$3:$U$33,3,0),$A4>VLOOKUP(C$2,行为概览!$D$3:$U$33,4,0)),0,VLOOKUP(C$2,行为概览!$D$3:$U$33,6,0)),4) -> 0 | D4: =ROUND(IF(OR($A4<VLOOKUP(D$2,行为概览!$D$3:$U$33,3,0),$A4>VLOOKUP(D$2,行为概览!$D$3:$U$33,4,0)),0,VLOOKUP(D$2,行为概览!$D$3:$U$33,6,0)),4) -> 0 | E4: =ROUND(IF(OR($A4<VLOOKUP(E$2,行为概览!$D$3:$U$33,3,0),$A4>VLOOKUP(E$2,行为概览!$D$3:$U$33,4,0)),0,VLOOKUP(E$2,行为概览!$D$3:$U$33,6,0)),4) -> 0 | F4: =ROUND(IF(OR($A4<VLOOKUP(F$2,行为概览!$D$3:$U$33,3,0),$A4>VLOOKUP(F$2,行为概览!$D$3:$U$33,4,0)),0,VLOOKUP(F$2,行为概览!$D$3:$U$33,6,0)),4) -> 0 | G4: =ROUND(IF(OR($A4<VLOOKUP(G$2,行为概览!$D$3:$U$33,3,0),$A4>VLOOKUP(G$2,行为概览!$D$3:$U$33,4,0)),0,VLOOKUP(G$2,行为概览!$D$3:$U$33,6,0)),4) -> 0 | H4: =ROUND(IF(OR($A4<VLOOKUP(H$2,行为概览!$D$3:$U$33,3,0),$A4>VLOOKUP(H$2,行为概览!$D$3:$U$33,4,0)),0,VLOOKUP(H$2,行为概览!$D$3:$U$33,6,0)),4) -> 0 | I4: =ROUND(IF(OR($A4<VLOOKUP(I$2,行为概览!$D$3:$U$33,3,0),$A4>VLOOKUP(I$2,行为概览!$D$3:$U$33,4,0)),0,VLOOKUP(I$2,行为概览!$D$3:$U$33,6,0)),4) -> 0 | ... AF4: =ROUND(IF(OR($A4<VLOOKUP(AF$2,行为概览!$D$3:$U$33,3,0),$A4>VLOOKUP(AF$2,行为概览!$D$3:$U$33,4,0)),0,VLOOKUP(AF$2,行为概览!$D$3:$U$33,6,0)),4) -> 0
A5: 3 | B5: =ROUND(IF(OR($A5<VLOOKUP(B$2,行为概览!$D$3:$U$33,3,0),$A5>VLOOKUP(B$2,行为概览!$D$3:$U$33,4,0)),0,VLOOKUP(B$2,行为概览!$D$3:$U$33,6,0)),4) -> 0 | C5: =ROUND(IF(OR($A5<VLOOKUP(C$2,行为概览!$D$3:$U$33,3,0),$A5>VLOOKUP(C$2,行为概览!$D$3:$U$33,4,0)),0,VLOOKUP(C$2,行为概览!$D$3:$U$33,6,0)),4) -> 0 | D5: =ROUND(IF(OR($A5<VLOOKUP(D$2,行为概览!$D$3:$U$33,3,0),$A5>VLOOKUP(D$2,行为概览!$D$3:$U$33,4,0)),0,VLOOKUP(D$2,行为概览!$D$3:$U$33,6,0)),4) -> 0 | E5: =ROUND(IF(OR($A5<VLOOKUP(E$2,行为概览!$D$3:$U$33,3,0),$A5>VLOOKUP(E$2,行为概览!$D$3:$U$33,4,0)),0,VLOOKUP(E$2,行为概览!$D$3:$U$33,6,0)),4) -> 0 | F5: =ROUND(IF(OR($A5<VLOOKUP(F$2,行为概览!$D$3:$U$33,3,0),$A5>VLOOKUP(F$2,行为概览!$D$3:$U$33,4,0)),0,VLOOKUP(F$2,行为概览!$D$3:$U$33,6,0)),4) -> 0 | G5: =ROUND(IF(OR($A5<VLOOKUP(G$2,行为概览!$D$3:$U$33,3,0),$A5>VLOOKUP(G$2,行为概览!$D$3:$U$33,4,0)),0,VLOOKUP(G$2,行为概览!$D$3:$U$33,6,0)),4) -> 0 | H5: =ROUND(IF(OR($A5<VLOOKUP(H$2,行为概览!$D$3:$U$33,3,0),$A5>VLOOKUP(H$2,行为概览!$D$3:$U$33,4,0)),0,VLOOKUP(H$2,行为概览!$D$3:$U$33,6,0)),4) -> 0 | I5: =ROUND(IF(OR($A5<VLOOKUP(I$2,行为概览!$D$3:$U$33,3,0),$A5>VLOOKUP(I$2,行为概览!$D$3:$U$33,4,0)),0,VLOOKUP(I$2,行为概览!$D$3:$U$33,6,0)),4) -> 0 | ... AF5: =ROUND(IF(OR($A5<VLOOKUP(AF$2,行为概览!$D$3:$U$33,3,0),$A5>VLOOKUP(AF$2,行为概览!$D$3:$U$33,4,0)),0,VLOOKUP(AF$2,行为概览!$D$3:$U$33,6,0)),4) -> 0
A6: 4 | B6: =ROUND(IF(OR($A6<VLOOKUP(B$2,行为概览!$D$3:$U$33,3,0),$A6>VLOOKUP(B$2,行为概览!$D$3:$U$33,4,0)),0,VLOOKUP(B$2,行为概览!$D$3:$U$33,6,0)),4) -> 0 | C6: =ROUND(IF(OR($A6<VLOOKUP(C$2,行为概览!$D$3:$U$33,3,0),$A6>VLOOKUP(C$2,行为概览!$D$3:$U$33,4,0)),0,VLOOKUP(C$2,行为概览!$D$3:$U$33,6,0)),4) -> 0 | D6: =ROUND(IF(OR($A6<VLOOKUP(D$2,行为概览!$D$3:$U$33,3,0),$A6>VLOOKUP(D$2,行为概览!$D$3:$U$33,4,0)),0,VLOOKUP(D$2,行为概览!$D$3:$U$33,6,0)),4) -> 0 | E6: =ROUND(IF(OR($A6<VLOOKUP(E$2,行为概览!$D$3:$U$33,3,0),$A6>VLOOKUP(E$2,行为概览!$D$3:$U$33,4,0)),0,VLOOKUP(E$2,行为概览!$D$3:$U$33,6,0)),4) -> 0 | F6: =ROUND(IF(OR($A6<VLOOKUP(F$2,行为概览!$D$3:$U$33,3,0),$A6>VLOOKUP(F$2,行为概览!$D$3:$U$33,4,0)),0,VLOOKUP(F$2,行为概览!$D$3:$U$33,6,0)),4) -> 0 | G6: =ROUND(IF(OR($A6<VLOOKUP(G$2,行为概览!$D$3:$U$33,3,0),$A6>VLOOKUP(G$2,行为概览!$D$3:$U$33,4,0)),0,VLOOKUP(G$2,行为概览!$D$3:$U$33,6,0)),4) -> 0 | H6: =ROUND(IF(OR($A6<VLOOKUP(H$2,行为概览!$D$3:$U$33,3,0),$A6>VLOOKUP(H$2,行为概览!$D$3:$U$33,4,0)),0,VLOOKUP(H$2,行为概览!$D$3:$U$33,6,0)),4) -> 0 | I6: =ROUND(IF(OR($A6<VLOOKUP(I$2,行为概览!$D$3:$U$33,3,0),$A6>VLOOKUP(I$2,行为概览!$D$3:$U$33,4,0)),0,VLOOKUP(I$2,行为概览!$D$3:$U$33,6,0)),4) -> 0 | ... AF6: =ROUND(IF(OR($A6<VLOOKUP(AF$2,行为概览!$D$3:$U$33,3,0),$A6>VLOOKUP(AF$2,行为概览!$D$3:$U$33,4,0)),0,VLOOKUP(AF$2,行为概览!$D$3:$U$33,6,0)),4) -> 0
A7: 5 | B7: =ROUND(IF(OR($A7<VLOOKUP(B$2,行为概览!$D$3:$U$33,3,0),$A7>VLOOKUP(B$2,行为概览!$D$3:$U$33,4,0)),0,VLOOKUP(B$2,行为概览!$D$3:$U$33,6,0)),4) -> 0 | C7: =ROUND(IF(OR($A7<VLOOKUP(C$2,行为概览!$D$3:$U$33,3,0),$A7>VLOOKUP(C$2,行为概览!$D$3:$U$33,4,0)),0,VLOOKUP(C$2,行为概览!$D$3:$U$33,6,0)),4) -> 0 | D7: =ROUND(IF(OR($A7<VLOOKUP(D$2,行为概览!$D$3:$U$33,3,0),$A7>VLOOKUP(D$2,行为概览!$D$3:$U$33,4,0)),0,VLOOKUP(D$2,行为概览!$D$3:$U$33,6,0)),4) -> 0 | E7: =ROUND(IF(OR($A7<VLOOKUP(E$2,行为概览!$D$3:$U$33,3,0),$A7>VLOOKUP(E$2,行为概览!$D$3:$U$33,4,0)),0,VLOOKUP(E$2,行为概览!$D$3:$U$33,6,0)),4) -> 0 | F7: =ROUND(IF(OR($A7<VLOOKUP(F$2,行为概览!$D$3:$U$33,3,0),$A7>VLOOKUP(F$2,行为概览!$D$3:$U$33,4,0)),0,VLOOKUP(F$2,行为概览!$D$3:$U$33,6,0)),4) -> 0 | G7: =ROUND(IF(OR($A7<VLOOKUP(G$2,行为概览!$D$3:$U$33,3,0),$A7>VLOOKUP(G$2,行为概览!$D$3:$U$33,4,0)),0,VLOOKUP(G$2,行为概览!$D$3:$U$33,6,0)),4) -> 0 | H7: =ROUND(IF(OR($A7<VLOOKUP(H$2,行为概览!$D$3:$U$33,3,0),$A7>VLOOKUP(H$2,行为概览!$D$3:$U$33,4,0)),0,VLOOKUP(H$2,行为概览!$D$3:$U$33,6,0)),4) -> 0 | I7: =ROUND(IF(OR($A7<VLOOKUP(I$2,行为概览!$D$3:$U$33,3,0),$A7>VLOOKUP(I$2,行为概览!$D$3:$U$33,4,0)),0,VLOOKUP(I$2,行为概览!$D$3:$U$33,6,0)),4) -> 0 | ... AF7: =ROUND(IF(OR($A7<VLOOKUP(AF$2,行为概览!$D$3:$U$33,3,0),$A7>VLOOKUP(AF$2,行为概览!$D$3:$U$33,4,0)),0,VLOOKUP(AF$2,行为概览!$D$3:$U$33,6,0)),4) -> 0
A8: 6 | B8: =ROUND(IF(OR($A8<VLOOKUP(B$2,行为概览!$D$3:$U$33,3,0),$A8>VLOOKUP(B$2,行为概览!$D$3:$U$33,4,0)),0,VLOOKUP(B$2,行为概览!$D$3:$U$33,6,0)),4) -> 0 | C8: =ROUND(IF(OR($A8<VLOOKUP(C$2,行为概览!$D$3:$U$33,3,0),$A8>VLOOKUP(C$2,行为概览!$D$3:$U$33,4,0)),0,VLOOKUP(C$2,行为概览!$D$3:$U$33,6,0)),4) -> 0 | D8: =ROUND(IF(OR($A8<VLOOKUP(D$2,行为概览!$D$3:$U$33,3,0),$A8>VLOOKUP(D$2,行为概览!$D$3:$U$33,4,0)),0,VLOOKUP(D$2,行为概览!$D$3:$U$33,6,0)),4) -> 0 | E8: =ROUND(IF(OR($A8<VLOOKUP(E$2,行为概览!$D$3:$U$33,3,0),$A8>VLOOKUP(E$2,行为概览!$D$3:$U$33,4,0)),0,VLOOKUP(E$2,行为概览!$D$3:$U$33,6,0)),4) -> 0 | F8: =ROUND(IF(OR($A8<VLOOKUP(F$2,行为概览!$D$3:$U$33,3,0),$A8>VLOOKUP(F$2,行为概览!$D$3:$U$33,4,0)),0,VLOOKUP(F$2,行为概览!$D$3:$U$33,6,0)),4) -> 0 | G8: =ROUND(IF(OR($A8<VLOOKUP(G$2,行为概览!$D$3:$U$33,3,0),$A8>VLOOKUP(G$2,行为概览!$D$3:$U$33,4,0)),0,VLOOKUP(G$2,行为概览!$D$3:$U$33,6,0)),4) -> 0 | H8: =ROUND(IF(OR($A8<VLOOKUP(H$2,行为概览!$D$3:$U$33,3,0),$A8>VLOOKUP(H$2,行为概览!$D$3:$U$33,4,0)),0,VLOOKUP(H$2,行为概览!$D$3:$U$33,6,0)),4) -> 0 | I8: =ROUND(IF(OR($A8<VLOOKUP(I$2,行为概览!$D$3:$U$33,3,0),$A8>VLOOKUP(I$2,行为概览!$D$3:$U$33,4,0)),0,VLOOKUP(I$2,行为概览!$D$3:$U$33,6,0)),4) -> 0 | ... AF8: =ROUND(IF(OR($A8<VLOOKUP(AF$2,行为概览!$D$3:$U$33,3,0),$A8>VLOOKUP(AF$2,行为概览!$D$3:$U$33,4,0)),0,VLOOKUP(AF$2,行为概览!$D$3:$U$33,6,0)),4) -> 0
A9: 7 | B9: =ROUND(IF(OR($A9<VLOOKUP(B$2,行为概览!$D$3:$U$33,3,0),$A9>VLOOKUP(B$2,行为概览!$D$3:$U$33,4,0)),0,VLOOKUP(B$2,行为概览!$D$3:$U$33,6,0)),4) -> 0 | C9: =ROUND(IF(OR($A9<VLOOKUP(C$2,行为概览!$D$3:$U$33,3,0),$A9>VLOOKUP(C$2,行为概览!$D$3:$U$33,4,0)),0,VLOOKUP(C$2,行为概览!$D$3:$U$33,6,0)),4) -> 0 | D9: =ROUND(IF(OR($A9<VLOOKUP(D$2,行为概览!$D$3:$U$33,3,0),$A9>VLOOKUP(D$2,行为概览!$D$3:$U$33,4,0)),0,VLOOKUP(D$2,行为概览!$D$3:$U$33,6,0)),4) -> 0 | E9: =ROUND(IF(OR($A9<VLOOKUP(E$2,行为概览!$D$3:$U$33,3,0),$A9>VLOOKUP(E$2,行为概览!$D$3:$U$33,4,0)),0,VLOOKUP(E$2,行为概览!$D$3:$U$33,6,0)),4) -> 0 | F9: =ROUND(IF(OR($A9<VLOOKUP(F$2,行为概览!$D$3:$U$33,3,0),$A9>VLOOKUP(F$2,行为概览!$D$3:$U$33,4,0)),0,VLOOKUP(F$2,行为概览!$D$3:$U$33,6,0)),4) -> 0 | G9: =ROUND(IF(OR($A9<VLOOKUP(G$2,行为概览!$D$3:$U$33,3,0),$A9>VLOOKUP(G$2,行为概览!$D$3:$U$33,4,0)),0,VLOOKUP(G$2,行为概览!$D$3:$U$33,6,0)),4) -> 0 | H9: =ROUND(IF(OR($A9<VLOOKUP(H$2,行为概览!$D$3:$U$33,3,0),$A9>VLOOKUP(H$2,行为概览!$D$3:$U$33,4,0)),0,VLOOKUP(H$2,行为概览!$D$3:$U$33,6,0)),4) -> 0 | I9: =ROUND(IF(OR($A9<VLOOKUP(I$2,行为概览!$D$3:$U$33,3,0),$A9>VLOOKUP(I$2,行为概览!$D$3:$U$33,4,0)),0,VLOOKUP(I$2,行为概览!$D$3:$U$33,6,0)),4) -> 0 | ... AF9: =ROUND(IF(OR($A9<VLOOKUP(AF$2,行为概览!$D$3:$U$33,3,0),$A9>VLOOKUP(AF$2,行为概览!$D$3:$U$33,4,0)),0,VLOOKUP(AF$2,行为概览!$D$3:$U$33,6,0)),4) -> 0
A10: 8 | B10: =ROUND(IF(OR($A10<VLOOKUP(B$2,行为概览!$D$3:$U$33,3,0),$A10>VLOOKUP(B$2,行为概览!$D$3:$U$33,4,0)),0,VLOOKUP(B$2,行为概览!$D$3:$U$33,6,0)),4) -> 0 | C10: =ROUND(IF(OR($A10<VLOOKUP(C$2,行为概览!$D$3:$U$33,3,0),$A10>VLOOKUP(C$2,行为概览!$D$3:$U$33,4,0)),0,VLOOKUP(C$2,行为概览!$D$3:$U$33,6,0)),4) -> 0 | D10: =ROUND(IF(OR($A10<VLOOKUP(D$2,行为概览!$D$3:$U$33,3,0),$A10>VLOOKUP(D$2,行为概览!$D$3:$U$33,4,0)),0,VLOOKUP(D$2,行为概览!$D$3:$U$33,6,0)),4) -> 0 | E10: =ROUND(IF(OR($A10<VLOOKUP(E$2,行为概览!$D$3:$U$33,3,0),$A10>VLOOKUP(E$2,行为概览!$D$3:$U$33,4,0)),0,VLOOKUP(E$2,行为概览!$D$3:$U$33,6,0)),4) -> 0 | F10: =ROUND(IF(OR($A10<VLOOKUP(F$2,行为概览!$D$3:$U$33,3,0),$A10>VLOOKUP(F$2,行为概览!$D$3:$U$33,4,0)),0,VLOOKUP(F$2,行为概览!$D$3:$U$33,6,0)),4) -> 0 | G10: =ROUND(IF(OR($A10<VLOOKUP(G$2,行为概览!$D$3:$U$33,3,0),$A10>VLOOKUP(G$2,行为概览!$D$3:$U$33,4,0)),0,VLOOKUP(G$2,行为概览!$D$3:$U$33,6,0)),4) -> 0 | H10: =ROUND(IF(OR($A10<VLOOKUP(H$2,行为概览!$D$3:$U$33,3,0),$A10>VLOOKUP(H$2,行为概览!$D$3:$U$33,4,0)),0,VLOOKUP(H$2,行为概览!$D$3:$U$33,6,0)),4) -> 0 | I10: =ROUND(IF(OR($A10<VLOOKUP(I$2,行为概览!$D$3:$U$33,3,0),$A10>VLOOKUP(I$2,行为概览!$D$3:$U$33,4,0)),0,VLOOKUP(I$2,行为概览!$D$3:$U$33,6,0)),4) -> 0 | ... AF10: =ROUND(IF(OR($A10<VLOOKUP(AF$2,行为概览!$D$3:$U$33,3,0),$A10>VLOOKUP(AF$2,行为概览!$D$3:$U$33,4,0)),0,VLOOKUP(AF$2,行为概览!$D$3:$U$33,6,0)),4) -> 0
A11: 9 | B11: =ROUND(IF(OR($A11<VLOOKUP(B$2,行为概览!$D$3:$U$33,3,0),$A11>VLOOKUP(B$2,行为概览!$D$3:$U$33,4,0)),0,VLOOKUP(B$2,行为概览!$D$3:$U$33,6,0)),4) -> 0 | C11: =ROUND(IF(OR($A11<VLOOKUP(C$2,行为概览!$D$3:$U$33,3,0),$A11>VLOOKUP(C$2,行为概览!$D$3:$U$33,4,0)),0,VLOOKUP(C$2,行为概览!$D$3:$U$33,6,0)),4) -> 0 | D11: =ROUND(IF(OR($A11<VLOOKUP(D$2,行为概览!$D$3:$U$33,3,0),$A11>VLOOKUP(D$2,行为概览!$D$3:$U$33,4,0)),0,VLOOKUP(D$2,行为概览!$D$3:$U$33,6,0)),4) -> 0 | E11: =ROUND(IF(OR($A11<VLOOKUP(E$2,行为概览!$D$3:$U$33,3,0),$A11>VLOOKUP(E$2,行为概览!$D$3:$U$33,4,0)),0,VLOOKUP(E$2,行为概览!$D$3:$U$33,6,0)),4) -> 0 | F11: =ROUND(IF(OR($A11<VLOOKUP(F$2,行为概览!$D$3:$U$33,3,0),$A11>VLOOKUP(F$2,行为概览!$D$3:$U$33,4,0)),0,VLOOKUP(F$2,行为概览!$D$3:$U$33,6,0)),4) -> 0 | G11: =ROUND(IF(OR($A11<VLOOKUP(G$2,行为概览!$D$3:$U$33,3,0),$A11>VLOOKUP(G$2,行为概览!$D$3:$U$33,4,0)),0,VLOOKUP(G$2,行为概览!$D$3:$U$33,6,0)),4) -> 0 | H11: =ROUND(IF(OR($A11<VLOOKUP(H$2,行为概览!$D$3:$U$33,3,0),$A11>VLOOKUP(H$2,行为概览!$D$3:$U$33,4,0)),0,VLOOKUP(H$2,行为概览!$D$3:$U$33,6,0)),4) -> 0 | I11: =ROUND(IF(OR($A11<VLOOKUP(I$2,行为概览!$D$3:$U$33,3,0),$A11>VLOOKUP(I$2,行为概览!$D$3:$U$33,4,0)),0,VLOOKUP(I$2,行为概览!$D$3:$U$33,6,0)),4) -> 0 | ... AF11: =ROUND(IF(OR($A11<VLOOKUP(AF$2,行为概览!$D$3:$U$33,3,0),$A11>VLOOKUP(AF$2,行为概览!$D$3:$U$33,4,0)),0,VLOOKUP(AF$2,行为概览!$D$3:$U$33,6,0)),4) -> 0
A12: 10 | B12: =ROUND(IF(OR($A12<VLOOKUP(B$2,行为概览!$D$3:$U$33,3,0),$A12>VLOOKUP(B$2,行为概览!$D$3:$U$33,4,0)),0,VLOOKUP(B$2,行为概览!$D$3:$U$33,6,0)),4) -> 0 | C12: =ROUND(IF(OR($A12<VLOOKUP(C$2,行为概览!$D$3:$U$33,3,0),$A12>VLOOKUP(C$2,行为概览!$D$3:$U$33,4,0)),0,VLOOKUP(C$2,行为概览!$D$3:$U$33,6,0)),4) -> 0 | D12: =ROUND(IF(OR($A12<VLOOKUP(D$2,行为概览!$D$3:$U$33,3,0),$A12>VLOOKUP(D$2,行为概览!$D$3:$U$33,4,0)),0,VLOOKUP(D$2,行为概览!$D$3:$U$33,6,0)),4) -> 0 | E12: =ROUND(IF(OR($A12<VLOOKUP(E$2,行为概览!$D$3:$U$33,3,0),$A12>VLOOKUP(E$2,行为概览!$D$3:$U$33,4,0)),0,VLOOKUP(E$2,行为概览!$D$3:$U$33,6,0)),4) -> 0 | F12: =ROUND(IF(OR($A12<VLOOKUP(F$2,行为概览!$D$3:$U$33,3,0),$A12>VLOOKUP(F$2,行为概览!$D$3:$U$33,4,0)),0,VLOOKUP(F$2,行为概览!$D$3:$U$33,6,0)),4) -> 0 | G12: =ROUND(IF(OR($A12<VLOOKUP(G$2,行为概览!$D$3:$U$33,3,0),$A12>VLOOKUP(G$2,行为概览!$D$3:$U$33,4,0)),0,VLOOKUP(G$2,行为概览!$D$3:$U$33,6,0)),4) -> 0 | H12: =ROUND(IF(OR($A12<VLOOKUP(H$2,行为概览!$D$3:$U$33,3,0),$A12>VLOOKUP(H$2,行为概览!$D$3:$U$33,4,0)),0,VLOOKUP(H$2,行为概览!$D$3:$U$33,6,0)),4) -> 0 | I12: =ROUND(IF(OR($A12<VLOOKUP(I$2,行为概览!$D$3:$U$33,3,0),$A12>VLOOKUP(I$2,行为概览!$D$3:$U$33,4,0)),0,VLOOKUP(I$2,行为概览!$D$3:$U$33,6,0)),4) -> 0 | ... AF12: =ROUND(IF(OR($A12<VLOOKUP(AF$2,行为概览!$D$3:$U$33,3,0),$A12>VLOOKUP(AF$2,行为概览!$D$3:$U$33,4,0)),0,VLOOKUP(AF$2,行为概览!$D$3:$U$33,6,0)),4) -> 0
A13: 11 | B13: =ROUND(IF(OR($A13<VLOOKUP(B$2,行为概览!$D$3:$U$33,3,0),$A13>VLOOKUP(B$2,行为概览!$D$3:$U$33,4,0)),0,VLOOKUP(B$2,行为概览!$D$3:$U$33,6,0)),4) -> 0 | C13: =ROUND(IF(OR($A13<VLOOKUP(C$2,行为概览!$D$3:$U$33,3,0),$A13>VLOOKUP(C$2,行为概览!$D$3:$U$33,4,0)),0,VLOOKUP(C$2,行为概览!$D$3:$U$33,6,0)),4) -> 0 | D13: =ROUND(IF(OR($A13<VLOOKUP(D$2,行为概览!$D$3:$U$33,3,0),$A13>VLOOKUP(D$2,行为概览!$D$3:$U$33,4,0)),0,VLOOKUP(D$2,行为概览!$D$3:$U$33,6,0)),4) -> 0 | E13: =ROUND(IF(OR($A13<VLOOKUP(E$2,行为概览!$D$3:$U$33,3,0),$A13>VLOOKUP(E$2,行为概览!$D$3:$U$33,4,0)),0,VLOOKUP(E$2,行为概览!$D$3:$U$33,6,0)),4) -> 0 | F13: =ROUND(IF(OR($A13<VLOOKUP(F$2,行为概览!$D$3:$U$33,3,0),$A13>VLOOKUP(F$2,行为概览!$D$3:$U$33,4,0)),0,VLOOKUP(F$2,行为概览!$D$3:$U$33,6,0)),4) -> 0 | G13: =ROUND(IF(OR($A13<VLOOKUP(G$2,行为概览!$D$3:$U$33,3,0),$A13>VLOOKUP(G$2,行为概览!$D$3:$U$33,4,0)),0,VLOOKUP(G$2,行为概览!$D$3:$U$33,6,0)),4) -> 0 | H13: =ROUND(IF(OR($A13<VLOOKUP(H$2,行为概览!$D$3:$U$33,3,0),$A13>VLOOKUP(H$2,行为概览!$D$3:$U$33,4,0)),0,VLOOKUP(H$2,行为概览!$D$3:$U$33,6,0)),4) -> 0 | I13: =ROUND(IF(OR($A13<VLOOKUP(I$2,行为概览!$D$3:$U$33,3,0),$A13>VLOOKUP(I$2,行为概览!$D$3:$U$33,4,0)),0,VLOOKUP(I$2,行为概览!$D$3:$U$33,6,0)),4) -> 0 | ... AF13: =ROUND(IF(OR($A13<VLOOKUP(AF$2,行为概览!$D$3:$U$33,3,0),$A13>VLOOKUP(AF$2,行为概览!$D$3:$U$33,4,0)),0,VLOOKUP(AF$2,行为概览!$D$3:$U$33,6,0)),4) -> 0
A14: 12 | B14: =ROUND(IF(OR($A14<VLOOKUP(B$2,行为概览!$D$3:$U$33,3,0),$A14>VLOOKUP(B$2,行为概览!$D$3:$U$33,4,0)),0,VLOOKUP(B$2,行为概览!$D$3:$U$33,6,0)),4) -> 0 | C14: =ROUND(IF(OR($A14<VLOOKUP(C$2,行为概览!$D$3:$U$33,3,0),$A14>VLOOKUP(C$2,行为概览!$D$3:$U$33,4,0)),0,VLOOKUP(C$2,行为概览!$D$3:$U$33,6,0)),4) -> 0 | D14: =ROUND(IF(OR($A14<VLOOKUP(D$2,行为概览!$D$3:$U$33,3,0),$A14>VLOOKUP(D$2,行为概览!$D$3:$U$33,4,0)),0,VLOOKUP(D$2,行为概览!$D$3:$U$33,6,0)),4) -> 0 | E14: =ROUND(IF(OR($A14<VLOOKUP(E$2,行为概览!$D$3:$U$33,3,0),$A14>VLOOKUP(E$2,行为概览!$D$3:$U$33,4,0)),0,VLOOKUP(E$2,行为概览!$D$3:$U$33,6,0)),4) -> 0 | F14: =ROUND(IF(OR($A14<VLOOKUP(F$2,行为概览!$D$3:$U$33,3,0),$A14>VLOOKUP(F$2,行为概览!$D$3:$U$33,4,0)),0,VLOOKUP(F$2,行为概览!$D$3:$U$33,6,0)),4) -> 0 | G14: =ROUND(IF(OR($A14<VLOOKUP(G$2,行为概览!$D$3:$U$33,3,0),$A14>VLOOKUP(G$2,行为概览!$D$3:$U$33,4,0)),0,VLOOKUP(G$2,行为概览!$D$3:$U$33,6,0)),4) -> 0 | H14: =ROUND(IF(OR($A14<VLOOKUP(H$2,行为概览!$D$3:$U$33,3,0),$A14>VLOOKUP(H$2,行为概览!$D$3:$U$33,4,0)),0,VLOOKUP(H$2,行为概览!$D$3:$U$33,6,0)),4) -> 0 | I14: =ROUND(IF(OR($A14<VLOOKUP(I$2,行为概览!$D$3:$U$33,3,0),$A14>VLOOKUP(I$2,行为概览!$D$3:$U$33,4,0)),0,VLOOKUP(I$2,行为概览!$D$3:$U$33,6,0)),4) -> 0 | ... AF14: =ROUND(IF(OR($A14<VLOOKUP(AF$2,行为概览!$D$3:$U$33,3,0),$A14>VLOOKUP(AF$2,行为概览!$D$3:$U$33,4,0)),0,VLOOKUP(AF$2,行为概览!$D$3:$U$33,6,0)),4) -> 0
... A152: 150 | B152: =ROUND(IF(OR($A152<VLOOKUP(B$2,行为概览!$D$3:$U$33,3,0),$A152>VLOOKUP(B$2,行为概览!$D$3:$U$33,4,0)),0,VLOOKUP(B$2,行为概览!$D$3:$U$33,6,0)),4) -> 0.3333 | C152: =ROUND(IF(OR($A152<VLOOKUP(C$2,行为概览!$D$3:$U$33,3,0),$A152>VLOOKUP(C$2,行为概览!$D$3:$U$33,4,0)),0,VLOOKUP(C$2,行为概览!$D$3:$U$33,6,0)),4) -> 2 | D152: =ROUND(IF(OR($A152<VLOOKUP(D$2,行为概览!$D$3:$U$33,3,0),$A152>VLOOKUP(D$2,行为概览!$D$3:$U$33,4,0)),0,VLOOKUP(D$2,行为概览!$D$3:$U$33,6,0)),4) -> 0.0833 | E152: =ROUND(IF(OR($A152<VLOOKUP(E$2,行为概览!$D$3:$U$33,3,0),$A152>VLOOKUP(E$2,行为概览!$D$3:$U$33,4,0)),0,VLOOKUP(E$2,行为概览!$D$3:$U$33,6,0)),4) -> 1 | F152: =ROUND(IF(OR($A152<VLOOKUP(F$2,行为概览!$D$3:$U$33,3,0),$A152>VLOOKUP(F$2,行为概览!$D$3:$U$33,4,0)),0,VLOOKUP(F$2,行为概览!$D$3:$U$33,6,0)),4) -> 0.3333 | G152: =ROUND(IF(OR($A152<VLOOKUP(G$2,行为概览!$D$3:$U$33,3,0),$A152>VLOOKUP(G$2,行为概览!$D$3:$U$33,4,0)),0,VLOOKUP(G$2,行为概览!$D$3:$U$33,6,0)),4) -> 0 | H152: =ROUND(IF(OR($A152<VLOOKUP(H$2,行为概览!$D$3:$U$33,3,0),$A152>VLOOKUP(H$2,行为概览!$D$3:$U$33,4,0)),0,VLOOKUP(H$2,行为概览!$D$3:$U$33,6,0)),4) -> 0 | I152: =ROUND(IF(OR($A152<VLOOKUP(I$2,行为概览!$D$3:$U$33,3,0),$A152>VLOOKUP(I$2,行为概览!$D$3:$U$33,4,0)),0,VLOOKUP(I$2,行为概览!$D$3:$U$33,6,0)),4) -> 0 | ... AF152: =ROUND(IF(OR($A152<VLOOKUP(AF$2,行为概览!$D$3:$U$33,3,0),$A152>VLOOKUP(AF$2,行为概览!$D$3:$U$33,4,0)),0,VLOOKUP(AF$2,行为概览!$D$3:$U$33,6,0)),4) -> 0

Sheet 升级节奏
C1: 主角
B2: 等级 | C2: 基准效率1小时获得经验(h) | D2: 基准效率1小时获得宠物经验(h) | E2: 基准权重银币 | F2: 基准权重金币 | G2: 停留时间(d) | H2: 累计时间(d) | I2: 手调系数 | J2: 公会资金 | L2: 服务器等级天数 | M2: 持续天数
B3: 1 | C3: =400*B3 -> 400 | D3: =5000*B3 -> 5000 | E3: =1000*B3 -> 1000 | F3: =1*B3 -> 1 | G3: =0.2*(1+0.01*B3^2)/24*I3 -> 0 | H3: =SUM($G$3:G3) -> 0 | I3: 0 | J3: =2500+50*B3 -> 2550 | M3: =IF(L3="","",1)
B4: 2 | C4: =400*B4 -> 800 | D4: =5000*B4 -> 10000 | E4: =1000*B4 -> 2000 | F4: =1*B4 -> 2 | G4: =0.2*(1+0.01*B4^2)/24*I4 -> 0 | H4: =SUM($G$3:G4) -> 0 | I4: 0 | J4: =2500+50*B4 -> 2600 | M4: =IF(L4="","",1)
B5: 3 | C5: =400*B5 -> 1200 | D5: =5000*B5 -> 15000 | E5: =1000*B5 -> 3000 | F5: =1*B5 -> 3 | G5: =0.2*(1+0.01*B5^2)/24*I5 -> 0 | H5: =SUM($G$3:G5) -> 0 | I5: 0 | J5: =2500+50*B5 -> 2650 | M5: =IF(L5="","",1)
B6: 4 | C6: =400*B6 -> 1600 | D6: =5000*B6 -> 20000 | E6: =1000*B6 -> 4000 | F6: =1*B6 -> 4 | G6: =0.2*(1+0.01*B6^2)/24*I6 -> 0 | H6: =SUM($G$3:G6) -> 0 | I6: 0 | J6: =2500+50*B6 -> 2700 | M6: =IF(L6="","",1)
B7: 5 | C7: =400*B7 -> 2000 | D7: =5000*B7 -> 25000 | E7: =1000*B7 -> 5000 | F7: =1*B7 -> 5 | G7: =0.2*(1+0.01*B7^2)/24*I7 -> 0 | H7: =SUM($G$3:G7) -> 0 | I7: 0 | J7: =2500+50*B7 -> 2750 | M7: =IF(L7="","",1)
B8: 6 | C8: =400*B8 -> 2400 | D8: =5000*B8 -> 30000 | E8: =1000*B8 -> 6000 | F8: =1*B8 -> 6 | G8: =0.2*(1+0.01*B8^2)/24*I8 -> 0 | H8: =SUM($G$3:G8) -> 0 | I8: 0 | J8: =2500+50*B8 -> 2800 | M8: =IF(L8="","",1)
B9: 7 | C9: =400*B9 -> 2800 | D9: =5000*B9 -> 35000 | E9: =1000*B9 -> 7000 | F9: =1*B9 -> 7 | G9: =0.2*(1+0.01*B9^2)/24*I9 -> 0 | H9: =SUM($G$3:G9) -> 0 | I9: 0 | J9: =2500+50*B9 -> 2850 | M9: =IF(L9="","",1)
B10: 8 | C10: =400*B10 -> 3200 | D10: =5000*B10 -> 40000 | E10: =1000*B10 -> 8000 | F10: =1*B10 -> 8 | G10: =0.2*(1+0.01*B10^2)/24*I10 -> 0 | H10: =SUM($G$3:G10) -> 0 | I10: 0 | J10: =2500+50*B10 -> 2900 | M10: =IF(L10="","",1)
B11: 9 | C11: =400*B11 -> 3600 | D11: =5000*B11 -> 45000 | E11: =1000*B11 -> 9000 | F11: =1*B11 -> 9 | G11: =0.2*(1+0.01*B11^2)/24*I11 -> 0 | H11: =SUM($G$3:G11) -> 0 | I11: 0 | J11: =2500+50*B11 -> 2950 | M11: =IF(L11="","",1)
B12: 10 | C12: =400*B12 -> 4000 | D12: =5000*B12 -> 50000 | E12: =1000*B12 -> 10000 | F12: =1*B12 -> 10 | G12: =0.2*(1+0.01*B12^2)/24*I12 -> 0 | H12: =SUM($G$3:G12) -> 0 | I12: 0 | J12: =2500+50*B12 -> 3000 | M12: =IF(L12="","",1)
B13: 11 | C13: =400*B13 -> 4400 | D13: =5000*B13 -> 55000 | E13: =1000*B13 -> 11000 | F13: =1*B13 -> 11 | G13: =0.2*(1+0.01*B13^2)/24*I13 -> 0 | H13: =SUM($G$3:G13) -> 0 | I13: 0 | J13: =2500+50*B13 -> 3050 | M13: =IF(L13="","",1)
B14: 12 | C14: =400*B14 -> 4800 | D14: =5000*B14 -> 60000 | E14: =1000*B14 -> 12000 | F14: =1*B14 -> 12 | G14: =0.2*(1+0.01*B14^2)/24*I14 -> 0 | H14: =SUM($G$3:G14) -> 0 | I14: 0 | J14: =2500+50*B14 -> 3100 | M14: =IF(L14="","",1)
... B39: 37 | C39: =400*B39 -> 14800 | D39: =5000*B39 -> 185000 | E39: =1000*B39 -> 37000 | F39: =1*B39 -> 37 | G39: =0.2*(1+0.01*B39^2)/24*I39 -> 0.13465833 | H39: =SUM($G$3:G39) -> 0.93738333 | I39: 1.1 | J39: =2500+50*B39 -> 4350 | M39: =IF(L39="","",1)
B40: 38 | C40: =400*B40 -> 15200 | D40: =5000*B40 -> 190000 | E40: =1000*B40 -> 38000 | F40: =1*B40 -> 38 | G40: =0.2*(1+0.01*B40^2)/24*I40 -> 0.14153333 | H40: =SUM($G$3:G40) -> 1.0789167 | I40: 1.1 | J40: =2500+50*B40 -> 4400 | K40: =ROUNDUP(H39,0) -> 1 | M40: =IF(L40="","",1)
B41: 39 | C41: =400*B41 -> 15600 | D41: =5000*B41 -> 195000 | E41: =1000*B41 -> 39000 | F41: =1*B41 -> 39 | G41: =0.2*(1+0.01*B41^2)/24*I41 -> 0.17560833 | H41: =SUM($G$3:G41) -> 1.254525 | I41: 1.3 | J41: =2500+50*B41 -> 4450 | L41: 1 | M41: =IF(L41="","",1) -> 1
B42: 40 | C42: =400*B42 -> 16000 | D42: =5000*B42 -> 200000 | E42: =1000*B42 -> 40000 | F42: =1*B42 -> 40 | G42: =0.2*(1+0.01*B42^2)/24*I42 -> 0.18416667 | H42: =SUM($G$3:G42) -> 1.4386917 | I42: 1.3 | J42: =2500+50*B42 -> 4500 | M42: =IF(L42="","",1)
B43: 41 | C43: =400*B43 -> 16400 | D43: =5000*B43 -> 205000 | E43: =1000*B43 -> 41000 | F43: =1*B43 -> 41 | G43: =0.2*(1+0.01*B43^2)/24*I43 -> 0.19294167 | H43: =SUM($G$3:G43) -> 1.6316333 | I43: 1.3 | J43: =2500+50*B43 -> 4550 | M43: =IF(L43="","",1)
B44: 42 | C44: =400*B44 -> 16800 | D44: =5000*B44 -> 210000 | E44: =1000*B44 -> 42000 | F44: =1*B44 -> 42 | G44: =0.2*(1+0.01*B44^2)/24*I44 -> 0.20193333 | H44: =SUM($G$3:G44) -> 1.8335667 | I44: 1.3 | J44: =2500+50*B44 -> 4600 | M44: =IF(L44="","",1)
B45: 43 | C45: =400*B45 -> 17200 | D45: =5000*B45 -> 215000 | E45: =1000*B45 -> 43000 | F45: =1*B45 -> 43 | G45: =0.2*(1+0.01*B45^2)/24*I45 -> 0.21114167 | H45: =SUM($G$3:G45) -> 2.0447083 | I45: 1.3 | J45: =2500+50*B45 -> 4650 | K45: =ROUNDUP(H44,0) -> 2 | M45: =IF(L45="","",1)
B46: 44 | C46: =400*B46 -> 17600 | D46: =5000*B46 -> 220000 | E46: =1000*B46 -> 44000 | F46: =1*B46 -> 44 | G46: =0.2*(1+0.01*B46^2)/24*I46 -> 0.2545 | H46: =SUM($G$3:G46) -> 2.2992083 | I46: 1.5 | J46: =2500+50*B46 -> 4700 | L46: 2 | M46: 1
B47: 45 | C47: =400*B47 -> 18000 | D47: =5000*B47 -> 225000 | E47: =1000*B47 -> 45000 | F47: =1*B47 -> 45 | G47: =0.2*(1+0.01*B47^2)/24*I47 -> 0.265625 | H47: =SUM($G$3:G47) -> 2.5648333 | I47: 1.5 | J47: =2500+50*B47 -> 4750
B48: 46 | C48: =400*B48 -> 18400 | D48: =5000*B48 -> 230000 | E48: =1000*B48 -> 46000 | F48: =1*B48 -> 46 | G48: =0.2*(1+0.01*B48^2)/24*I48 -> 0.277 | H48: =SUM($G$3:G48) -> 2.8418333 | I48: 1.5 | J48: =2500+50*B48 -> 4800 | M48: =IF(L48="","",1)
B49: 47 | C49: =400*B49 -> 18800 | D49: =5000*B49 -> 235000 | E49: =1000*B49 -> 47000 | F49: =1*B49 -> 47 | G49: =0.2*(1+0.01*B49^2)/24*I49 -> 0.288625 | H49: =SUM($G$3:G49) -> 3.1304583 | I49: 1.5 | J49: =2500+50*B49 -> 4850 | K49: =ROUNDUP(H48,0) -> 3 | M49: =IF(L49="","",1)
B50: 48 | C50: =400*B50 -> 19200 | D50: =5000*B50 -> 240000 | E50: =1000*B50 -> 48000 | F50: =1*B50 -> 48 | G50: =0.2*(1+0.01*B50^2)/24*I50 -> 0.3005 | H50: =SUM($G$3:G50) -> 3.4309583 | I50: 1.5 | J50: =2500+50*B50 -> 4900 | L50: 3 | M50: =IF(L50="","",1) -> 1
B51: 49 | C51: =400*B51 -> 19600 | D51: =5000*B51 -> 245000 | E51: =1000*B51 -> 49000 | F51: =1*B51 -> 49 | G51: =0.2*(1+0.01*B51^2)/24*I51 -> 0.35430833 | H51: =SUM($G$3:G51) -> 3.7852667 | I51: 1.7 | J51: =2500+50*B51 -> 4950 | M51: =IF(L51="","",1)
B52: 50 | C52: =400*B52 -> 20000 | D52: =5000*B52 -> 250000 | E52: =1000*B52 -> 50000 | F52: =1*B52 -> 50 | G52: =0.2*(1+0.01*B52^2)/24*I52 -> 0.36833333 | H52: =SUM($G$3:G52) -> 4.1536 | I52: 1.7 | J52: =2500+50*B52 -> 5000 | K52: =ROUNDUP(H51,0) -> 4 | M52: =IF(L52="","",1)
B53: 51 | C53: =400*B53 -> 20400 | D53: =5000*B53 -> 255000 | E53: =1000*B53 -> 51000 | F53: =1*B53 -> 51 | G53: =0.2*(1+0.01*B53^2)/24*I53 -> 0.38264167 | H53: =SUM($G$3:G53) -> 4.5362417 | I53: 1.7 | J53: =2500+50*B53 -> 5050 | L53: 4 | M53: =IF(L53="","",1) -> 1
B54: 52 | C54: =400*B54 -> 20800 | D54: =5000*B54 -> 260000 | E54: =1000*B54 -> 52000 | F54: =1*B54 -> 52 | G54: =0.2*(1+0.01*B54^2)/24*I54 -> 0.39723333 | H54: =SUM($G$3:G54) -> 4.933475 | I54: 1.7 | J54: =2500+50*B54 -> 5100 | M54: =IF(L54="","",1)
B55: 53 | C55: =400*B55 -> 21200 | D55: =5000*B55 -> 265000 | E55: =1000*B55 -> 53000 | F55: =1*B55 -> 53 | G55: =0.2*(1+0.01*B55^2)/24*I55 -> 0.41210833 | H55: =SUM($G$3:G55) -> 5.3455833 | I55: 1.7 | J55: =2500+50*B55 -> 5150 | K55: =ROUNDUP(H54,0) -> 5 | M55: =IF(L55="","",1)
B56: 54 | C56: =400*B56 -> 21600 | D56: =5000*B56 -> 270000 | E56: =1000*B56 -> 54000 | F56: =1*B56 -> 54 | G56: =0.2*(1+0.01*B56^2)/24*I56 -> 0.50266667 | H56: =SUM($G$3:G56) -> 5.84825 | I56: 2 | J56: =2500+50*B56 -> 5200 | L56: 5 | M56: =IF(L56="","",1) -> 1
B57: 55 | C57: =400*B57 -> 22000 | D57: =5000*B57 -> 275000 | E57: =1000*B57 -> 55000 | F57: =1*B57 -> 55 | G57: =0.2*(1+0.01*B57^2)/24*I57 -> 0.52083333 | H57: =SUM($G$3:G57) -> 6.3690833 | I57: 2 | J57: =2500+50*B57 -> 5250 | K57: =ROUNDUP(H56,0) -> 6 | M57: =IF(L57="","",1)
B58: 56 | C58: =400*B58 -> 22400 | D58: =5000*B58 -> 280000 | E58: =1000*B58 -> 56000 | F58: =1*B58 -> 56 | G58: =0.2*(1+0.01*B58^2)/24*I58 -> 0.809 | H58: =SUM($G$3:G58) -> 7.1780833 | I58: 3 | J58: =2500+50*B58 -> 5300 | L58: 6 | M58: =IF(L58="","",1) -> 1
B59: 57 | C59: =400*B59 -> 22800 | D59: =5000*B59 -> 285000 | E59: =1000*B59 -> 57000 | F59: =1*B59 -> 57 | G59: =0.2*(1+0.01*B59^2)/24*I59 -> 0.83725 | H59: =SUM($G$3:G59) -> 8.0153333 | I59: 3 | J59: =2500+50*B59 -> 5350 | M59: =IF(L59="","",1)
B60: 58 | C60: =400*B60 -> 23200 | D60: =5000*B60 -> 290000 | E60: =1000*B60 -> 58000 | F60: =1*B60 -> 58 | G60: =0.2*(1+0.01*B60^2)/24*I60 -> 0.866 | H60: =SUM($G$3:G60) -> 8.8813333 | I60: 3 | J60: =2500+50*B60 -> 5400 | L60: 7 | M60: =IF(G60-INT(G60)>=0.2,ROUNDUP(G60,0),ROUNDDOWN(G60,0)) -> 1
B61: 59 | C61: =400*B61 -> 23600 | D61: =5000*B61 -> 295000 | E61: =1000*B61 -> 59000 | F61: =1*B61 -> 59 | G61: =0.2*(1+0.01*B61^2)/24*I61 -> 0.89525 | H61: =SUM($G$3:G61) -> 9.7765833 | I61: 3 | J61: =2500+50*B61 -> 5450 | L61: =L60+M60 -> 8 | M61: =IF(G61-INT(G61)>=0.2,ROUNDUP(G61,0),ROUNDDOWN(G61,0)) -> 1
B62: 60 | C62: =400*B62 -> 24000 | D62: =5000*B62 -> 300000 | E62: =1000*B62 -> 60000 | F62: =1*B62 -> 60 | G62: =0.2*(1+0.01*B62^2)/24*I62 -> 1.2333333 | H62: =SUM($G$3:G62) -> 11.009917 | I62: 4 | J62: =2500+50*B62 -> 5500 | K62: =ROUNDUP(H61,0) -> 10 | L62: =L61+M61 -> 9 | M62: =IF(G62-INT(G62)>=0.2,ROUNDUP(G62,0),ROUNDDOWN(G62,0)) -> 2
B63: 61 | C63: =400*B63 -> 24400 | D63: =5000*B63 -> 305000 | E63: =1000*B63 -> 61000 | F63: =1*B63 -> 61 | G63: =0.2*(1+0.01*B63^2)/24*I63 -> 1.5920833 | H63: =SUM($G$3:G63) -> 12.602 | I63: 5 | J63: =2500+50*B63 -> 5550 | L63: =L62+M62 -> 11 | M63: =IF(G63-INT(G63)>=0.2,ROUNDUP(G63,0),ROUNDDOWN(G63,0)) -> 2
B64: 62 | C64: =400*B64 -> 24800 | D64: =5000*B64 -> 310000 | E64: =1000*B64 -> 62000 | F64: =1*B64 -> 62 | G64: =0.2*(1+0.01*B64^2)/24*I64 -> 1.972 | H64: =SUM($G$3:G64) -> 14.574 | I64: 6 | J64: =2500+50*B64 -> 5600 | L64: =L63+M63 -> 13 | M64: =IF(G64-INT(G64)>=0.2,ROUNDUP(G64,0),ROUNDDOWN(G64,0)) -> 2
B65: 63 | C65: =400*B65 -> 25200 | D65: =5000*B65 -> 315000 | E65: =1000*B65 -> 63000 | F65: =1*B65 -> 63 | G65: =0.2*(1+0.01*B65^2)/24*I65 -> 2.3735833 | H65: =SUM($G$3:G65) -> 16.947583 | I65: 7 | J65: =2500+50*B65 -> 5650 | L65: =L64+M64 -> 15 | M65: =IF(G65-INT(G65)>=0.2,ROUNDUP(G65,0),ROUNDDOWN(G65,0)) -> 3
B66: 64 | C66: =400*B66 -> 25600 | D66: =5000*B66 -> 320000 | E66: =1000*B66 -> 64000 | F66: =1*B66 -> 64 | G66: =0.2*(1+0.01*B66^2)/24*I66 -> 2.7973333 | H66: =SUM($G$3:G66) -> 19.744917 | I66: 8 | J66: =2500+50*B66 -> 5700 | L66: =L65+M65 -> 18 | M66: =IF(G66-INT(G66)>=0.2,ROUNDUP(G66,0),ROUNDDOWN(G66,0)) -> 3
B67: 65 | C67: =400*B67 -> 26000 | D67: =5000*B67 -> 325000 | E67: =1000*B67 -> 65000 | F67: =1*B67 -> 65 | G67: =0.2*(1+0.01*B67^2)/24*I67 -> 3.24375 | H67: =SUM($G$3:G67) -> 22.988667 | I67: 9 | J67: =2500+50*B67 -> 5750 | K67: =ROUNDUP(H66,0) -> 20 | L67: =L66+M66 -> 21 | M67: =IF(G67-INT(G67)>=0.2,ROUNDUP(G67,0),ROUNDDOWN(G67,0)) -> 4
B68: 66 | C68: =400*B68 -> 26400 | D68: =5000*B68 -> 330000 | E68: =1000*B68 -> 66000 | F68: =1*B68 -> 66 | G68: =0.2*(1+0.01*B68^2)/24*I68 -> 4.0846667 | H68: =SUM($G$3:G68) -> 27.073333 | I68: 11 | J68: =2500+50*B68 -> 5800 | L68: =L67+M67 -> 25 | M68: =IF(G68-INT(G68)>=0.2,ROUNDUP(G68,0),ROUNDDOWN(G68,0)) -> 4
B69: 67 | C69: =400*B69 -> 26800 | D69: =5000*B69 -> 335000 | E69: =1000*B69 -> 67000 | F69: =1*B69 -> 67 | G69: =0.2*(1+0.01*B69^2)/24*I69 -> 4.9714167 | H69: =SUM($G$3:G69) -> 32.04475 | I69: 13 | J69: =2500+50*B69 -> 5850 | L69: =L68+M68 -> 29 | M69: =IF(G69-INT(G69)>=0.2,ROUNDUP(G69,0),ROUNDDOWN(G69,0)) -> 5
B70: 68 | C70: =400*B70 -> 27200 | D70: =5000*B70 -> 340000 | E70: =1000*B70 -> 68000 | F70: =1*B70 -> 68 | G70: =0.2*(1+0.01*B70^2)/24*I70 -> 5.905 | H70: =SUM($G$3:G70) -> 37.94975 | I70: 15 | J70: =2500+50*B70 -> 5900 | L70: =L69+M69 -> 34 | M70: =IF(G70-INT(G70)>=0.2,ROUNDUP(G70,0),ROUNDDOWN(G70,0)) -> 6
B71: 69 | C71: =400*B71 -> 27600 | D71: =5000*B71 -> 345000 | E71: =1000*B71 -> 69000 | F71: =1*B71 -> 69 | G71: =0.2*(1+0.01*B71^2)/24*I71 -> 6.8864167 | H71: =SUM($G$3:G71) -> 44.836167 | I71: 17 | J71: =2500+50*B71 -> 5950 | L71: =L70+M70 -> 40 | M71: =IF(G71-INT(G71)>=0.2,ROUNDUP(G71,0),ROUNDDOWN(G71,0)) -> 7
B72: 70 | C72: =400*B72 -> 28000 | D72: =5000*B72 -> 350000 | E72: =1000*B72 -> 70000 | F72: =1*B72 -> 70 | G72: =0.2*(1+0.01*B72^2)/24*I72 -> 7.0833333 | H72: =SUM($G$3:G72) -> 51.9195 | I72: 17 | J72: =2500+50*B72 -> 6000 | K72: =ROUNDUP(H71,0) -> 45 | L72: =L71+M71 -> 47 | M72: =IF(G72-INT(G72)>=0.2,ROUNDUP(G72,0),ROUNDDOWN(G72,0)) -> 7
B73: 71 | C73: =400*B73 -> 28400 | D73: =5000*B73 -> 355000 | E73: =1000*B73 -> 71000 | F73: =1*B73 -> 71 | G73: =0.2*(1+0.01*B73^2)/24*I73 -> 7.2830833 | H73: =SUM($G$3:G73) -> 59.202583 | I73: 17 | J73: =2500+50*B73 -> 6050 | L73: =L72+M72 -> 54 | M73: =IF(G73-INT(G73)>=0.2,ROUNDUP(G73,0),ROUNDDOWN(G73,0)) -> 8
B74: 72 | C74: =400*B74 -> 28800 | D74: =5000*B74 -> 360000 | E74: =1000*B74 -> 72000 | F74: =1*B74 -> 72 | G74: =0.2*(1+0.01*B74^2)/24*I74 -> 7.4856667 | H74: =SUM($G$3:G74) -> 66.68825 | I74: 17 | J74: =2500+50*B74 -> 6100 | L74: =L73+M73 -> 62 | M74: =IF(G74-INT(G74)>=0.2,ROUNDUP(G74,0),ROUNDDOWN(G74,0)) -> 8
B75: 73 | C75: =400*B75 -> 29200 | D75: =5000*B75 -> 365000 | E75: =1000*B75 -> 73000 | F75: =1*B75 -> 73 | G75: =0.2*(1+0.01*B75^2)/24*I75 -> 7.6910833 | H75: =SUM($G$3:G75) -> 74.379333 | I75: 17 | J75: =2500+50*B75 -> 6150 | L75: =L74+M74 -> 70 | M75: =IF(G75-INT(G75)>=0.2,ROUNDUP(G75,0),ROUNDDOWN(G75,0)) -> 8
B76: 74 | C76: =400*B76 -> 29600 | D76: =5000*B76 -> 370000 | E76: =1000*B76 -> 74000 | F76: =1*B76 -> 74 | G76: =0.2*(1+0.01*B76^2)/24*I76 -> 7.8993333 | H76: =SUM($G$3:G76) -> 82.278667 | I76: 17 | J76: =2500+50*B76 -> 6200 | L76: =L75+M75 -> 78 | M76: =IF(G76-INT(G76)>=0.2,ROUNDUP(G76,0),ROUNDDOWN(G76,0)) -> 8
B77: 75 | C77: =400*B77 -> 30000 | D77: =5000*B77 -> 375000 | E77: =1000*B77 -> 75000 | F77: =1*B77 -> 75 | G77: =0.2*(1+0.01*B77^2)/24*I77 -> 8.1104167 | H77: =SUM($G$3:G77) -> 90.389083 | I77: 17 | J77: =2500+50*B77 -> 6250 | K77: =ROUNDUP(H76,0) -> 83 | L77: =L76+M76 -> 86 | M77: =IF(G77-INT(G77)>=0.2,ROUNDUP(G77,0),ROUNDDOWN(G77,0)) -> 8
B78: 76 | C78: =400*B78 -> 30400 | D78: =5000*B78 -> 380000 | E78: =1000*B78 -> 76000 | F78: =1*B78 -> 76 | G78: =0.2*(1+0.01*B78^2)/24*I78 -> 8.3243333 | H78: =SUM($G$3:G78) -> 98.713417 | I78: 17 | J78: =2500+50*B78 -> 6300 | L78: =L77+M77 -> 94 | M78: =IF(G78-INT(G78)>=0.2,ROUNDUP(G78,0),ROUNDDOWN(G78,0)) -> 9
B79: 77 | C79: =400*B79 -> 30800 | D79: =5000*B79 -> 385000 | E79: =1000*B79 -> 77000 | F79: =1*B79 -> 77 | G79: =0.2*(1+0.01*B79^2)/24*I79 -> 8.5410833 | H79: =SUM($G$3:G79) -> 107.2545 | I79: 17 | J79: =2500+50*B79 -> 6350 | L79: =L78+M78 -> 103 | M79: =IF(G79-INT(G79)>=0.2,ROUNDUP(G79,0),ROUNDDOWN(G79,0)) -> 9
B80: 78 | C80: =400*B80 -> 31200 | D80: =5000*B80 -> 390000 | E80: =1000*B80 -> 78000 | F80: =1*B80 -> 78 | G80: =0.2*(1+0.01*B80^2)/24*I80 -> 8.7606667 | H80: =SUM($G$3:G80) -> 116.01517 | I80: 17 | J80: =2500+50*B80 -> 6400 | L80: =L79+M79 -> 112 | M80: =IF(G80-INT(G80)>=0.2,ROUNDUP(G80,0),ROUNDDOWN(G80,0)) -> 9
B81: 79 | C81: =400*B81 -> 31600 | D81: =5000*B81 -> 395000 | E81: =1000*B81 -> 79000 | F81: =1*B81 -> 79 | G81: =0.2*(1+0.01*B81^2)/24*I81 -> 8.9830833 | H81: =SUM($G$3:G81) -> 124.99825 | I81: 17 | J81: =2500+50*B81 -> 6450 | L81: =L80+M80 -> 121 | M81: =IF(G81-INT(G81)>=0.2,ROUNDUP(G81,0),ROUNDDOWN(G81,0)) -> 9
B82: 80 | C82: =400*B82 -> 32000 | D82: =5000*B82 -> 400000 | E82: =1000*B82 -> 80000 | F82: =1*B82 -> 80 | G82: =0.2*(1+0.01*B82^2)/24*I82 -> 9.2083333 | H82: =SUM($G$3:G82) -> 134.20658 | I82: 17 | J82: =2500+50*B82 -> 6500 | K82: =ROUNDUP(H81,0) -> 125 | L82: =L81+M81 -> 130 | M82: =IF(G82-INT(G82)>=0.2,ROUNDUP(G82,0),ROUNDDOWN(G82,0)) -> 10
B83: 81 | C83: =400*B83 -> 32400 | D83: =5000*B83 -> 405000 | E83: =1000*B83 -> 81000 | F83: =1*B83 -> 81 | G83: =0.2*(1+0.01*B83^2)/24*I83 -> 9.4364167 | H83: =SUM($G$3:G83) -> 143.643 | I83: 17 | J83: =2500+50*B83 -> 6550 | L83: =L82+M82 -> 140 | M83: =IF(G83-INT(G83)>=0.2,ROUNDUP(G83,0),ROUNDDOWN(G83,0)) -> 10
B84: 82 | C84: =400*B84 -> 32800 | D84: =5000*B84 -> 410000 | E84: =1000*B84 -> 82000 | F84: =1*B84 -> 82 | G84: =0.2*(1+0.01*B84^2)/24*I84 -> 9.6673333 | H84: =SUM($G$3:G84) -> 153.31033 | I84: 17 | J84: =2500+50*B84 -> 6600 | L84: =L83+M83 -> 150 | M84: =IF(G84-INT(G84)>=0.2,ROUNDUP(G84,0),ROUNDDOWN(G84,0)) -> 10
B85: 83 | C85: =400*B85 -> 33200 | D85: =5000*B85 -> 415000 | E85: =1000*B85 -> 83000 | F85: =1*B85 -> 83 | G85: =0.2*(1+0.01*B85^2)/24*I85 -> 9.9010833 | H85: =SUM($G$3:G85) -> 163.21142 | I85: 17 | J85: =2500+50*B85 -> 6650 | L85: =L84+M84 -> 160 | M85: =IF(G85-INT(G85)>=0.2,ROUNDUP(G85,0),ROUNDDOWN(G85,0)) -> 10
B86: 84 | C86: =400*B86 -> 33600 | D86: =5000*B86 -> 420000 | E86: =1000*B86 -> 84000 | F86: =1*B86 -> 84 | G86: =0.2*(1+0.01*B86^2)/24*I86 -> 10.137667 | H86: =SUM($G$3:G86) -> 173.34908 | I86: 17 | J86: =2500+50*B86 -> 6700 | L86: =L85+M85 -> 170 | M86: =IF(G86-INT(G86)>=0.2,ROUNDUP(G86,0),ROUNDDOWN(G86,0)) -> 10
B87: 85 | C87: =400*B87 -> 34000 | D87: =5000*B87 -> 425000 | E87: =1000*B87 -> 85000 | F87: =1*B87 -> 85 | G87: =0.2*(1+0.01*B87^2)/24*I87 -> 10.377083 | H87: =SUM($G$3:G87) -> 183.72617 | I87: 17 | J87: =2500+50*B87 -> 6750 | L87: =L86+M86 -> 180 | M87: =IF(G87-INT(G87)>=0.2,ROUNDUP(G87,0),ROUNDDOWN(G87,0)) -> 11
B88: 86 | C88: =400*B88 -> 34400 | D88: =5000*B88 -> 430000 | E88: =1000*B88 -> 86000 | F88: =1*B88 -> 86 | G88: =0.2*(1+0.01*B88^2)/24*I88 -> 10.619333 | H88: =SUM($G$3:G88) -> 194.3455 | I88: 17 | J88: =2500+50*B88 -> 6800 | L88: =L87+M87 -> 191 | M88: =IF(G88-INT(G88)>=0.2,ROUNDUP(G88,0),ROUNDDOWN(G88,0)) -> 11
B89: 87 | C89: =400*B89 -> 34800 | D89: =5000*B89 -> 435000 | E89: =1000*B89 -> 87000 | F89: =1*B89 -> 87 | G89: =0.2*(1+0.01*B89^2)/24*I89 -> 10.864417 | H89: =SUM($G$3:G89) -> 205.20992 | I89: 17 | J89: =2500+50*B89 -> 6850 | L89: =L88+M88 -> 202 | M89: =IF(G89-INT(G89)>=0.2,ROUNDUP(G89,0),ROUNDDOWN(G89,0)) -> 11
B90: 88 | C90: =400*B90 -> 35200 | D90: =5000*B90 -> 440000 | E90: =1000*B90 -> 88000 | F90: =1*B90 -> 88 | G90: =0.2*(1+0.01*B90^2)/24*I90 -> 11.112333 | H90: =SUM($G$3:G90) -> 216.32225 | I90: 17 | J90: =2500+50*B90 -> 6900 | L90: =L89+M89 -> 213 | M90: =IF(G90-INT(G90)>=0.2,ROUNDUP(G90,0),ROUNDDOWN(G90,0)) -> 11
B91: 89 | C91: =400*B91 -> 35600 | D91: =5000*B91 -> 445000 | E91: =1000*B91 -> 89000 | F91: =1*B91 -> 89 | G91: =0.2*(1+0.01*B91^2)/24*I91 -> 11.363083 | H91: =SUM($G$3:G91) -> 227.68533 | I91: 17 | J91: =2500+50*B91 -> 6950 | L91: =L90+M90 -> 224 | M91: =IF(G91-INT(G91)>=0.2,ROUNDUP(G91,0),ROUNDDOWN(G91,0)) -> 12
B92: 90 | C92: =400*B92 -> 36000 | D92: =5000*B92 -> 450000 | E92: =1000*B92 -> 90000 | F92: =1*B92 -> 90 | G92: =0.2*(1+0.01*B92^2)/24*I92 -> 11.616667 | H92: =SUM($G$3:G92) -> 239.302 | I92: 17 | J92: =2500+50*B92 -> 7000 | K92: =ROUNDUP(H91,0) -> 228 | L92: =L91+M91 -> 236 | M92: =IF(G92-INT(G92)>=0.2,ROUNDUP(G92,0),ROUNDDOWN(G92,0)) -> 12
B93: 91 | C93: =400*B93 -> 36400 | D93: =5000*B93 -> 455000 | E93: =1000*B93 -> 91000 | F93: =1*B93 -> 91 | G93: =0.2*(1+0.01*B93^2)/24*I93 -> 11.873083 | H93: =SUM($G$3:G93) -> 251.17508 | I93: 17 | J93: =2500+50*B93 -> 7050 | L93: =L92+M92 -> 248 | M93: =IF(G93-INT(G93)>=0.2,ROUNDUP(G93,0),ROUNDDOWN(G93,0)) -> 12
B94: 92 | C94: =400*B94 -> 36800 | D94: =5000*B94 -> 460000 | E94: =1000*B94 -> 92000 | F94: =1*B94 -> 92 | G94: =0.2*(1+0.01*B94^2)/24*I94 -> 12.132333 | H94: =SUM($G$3:G94) -> 263.30742 | I94: 17 | J94: =2500+50*B94 -> 7100 | L94: =L93+M93 -> 260 | M94: =IF(G94-INT(G94)>=0.2,ROUNDUP(G94,0),ROUNDDOWN(G94,0)) -> 12
B95: 93 | C95: =400*B95 -> 37200 | D95: =5000*B95 -> 465000 | E95: =1000*B95 -> 93000 | F95: =1*B95 -> 93 | G95: =0.2*(1+0.01*B95^2)/24*I95 -> 12.394417 | H95: =SUM($G$3:G95) -> 275.70183 | I95: 17 | J95: =2500+50*B95 -> 7150 | L95: =L94+M94 -> 272 | M95: =IF(G95-INT(G95)>=0.2,ROUNDUP(G95,0),ROUNDDOWN(G95,0)) -> 13
B96: 94 | C96: =400*B96 -> 37600 | D96: =5000*B96 -> 470000 | E96: =1000*B96 -> 94000 | F96: =1*B96 -> 94 | G96: =0.2*(1+0.01*B96^2)/24*I96 -> 12.659333 | H96: =SUM($G$3:G96) -> 288.36117 | I96: 17 | J96: =2500+50*B96 -> 7200 | L96: =L95+M95 -> 285 | M96: =IF(G96-INT(G96)>=0.2,ROUNDUP(G96,0),ROUNDDOWN(G96,0)) -> 13
B97: 95 | C97: =400*B97 -> 38000 | D97: =5000*B97 -> 475000 | E97: =1000*B97 -> 95000 | F97: =1*B97 -> 95 | G97: =0.2*(1+0.01*B97^2)/24*I97 -> 12.927083 | H97: =SUM($G$3:G97) -> 301.28825 | I97: 17 | J97: =2500+50*B97 -> 7250 | L97: =L96+M96 -> 298 | M97: =IF(G97-INT(G97)>=0.2,ROUNDUP(G97,0),ROUNDDOWN(G97,0)) -> 13
B98: 96 | C98: =400*B98 -> 38400 | D98: =5000*B98 -> 480000 | E98: =1000*B98 -> 96000 | F98: =1*B98 -> 96 | G98: =0.2*(1+0.01*B98^2)/24*I98 -> 13.197667 | H98: =SUM($G$3:G98) -> 314.48592 | I98: 17 | J98: =2500+50*B98 -> 7300 | L98: =L97+M97 -> 311 | M98: =IF(G98-INT(G98)>=0.2,ROUNDUP(G98,0),ROUNDDOWN(G98,0)) -> 13
B99: 97 | C99: =400*B99 -> 38800 | D99: =5000*B99 -> 485000 | E99: =1000*B99 -> 97000 | F99: =1*B99 -> 97 | G99: =0.2*(1+0.01*B99^2)/24*I99 -> 13.471083 | H99: =SUM($G$3:G99) -> 327.957 | I99: 17 | J99: =2500+50*B99 -> 7350 | L99: =L98+M98 -> 324 | M99: =IF(G99-INT(G99)>=0.2,ROUNDUP(G99,0),ROUNDDOWN(G99,0)) -> 14
B100: 98 | C100: =400*B100 -> 39200 | D100: =5000*B100 -> 490000 | E100: =1000*B100 -> 98000 | F100: =1*B100 -> 98 | G100: =0.2*(1+0.01*B100^2)/24*I100 -> 13.747333 | H100: =SUM($G$3:G100) -> 341.70433 | I100: 17 | J100: =2500+50*B100 -> 7400 | L100: =L99+M99 -> 338 | M100: =IF(G100-INT(G100)>=0.2,ROUNDUP(G100,0),ROUNDDOWN(G100,0)) -> 14
B101: 99 | C101: =400*B101 -> 39600 | D101: =5000*B101 -> 495000 | E101: =1000*B101 -> 99000 | F101: =1*B101 -> 99 | G101: =0.2*(1+0.01*B101^2)/24*I101 -> 14.026417 | H101: =SUM($G$3:G101) -> 355.73075 | I101: 17 | J101: =2500+50*B101 -> 7450 | L101: =L100+M100 -> 352 | M101: =IF(G101-INT(G101)>=0.2,ROUNDUP(G101,0),ROUNDDOWN(G101,0)) -> 14
B102: 100 | C102: =400*B102 -> 40000 | D102: =5000*B102 -> 500000 | E102: =1000*B102 -> 100000 | F102: =1*B102 -> 100 | G102: =0.2*(1+0.01*B102^2)/24*I102 -> 14.308333 | H102: =SUM($G$3:G102) -> 370.03908 | I102: 17 | J102: =2500+50*B102 -> 7500 | L102: =L101+M101 -> 366 | M102: =IF(G102-INT(G102)>=0.2,ROUNDUP(G102,0),ROUNDDOWN(G102,0)) -> 15
B103: 101 | C103: =400*B103 -> 40400 | D103: =5000*B103 -> 505000 | E103: =1000*B103 -> 101000 | F103: =1*B103 -> 101 | G103: =0.2*(1+0.01*B103^2)/24*I103 -> 14.593083 | H103: =SUM($G$3:G103) -> 384.63217 | I103: 17 | J103: =2500+50*B103 -> 7550 | L103: =L102+M102 -> 381 | M103: =IF(G103-INT(G103)>=0.2,ROUNDUP(G103,0),ROUNDDOWN(G103,0)) -> 15
B104: 102 | C104: =400*B104 -> 40800 | D104: =5000*B104 -> 510000 | E104: =1000*B104 -> 102000 | F104: =1*B104 -> 102 | G104: =0.2*(1+0.01*B104^2)/24*I104 -> 14.880667 | H104: =SUM($G$3:G104) -> 399.51283 | I104: 17 | J104: =2500+50*B104 -> 7600 | L104: =L103+M103 -> 396 | M104: =IF(G104-INT(G104)>=0.2,ROUNDUP(G104,0),ROUNDDOWN(G104,0)) -> 15
... B152: 150 | C152: =400*B152 -> 60000 | D152: =5000*B152 -> 750000 | E152: =1000*B152 -> 150000 | F152: =1*B152 -> 150 | G152: =0.2*(1+0.01*B152^2)/24*I152 -> 32.016667 | H152: =SUM($G$3:G152) -> 1507.5162 | I152: 17 | J152: =2500+50*B152 -> 10000 | L152: =L151+M151 -> 1503 | M152: =IF(G152-INT(G152)>=0.2,ROUNDUP(G152,0),ROUNDDOWN(G152,0)) -> 32

Sheet 主角经验
C1: 产出效率 | AF1: 日常活动每日产出权重 | AV1: 定时活动每日产出权重 | BG1: 节日活动每日产出权重
A2: 角色等级 | B2: 基准效率1小时获得经验(h） | C2: 职业日常 | D2: 日常副本 | E2: 英雄试炼 | F2: 冰封王座 | G2: 考古 | H2: 运镖 | I2: 卡拉赞系列 | J2: 卡拉赞精英 | K2: 精英副本 | L2: 公会任务(周7轮) | M2: 暗夜马戏团(周20轮) | N2: 野外挂机/离线经验 | O2: 经验道具 | P2: 分享 | Q2: 双倍点数 | R2: 援助战斗和道具 | S2: 古神爪牙 | T2: 幼龙 | U2: 屠龙 | V2: 古神 | W2: 艾泽拉斯地理探索 | X2: 艾泽拉斯百科竞赛 | Y2: 职业闯关(周2次) | Z2: 竞技场（周5次） | AA2: 公会副本(周1次) | AB2: 帮派强盗 | AC2: 帮派采药 | AD2: 节日活动1 | AE2: 节日活动2 | AF2: 职业日常 | AG2: 日常副本 | AH2: 英雄试炼 | AI2: 冰封王座 | AJ2: 考古 | AK2: 运镖 | AL2: 卡拉赞系列 | AM2: 卡拉赞精英 | AN2: 精英副本 | AO2: 公会任务(周7轮) | AP2: 暗夜马戏团(周20轮) | AQ2: 野外挂机/离线经验 | AR2: 经验道具 | AS2: 分享 | AT2: 双倍点数 | AU2: 援助战斗和道具 | AV2: 古神爪牙 | AW2: 幼龙 | AX2: 屠龙 | AY2: 古神 | AZ2: 艾泽拉斯地理探索 | BA2: 艾泽拉斯百科竞赛 | BB2: 职业闯关(周2次) | BC2: 竞技场（周5次） | BD2: 公会副本(周1次) | BE2: 帮派强盗 | BF2: 帮派采药 | BG2: 节日活动1 | BH2: 节日活动2 | BI2: 每日循环总量 | BJ2: 每日循环收益 | BK2: 剧情任务收益 | BL2: 剧情任务分段经验 | BM2: 剧情任务经验占比 | BN2: 主角升级经验 *暂时不算上节日活动的经验 | BO2: 刷野战斗经验
A3: 1 | B3: =升级节奏!C3 -> 400 | C3: =IF(VLOOKUP(C$2,行为概览!$D$3:$J$33,7,0)="","",VLOOKUP(C$2,行为概览!$D$3:$J$33,7,0)) -> 50 | D3: =IF(VLOOKUP(D$2,行为概览!$D$3:$J$33,7,0)="","",VLOOKUP(D$2,行为概览!$D$3:$J$33,7,0)) -> 3.3 | E3: =IF(VLOOKUP(E$2,行为概览!$D$3:$J$33,7,0)="","",VLOOKUP(E$2,行为概览!$D$3:$J$33,7,0)) -> 30 | F3: =IF(VLOOKUP(F$2,行为概览!$D$3:$J$33,7,0)="","",VLOOKUP(F$2,行为概览!$D$3:$J$33,7,0)) -> 15 | G3: =IF(VLOOKUP(G$2,行为概览!$D$3:$J$33,7,0)="","",VLOOKUP(G$2,行为概览!$D$3:$J$33,7,0)) | H3: =IF(VLOOKUP(H$2,行为概览!$D$3:$J$33,7,0)="","",VLOOKUP(H$2,行为概览!$D$3:$J$33,7,0)) | I3: =IF(VLOOKUP(I$2,行为概览!$D$3:$J$33,7,0)="","",VLOOKUP(I$2,行为概览!$D$3:$J$33,7,0)) | J3: =IF(VLOOKUP(J$2,行为概览!$D$3:$J$33,7,0)="","",VLOOKUP(J$2,行为概览!$D$3:$J$33,7,0)) | ... AE3: =IF(VLOOKUP(AE$2,行为概览!$D$3:$J$33,7,0)="","",VLOOKUP(AE$2,行为概览!$D$3:$J$33,7,0)) | AF3: =IF(C3="","",ROUND(C3*玩法行为规划!B3,2)) -> 0 | AG3: =IF(D3="","",ROUND(D3*玩法行为规划!C3,2)) -> 0 | AH3: =IF(E3="","",ROUND(E3*玩法行为规划!D3,2)) -> 0 | AI3: =IF(F3="","",ROUND(F3*玩法行为规划!E3,2)) -> 0 | AJ3: =IF(G3="","",ROUND(G3*玩法行为规划!F3,2)) | AK3: =IF(H3="","",ROUND(H3*玩法行为规划!G3,2)) | AL3: =IF(I3="","",ROUND(I3*玩法行为规划!H3,2)) | AM3: =IF(J3="","",ROUND(J3*玩法行为规划!I3,2)) | ... BH3: =IF(AE3="","",ROUND(AE3*玩法行为规划!AD3,2)) | BI3: =SUM(AF3:BF3) -> 52 | BJ3: =B3*BI3 -> 20800 | BK3: =ROUND(B3*(4+MAX(A3-30,0)*0.6),-2) -> 1600 | BL3: =SUM(BK3:BK11) -> 72000 | BM3: =BK3/BN3 -> 1 | BN3: =INT(BJ3*升级节奏!G3+BK3) -> 1600 | BO3: =ROUND(B3/90,0) -> 4
A4: 2 | B4: =升级节奏!C4 -> 800 | C4: =IF(VLOOKUP(C$2,行为概览!$D$3:$J$33,7,0)="","",VLOOKUP(C$2,行为概览!$D$3:$J$33,7,0)) -> 50 | D4: =IF(VLOOKUP(D$2,行为概览!$D$3:$J$33,7,0)="","",VLOOKUP(D$2,行为概览!$D$3:$J$33,7,0)) -> 3.3 | E4: =IF(VLOOKUP(E$2,行为概览!$D$3:$J$33,7,0)="","",VLOOKUP(E$2,行为概览!$D$3:$J$33,7,0)) -> 30 | F4: =IF(VLOOKUP(F$2,行为概览!$D$3:$J$33,7,0)="","",VLOOKUP(F$2,行为概览!$D$3:$J$33,7,0)) -> 15 | G4: =IF(VLOOKUP(G$2,行为概览!$D$3:$J$33,7,0)="","",VLOOKUP(G$2,行为概览!$D$3:$J$33,7,0)) | H4: =IF(VLOOKUP(H$2,行为概览!$D$3:$J$33,7,0)="","",VLOOKUP(H$2,行为概览!$D$3:$J$33,7,0)) | I4: =IF(VLOOKUP(I$2,行为概览!$D$3:$J$33,7,0)="","",VLOOKUP(I$2,行为概览!$D$3:$J$33,7,0)) | J4: =IF(VLOOKUP(J$2,行为概览!$D$3:$J$33,7,0)="","",VLOOKUP(J$2,行为概览!$D$3:$J$33,7,0)) | ... AE4: =IF(VLOOKUP(AE$2,行为概览!$D$3:$J$33,7,0)="","",VLOOKUP(AE$2,行为概览!$D$3:$J$33,7,0)) | AF4: =IF(C4="","",ROUND(C4*玩法行为规划!B4,2)) -> 0 | AG4: =IF(D4="","",ROUND(D4*玩法行为规划!C4,2)) -> 0 | AH4: =IF(E4="","",ROUND(E4*玩法行为规划!D4,2)) -> 0 | AI4: =IF(F4="","",ROUND(F4*玩法行为规划!E4,2)) -> 0 | AJ4: =IF(G4="","",ROUND(G4*玩法行为规划!F4,2)) | AK4: =IF(H4="","",ROUND(H4*玩法行为规划!G4,2)) | AL4: =IF(I4="","",ROUND(I4*玩法行为规划!H4,2)) | AM4: =IF(J4="","",ROUND(J4*玩法行为规划!I4,2)) | ... BH4: =IF(AE4="","",ROUND(AE4*玩法行为规划!AD4,2)) | BI4: =SUM(AF4:BF4) -> 52 | BJ4: =B4*BI4 -> 41600 | BK4: =ROUND(B4*(4+MAX(A4-30,0)*0.6),-2) -> 3200 | BM4: =BK4/BN4 -> 1 | BN4: =INT(BJ4*升级节奏!G4+BK4) -> 3200 | BO4: =ROUND(B4/90,0) -> 9
A5: 3 | B5: =升级节奏!C5 -> 1200 | C5: =IF(VLOOKUP(C$2,行为概览!$D$3:$J$33,7,0)="","",VLOOKUP(C$2,行为概览!$D$3:$J$33,7,0)) -> 50 | D5: =IF(VLOOKUP(D$2,行为概览!$D$3:$J$33,7,0)="","",VLOOKUP(D$2,行为概览!$D$3:$J$33,7,0)) -> 3.3 | E5: =IF(VLOOKUP(E$2,行为概览!$D$3:$J$33,7,0)="","",VLOOKUP(E$2,行为概览!$D$3:$J$33,7,0)) -> 30 | F5: =IF(VLOOKUP(F$2,行为概览!$D$3:$J$33,7,0)="","",VLOOKUP(F$2,行为概览!$D$3:$J$33,7,0)) -> 15 | G5: =IF(VLOOKUP(G$2,行为概览!$D$3:$J$33,7,0)="","",VLOOKUP(G$2,行为概览!$D$3:$J$33,7,0)) | H5: =IF(VLOOKUP(H$2,行为概览!$D$3:$J$33,7,0)="","",VLOOKUP(H$2,行为概览!$D$3:$J$33,7,0)) | I5: =IF(VLOOKUP(I$2,行为概览!$D$3:$J$33,7,0)="","",VLOOKUP(I$2,行为概览!$D$3:$J$33,7,0)) | J5: =IF(VLOOKUP(J$2,行为概览!$D$3:$J$33,7,0)="","",VLOOKUP(J$2,行为概览!$D$3:$J$33,7,0)) | ... AE5: =IF(VLOOKUP(AE$2,行为概览!$D$3:$J$33,7,0)="","",VLOOKUP(AE$2,行为概览!$D$3:$J$33,7,0)) | AF5: =IF(C5="","",ROUND(C5*玩法行为规划!B5,2)) -> 0 | AG5: =IF(D5="","",ROUND(D5*玩法行为规划!C5,2)) -> 0 | AH5: =IF(E5="","",ROUND(E5*玩法行为规划!D5,2)) -> 0 | AI5: =IF(F5="","",ROUND(F5*玩法行为规划!E5,2)) -> 0 | AJ5: =IF(G5="","",ROUND(G5*玩法行为规划!F5,2)) | AK5: =IF(H5="","",ROUND(H5*玩法行为规划!G5,2)) | AL5: =IF(I5="","",ROUND(I5*玩法行为规划!H5,2)) | AM5: =IF(J5="","",ROUND(J5*玩法行为规划!I5,2)) | ... BH5: =IF(AE5="","",ROUND(AE5*玩法行为规划!AD5,2)) | BI5: =SUM(AF5:BF5) -> 52 | BJ5: =B5*BI5 -> 62400 | BK5: =ROUND(B5*(4+MAX(A5-30,0)*0.6),-2) -> 4800 | BM5: =BK5/BN5 -> 1 | BN5: =INT(BJ5*升级节奏!G5+BK5) -> 4800 | BO5: =ROUND(B5/90,0) -> 13
A6: 4 | B6: =升级节奏!C6 -> 1600 | C6: =IF(VLOOKUP(C$2,行为概览!$D$3:$J$33,7,0)="","",VLOOKUP(C$2,行为概览!$D$3:$J$33,7,0)) -> 50 | D6: =IF(VLOOKUP(D$2,行为概览!$D$3:$J$33,7,0)="","",VLOOKUP(D$2,行为概览!$D$3:$J$33,7,0)) -> 3.3 | E6: =IF(VLOOKUP(E$2,行为概览!$D$3:$J$33,7,0)="","",VLOOKUP(E$2,行为概览!$D$3:$J$33,7,0)) -> 30 | F6: =IF(VLOOKUP(F$2,行为概览!$D$3:$J$33,7,0)="","",VLOOKUP(F$2,行为概览!$D$3:$J$33,7,0)) -> 15 | G6: =IF(VLOOKUP(G$2,行为概览!$D$3:$J$33,7,0)="","",VLOOKUP(G$2,行为概览!$D$3:$J$33,7,0)) | H6: =IF(VLOOKUP(H$2,行为概览!$D$3:$J$33,7,0)="","",VLOOKUP(H$2,行为概览!$D$3:$J$33,7,0)) | I6: =IF(VLOOKUP(I$2,行为概览!$D$3:$J$33,7,0)="","",VLOOKUP(I$2,行为概览!$D$3:$J$33,7,0)) | J6: =IF(VLOOKUP(J$2,行为概览!$D$3:$J$33,7,0)="","",VLOOKUP(J$2,行为概览!$D$3:$J$33,7,0)) | ... AE6: =IF(VLOOKUP(AE$2,行为概览!$D$3:$J$33,7,0)="","",VLOOKUP(AE$2,行为概览!$D$3:$J$33,7,0)) | AF6: =IF(C6="","",ROUND(C6*玩法行为规划!B6,2)) -> 0 | AG6: =IF(D6="","",ROUND(D6*玩法行为规划!C6,2)) -> 0 | AH6: =IF(E6="","",ROUND(E6*玩法行为规划!D6,2)) -> 0 | AI6: =IF(F6="","",ROUND(F6*玩法行为规划!E6,2)) -> 0 | AJ6: =IF(G6="","",ROUND(G6*玩法行为规划!F6,2)) | AK6: =IF(H6="","",ROUND(H6*玩法行为规划!G6,2)) | AL6: =IF(I6="","",ROUND(I6*玩法行为规划!H6,2)) | AM6: =IF(J6="","",ROUND(J6*玩法行为规划!I6,2)) | ... BH6: =IF(AE6="","",ROUND(AE6*玩法行为规划!AD6,2)) | BI6: =SUM(AF6:BF6) -> 52 | BJ6: =B6*BI6 -> 83200 | BK6: =ROUND(B6*(4+MAX(A6-30,0)*0.6),-2) -> 6400 | BM6: =BK6/BN6 -> 1 | BN6: =INT(BJ6*升级节奏!G6+BK6) -> 6400 | BO6: =ROUND(B6/90,0) -> 18
A7: 5 | B7: =升级节奏!C7 -> 2000 | C7: =IF(VLOOKUP(C$2,行为概览!$D$3:$J$33,7,0)="","",VLOOKUP(C$2,行为概览!$D$3:$J$33,7,0)) -> 50 | D7: =IF(VLOOKUP(D$2,行为概览!$D$3:$J$33,7,0)="","",VLOOKUP(D$2,行为概览!$D$3:$J$33,7,0)) -> 3.3 | E7: =IF(VLOOKUP(E$2,行为概览!$D$3:$J$33,7,0)="","",VLOOKUP(E$2,行为概览!$D$3:$J$33,7,0)) -> 30 | F7: =IF(VLOOKUP(F$2,行为概览!$D$3:$J$33,7,0)="","",VLOOKUP(F$2,行为概览!$D$3:$J$33,7,0)) -> 15 | G7: =IF(VLOOKUP(G$2,行为概览!$D$3:$J$33,7,0)="","",VLOOKUP(G$2,行为概览!$D$3:$J$33,7,0)) | H7: =IF(VLOOKUP(H$2,行为概览!$D$3:$J$33,7,0)="","",VLOOKUP(H$2,行为概览!$D$3:$J$33,7,0)) | I7: =IF(VLOOKUP(I$2,行为概览!$D$3:$J$33,7,0)="","",VLOOKUP(I$2,行为概览!$D$3:$J$33,7,0)) | J7: =IF(VLOOKUP(J$2,行为概览!$D$3:$J$33,7,0)="","",VLOOKUP(J$2,行为概览!$D$3:$J$33,7,0)) | ... AE7: =IF(VLOOKUP(AE$2,行为概览!$D$3:$J$33,7,0)="","",VLOOKUP(AE$2,行为概览!$D$3:$J$33,7,0)) | AF7: =IF(C7="","",ROUND(C7*玩法行为规划!B7,2)) -> 0 | AG7: =IF(D7="","",ROUND(D7*玩法行为规划!C7,2)) -> 0 | AH7: =IF(E7="","",ROUND(E7*玩法行为规划!D7,2)) -> 0 | AI7: =IF(F7="","",ROUND(F7*玩法行为规划!E7,2)) -> 0 | AJ7: =IF(G7="","",ROUND(G7*玩法行为规划!F7,2)) | AK7: =IF(H7="","",ROUND(H7*玩法行为规划!G7,2)) | AL7: =IF(I7="","",ROUND(I7*玩法行为规划!H7,2)) | AM7: =IF(J7="","",ROUND(J7*玩法行为规划!I7,2)) | ... BH7: =IF(AE7="","",ROUND(AE7*玩法行为规划!AD7,2)) | BI7: =SUM(AF7:BF7) -> 52 | BJ7: =B7*BI7 -> 104000 | BK7: =ROUND(B7*(4+MAX(A7-30,0)*0.6),-2) -> 8000 | BM7: =BK7/BN7 -> 1 | BN7: =INT(BJ7*升级节奏!G7+BK7) -> 8000 | BO7: =ROUND(B7/90,0) -> 22
A8: 6 | B8: =升级节奏!C8 -> 2400 | C8: =IF(VLOOKUP(C$2,行为概览!$D$3:$J$33,7,0)="","",VLOOKUP(C$2,行为概览!$D$3:$J$33,7,0)) -> 50 | D8: =IF(VLOOKUP(D$2,行为概览!$D$3:$J$33,7,0)="","",VLOOKUP(D$2,行为概览!$D$3:$J$33,7,0)) -> 3.3 | E8: =IF(VLOOKUP(E$2,行为概览!$D$3:$J$33,7,0)="","",VLOOKUP(E$2,行为概览!$D$3:$J$33,7,0)) -> 30 | F8: =IF(VLOOKUP(F$2,行为概览!$D$3:$J$33,7,0)="","",VLOOKUP(F$2,行为概览!$D$3:$J$33,7,0)) -> 15 | G8: =IF(VLOOKUP(G$2,行为概览!$D$3:$J$33,7,0)="","",VLOOKUP(G$2,行为概览!$D$3:$J$33,7,0)) | H8: =IF(VLOOKUP(H$2,行为概览!$D$3:$J$33,7,0)="","",VLOOKUP(H$2,行为概览!$D$3:$J$33,7,0)) | I8: =IF(VLOOKUP(I$2,行为概览!$D$3:$J$33,7,0)="","",VLOOKUP(I$2,行为概览!$D$3:$J$33,7,0)) | J8: =IF(VLOOKUP(J$2,行为概览!$D$3:$J$33,7,0)="","",VLOOKUP(J$2,行为概览!$D$3:$J$33,7,0)) | ... AE8: =IF(VLOOKUP(AE$2,行为概览!$D$3:$J$33,7,0)="","",VLOOKUP(AE$2,行为概览!$D$3:$J$33,7,0)) | AF8: =IF(C8="","",ROUND(C8*玩法行为规划!B8,2)) -> 0 | AG8: =IF(D8="","",ROUND(D8*玩法行为规划!C8,2)) -> 0 | AH8: =IF(E8="","",ROUND(E8*玩法行为规划!D8,2)) -> 0 | AI8: =IF(F8="","",ROUND(F8*玩法行为规划!E8,2)) -> 0 | AJ8: =IF(G8="","",ROUND(G8*玩法行为规划!F8,2)) | AK8: =IF(H8="","",ROUND(H8*玩法行为规划!G8,2)) | AL8: =IF(I8="","",ROUND(I8*玩法行为规划!H8,2)) | AM8: =IF(J8="","",ROUND(J8*玩法行为规划!I8,2)) | ... BH8: =IF(AE8="","",ROUND(AE8*玩法行为规划!AD8,2)) | BI8: =SUM(AF8:BF8) -> 52 | BJ8: =B8*BI8 -> 124800 | BK8: =ROUND(B8*(4+MAX(A8-30,0)*0.6),-2) -> 9600 | BM8: =BK8/BN8 -> 1 | BN8: =INT(BJ8*升级节奏!G8+BK8) -> 9600 | BO8: =ROUND(B8/90,0) -> 27
A9: 7 | B9: =升级节奏!C9 -> 2800 | C9: =IF(VLOOKUP(C$2,行为概览!$D$3:$J$33,7,0)="","",VLOOKUP(C$2,行为概览!$D$3:$J$33,7,0)) -> 50 | D9: =IF(VLOOKUP(D$2,行为概览!$D$3:$J$33,7,0)="","",VLOOKUP(D$2,行为概览!$D$3:$J$33,7,0)) -> 3.3 | E9: =IF(VLOOKUP(E$2,行为概览!$D$3:$J$33,7,0)="","",VLOOKUP(E$2,行为概览!$D$3:$J$33,7,0)) -> 30 | F9: =IF(VLOOKUP(F$2,行为概览!$D$3:$J$33,7,0)="","",VLOOKUP(F$2,行为概览!$D$3:$J$33,7,0)) -> 15 | G9: =IF(VLOOKUP(G$2,行为概览!$D$3:$J$33,7,0)="","",VLOOKUP(G$2,行为概览!$D$3:$J$33,7,0)) | H9: =IF(VLOOKUP(H$2,行为概览!$D$3:$J$33,7,0)="","",VLOOKUP(H$2,行为概览!$D$3:$J$33,7,0)) | I9: =IF(VLOOKUP(I$2,行为概览!$D$3:$J$33,7,0)="","",VLOOKUP(I$2,行为概览!$D$3:$J$33,7,0)) | J9: =IF(VLOOKUP(J$2,行为概览!$D$3:$J$33,7,0)="","",VLOOKUP(J$2,行为概览!$D$3:$J$33,7,0)) | ... AE9: =IF(VLOOKUP(AE$2,行为概览!$D$3:$J$33,7,0)="","",VLOOKUP(AE$2,行为概览!$D$3:$J$33,7,0)) | AF9: =IF(C9="","",ROUND(C9*玩法行为规划!B9,2)) -> 0 | AG9: =IF(D9="","",ROUND(D9*玩法行为规划!C9,2)) -> 0 | AH9: =IF(E9="","",ROUND(E9*玩法行为规划!D9,2)) -> 0 | AI9: =IF(F9="","",ROUND(F9*玩法行为规划!E9,2)) -> 0 | AJ9: =IF(G9="","",ROUND(G9*玩法行为规划!F9,2)) | AK9: =IF(H9="","",ROUND(H9*玩法行为规划!G9,2)) | AL9: =IF(I9="","",ROUND(I9*玩法行为规划!H9,2)) | AM9: =IF(J9="","",ROUND(J9*玩法行为规划!I9,2)) | ... BH9: =IF(AE9="","",ROUND(AE9*玩法行为规划!AD9,2)) | BI9: =SUM(AF9:BF9) -> 52 | BJ9: =B9*BI9 -> 145600 | BK9: =ROUND(B9*(4+MAX(A9-30,0)*0.6),-2) -> 11200 | BM9: =BK9/BN9 -> 1 | BN9: =INT(BJ9*升级节奏!G9+BK9) -> 11200 | BO9: =ROUND(B9/90,0) -> 31
A10: 8 | B10: =升级节奏!C10 -> 3200 | C10: =IF(VLOOKUP(C$2,行为概览!$D$3:$J$33,7,0)="","",VLOOKUP(C$2,行为概览!$D$3:$J$33,7,0)) -> 50 | D10: =IF(VLOOKUP(D$2,行为概览!$D$3:$J$33,7,0)="","",VLOOKUP(D$2,行为概览!$D$3:$J$33,7,0)) -> 3.3 | E10: =IF(VLOOKUP(E$2,行为概览!$D$3:$J$33,7,0)="","",VLOOKUP(E$2,行为概览!$D$3:$J$33,7,0)) -> 30 | F10: =IF(VLOOKUP(F$2,行为概览!$D$3:$J$33,7,0)="","",VLOOKUP(F$2,行为概览!$D$3:$J$33,7,0)) -> 15 | G10: =IF(VLOOKUP(G$2,行为概览!$D$3:$J$33,7,0)="","",VLOOKUP(G$2,行为概览!$D$3:$J$33,7,0)) | H10: =IF(VLOOKUP(H$2,行为概览!$D$3:$J$33,7,0)="","",VLOOKUP(H$2,行为概览!$D$3:$J$33,7,0)) | I10: =IF(VLOOKUP(I$2,行为概览!$D$3:$J$33,7,0)="","",VLOOKUP(I$2,行为概览!$D$3:$J$33,7,0)) | J10: =IF(VLOOKUP(J$2,行为概览!$D$3:$J$33,7,0)="","",VLOOKUP(J$2,行为概览!$D$3:$J$33,7,0)) | ... AE10: =IF(VLOOKUP(AE$2,行为概览!$D$3:$J$33,7,0)="","",VLOOKUP(AE$2,行为概览!$D$3:$J$33,7,0)) | AF10: =IF(C10="","",ROUND(C10*玩法行为规划!B10,2)) -> 0 | AG10: =IF(D10="","",ROUND(D10*玩法行为规划!C10,2)) -> 0 | AH10: =IF(E10="","",ROUND(E10*玩法行为规划!D10,2)) -> 0 | AI10: =IF(F10="","",ROUND(F10*玩法行为规划!E10,2)) -> 0 | AJ10: =IF(G10="","",ROUND(G10*玩法行为规划!F10,2)) | AK10: =IF(H10="","",ROUND(H10*玩法行为规划!G10,2)) | AL10: =IF(I10="","",ROUND(I10*玩法行为规划!H10,2)) | AM10: =IF(J10="","",ROUND(J10*玩法行为规划!I10,2)) | ... BH10: =IF(AE10="","",ROUND(AE10*玩法行为规划!AD10,2)) | BI10: =SUM(AF10:BF10) -> 52 | BJ10: =B10*BI10 -> 166400 | BK10: =ROUND(B10*(4+MAX(A10-30,0)*0.6),-2) -> 12800 | BM10: =BK10/BN10 -> 1 | BN10: =INT(BJ10*升级节奏!G10+BK10) -> 12800 | BO10: =ROUND(B10/90,0) -> 36
A11: 9 | B11: =升级节奏!C11 -> 3600 | C11: =IF(VLOOKUP(C$2,行为概览!$D$3:$J$33,7,0)="","",VLOOKUP(C$2,行为概览!$D$3:$J$33,7,0)) -> 50 | D11: =IF(VLOOKUP(D$2,行为概览!$D$3:$J$33,7,0)="","",VLOOKUP(D$2,行为概览!$D$3:$J$33,7,0)) -> 3.3 | E11: =IF(VLOOKUP(E$2,行为概览!$D$3:$J$33,7,0)="","",VLOOKUP(E$2,行为概览!$D$3:$J$33,7,0)) -> 30 | F11: =IF(VLOOKUP(F$2,行为概览!$D$3:$J$33,7,0)="","",VLOOKUP(F$2,行为概览!$D$3:$J$33,7,0)) -> 15 | G11: =IF(VLOOKUP(G$2,行为概览!$D$3:$J$33,7,0)="","",VLOOKUP(G$2,行为概览!$D$3:$J$33,7,0)) | H11: =IF(VLOOKUP(H$2,行为概览!$D$3:$J$33,7,0)="","",VLOOKUP(H$2,行为概览!$D$3:$J$33,7,0)) | I11: =IF(VLOOKUP(I$2,行为概览!$D$3:$J$33,7,0)="","",VLOOKUP(I$2,行为概览!$D$3:$J$33,7,0)) | J11: =IF(VLOOKUP(J$2,行为概览!$D$3:$J$33,7,0)="","",VLOOKUP(J$2,行为概览!$D$3:$J$33,7,0)) | ... AE11: =IF(VLOOKUP(AE$2,行为概览!$D$3:$J$33,7,0)="","",VLOOKUP(AE$2,行为概览!$D$3:$J$33,7,0)) | AF11: =IF(C11="","",ROUND(C11*玩法行为规划!B11,2)) -> 0 | AG11: =IF(D11="","",ROUND(D11*玩法行为规划!C11,2)) -> 0 | AH11: =IF(E11="","",ROUND(E11*玩法行为规划!D11,2)) -> 0 | AI11: =IF(F11="","",ROUND(F11*玩法行为规划!E11,2)) -> 0 | AJ11: =IF(G11="","",ROUND(G11*玩法行为规划!F11,2)) | AK11: =IF(H11="","",ROUND(H11*玩法行为规划!G11,2)) | AL11: =IF(I11="","",ROUND(I11*玩法行为规划!H11,2)) | AM11: =IF(J11="","",ROUND(J11*玩法行为规划!I11,2)) | ... BH11: =IF(AE11="","",ROUND(AE11*玩法行为规划!AD11,2)) | BI11: =SUM(AF11:BF11) -> 52 | BJ11: =B11*BI11 -> 187200 | BK11: =ROUND(B11*(4+MAX(A11-30,0)*0.6),-2) -> 14400 | BM11: =BK11/BN11 -> 1 | BN11: =INT(BJ11*升级节奏!G11+BK11) -> 14400 | BO11: =ROUND(B11/90,0) -> 40
A12: 10 | B12: =升级节奏!C12 -> 4000 | C12: =IF(VLOOKUP(C$2,行为概览!$D$3:$J$33,7,0)="","",VLOOKUP(C$2,行为概览!$D$3:$J$33,7,0)) -> 50 | D12: =IF(VLOOKUP(D$2,行为概览!$D$3:$J$33,7,0)="","",VLOOKUP(D$2,行为概览!$D$3:$J$33,7,0)) -> 3.3 | E12: =IF(VLOOKUP(E$2,行为概览!$D$3:$J$33,7,0)="","",VLOOKUP(E$2,行为概览!$D$3:$J$33,7,0)) -> 30 | F12: =IF(VLOOKUP(F$2,行为概览!$D$3:$J$33,7,0)="","",VLOOKUP(F$2,行为概览!$D$3:$J$33,7,0)) -> 15 | G12: =IF(VLOOKUP(G$2,行为概览!$D$3:$J$33,7,0)="","",VLOOKUP(G$2,行为概览!$D$3:$J$33,7,0)) | H12: =IF(VLOOKUP(H$2,行为概览!$D$3:$J$33,7,0)="","",VLOOKUP(H$2,行为概览!$D$3:$J$33,7,0)) | I12: =IF(VLOOKUP(I$2,行为概览!$D$3:$J$33,7,0)="","",VLOOKUP(I$2,行为概览!$D$3:$J$33,7,0)) | J12: =IF(VLOOKUP(J$2,行为概览!$D$3:$J$33,7,0)="","",VLOOKUP(J$2,行为概览!$D$3:$J$33,7,0)) | ... AE12: =IF(VLOOKUP(AE$2,行为概览!$D$3:$J$33,7,0)="","",VLOOKUP(AE$2,行为概览!$D$3:$J$33,7,0)) | AF12: =IF(C12="","",ROUND(C12*玩法行为规划!B12,2)) -> 0 | AG12: =IF(D12="","",ROUND(D12*玩法行为规划!C12,2)) -> 0 | AH12: =IF(E12="","",ROUND(E12*玩法行为规划!D12,2)) -> 0 | AI12: =IF(F12="","",ROUND(F12*玩法行为规划!E12,2)) -> 0 | AJ12: =IF(G12="","",ROUND(G12*玩法行为规划!F12,2)) | AK12: =IF(H12="","",ROUND(H12*玩法行为规划!G12,2)) | AL12: =IF(I12="","",ROUND(I12*玩法行为规划!H12,2)) | AM12: =IF(J12="","",ROUND(J12*玩法行为规划!I12,2)) | ... BH12: =IF(AE12="","",ROUND(AE12*玩法行为规划!AD12,2)) | BI12: =SUM(AF12:BF12) -> 64.83 | BJ12: =B12*BI12 -> 259320 | BK12: =ROUND(B12*(4+MAX(A12-30,0)*0.6),-2) -> 16000 | BL12: =IF(--RIGHT(A12,1)=0,SUM(BK12:BK21),"") -> 232000 | BM12: =BK12/BN12 -> 1 | BN12: =INT(BJ12*升级节奏!G12+BK12) -> 16000 | BO12: =ROUND(B12/90,0) -> 44
A13: 11 | B13: =升级节奏!C13 -> 4400 | C13: =IF(VLOOKUP(C$2,行为概览!$D$3:$J$33,7,0)="","",VLOOKUP(C$2,行为概览!$D$3:$J$33,7,0)) -> 50 | D13: =IF(VLOOKUP(D$2,行为概览!$D$3:$J$33,7,0)="","",VLOOKUP(D$2,行为概览!$D$3:$J$33,7,0)) -> 3.3 | E13: =IF(VLOOKUP(E$2,行为概览!$D$3:$J$33,7,0)="","",VLOOKUP(E$2,行为概览!$D$3:$J$33,7,0)) -> 30 | F13: =IF(VLOOKUP(F$2,行为概览!$D$3:$J$33,7,0)="","",VLOOKUP(F$2,行为概览!$D$3:$J$33,7,0)) -> 15 | G13: =IF(VLOOKUP(G$2,行为概览!$D$3:$J$33,7,0)="","",VLOOKUP(G$2,行为概览!$D$3:$J$33,7,0)) | H13: =IF(VLOOKUP(H$2,行为概览!$D$3:$J$33,7,0)="","",VLOOKUP(H$2,行为概览!$D$3:$J$33,7,0)) | I13: =IF(VLOOKUP(I$2,行为概览!$D$3:$J$33,7,0)="","",VLOOKUP(I$2,行为概览!$D$3:$J$33,7,0)) | J13: =IF(VLOOKUP(J$2,行为概览!$D$3:$J$33,7,0)="","",VLOOKUP(J$2,行为概览!$D$3:$J$33,7,0)) | ... AE13: =IF(VLOOKUP(AE$2,行为概览!$D$3:$J$33,7,0)="","",VLOOKUP(AE$2,行为概览!$D$3:$J$33,7,0)) | AF13: =IF(C13="","",ROUND(C13*玩法行为规划!B13,2)) -> 0 | AG13: =IF(D13="","",ROUND(D13*玩法行为规划!C13,2)) -> 0 | AH13: =IF(E13="","",ROUND(E13*玩法行为规划!D13,2)) -> 0 | AI13: =IF(F13="","",ROUND(F13*玩法行为规划!E13,2)) -> 0 | AJ13: =IF(G13="","",ROUND(G13*玩法行为规划!F13,2)) | AK13: =IF(H13="","",ROUND(H13*玩法行为规划!G13,2)) | AL13: =IF(I13="","",ROUND(I13*玩法行为规划!H13,2)) | AM13: =IF(J13="","",ROUND(J13*玩法行为规划!I13,2)) | ... BH13: =IF(AE13="","",ROUND(AE13*玩法行为规划!AD13,2)) | BI13: =SUM(AF13:BF13) -> 64.83 | BJ13: =B13*BI13 -> 285252 | BK13: =ROUND(B13*(4+MAX(A13-30,0)*0.6),-2) -> 17600 | BL13: =IF(--RIGHT(A13,1)=0,SUM(BK13:BK22),"") | BM13: =BK13/BN13 -> 1 | BN13: =INT(BJ13*升级节奏!G13+BK13) -> 17600 | BO13: =ROUND(B13/90,0) -> 49
A14: 12 | B14: =升级节奏!C14 -> 4800 | C14: =IF(VLOOKUP(C$2,行为概览!$D$3:$J$33,7,0)="","",VLOOKUP(C$2,行为概览!$D$3:$J$33,7,0)) -> 50 | D14: =IF(VLOOKUP(D$2,行为概览!$D$3:$J$33,7,0)="","",VLOOKUP(D$2,行为概览!$D$3:$J$33,7,0)) -> 3.3 | E14: =IF(VLOOKUP(E$2,行为概览!$D$3:$J$33,7,0)="","",VLOOKUP(E$2,行为概览!$D$3:$J$33,7,0)) -> 30 | F14: =IF(VLOOKUP(F$2,行为概览!$D$3:$J$33,7,0)="","",VLOOKUP(F$2,行为概览!$D$3:$J$33,7,0)) -> 15 | G14: =IF(VLOOKUP(G$2,行为概览!$D$3:$J$33,7,0)="","",VLOOKUP(G$2,行为概览!$D$3:$J$33,7,0)) | H14: =IF(VLOOKUP(H$2,行为概览!$D$3:$J$33,7,0)="","",VLOOKUP(H$2,行为概览!$D$3:$J$33,7,0)) | I14: =IF(VLOOKUP(I$2,行为概览!$D$3:$J$33,7,0)="","",VLOOKUP(I$2,行为概览!$D$3:$J$33,7,0)) | J14: =IF(VLOOKUP(J$2,行为概览!$D$3:$J$33,7,0)="","",VLOOKUP(J$2,行为概览!$D$3:$J$33,7,0)) | ... AE14: =IF(VLOOKUP(AE$2,行为概览!$D$3:$J$33,7,0)="","",VLOOKUP(AE$2,行为概览!$D$3:$J$33,7,0)) | AF14: =IF(C14="","",ROUND(C14*玩法行为规划!B14,2)) -> 0 | AG14: =IF(D14="","",ROUND(D14*玩法行为规划!C14,2)) -> 0 | AH14: =IF(E14="","",ROUND(E14*玩法行为规划!D14,2)) -> 0 | AI14: =IF(F14="","",ROUND(F14*玩法行为规划!E14,2)) -> 0 | AJ14: =IF(G14="","",ROUND(G14*玩法行为规划!F14,2)) | AK14: =IF(H14="","",ROUND(H14*玩法行为规划!G14,2)) | AL14: =IF(I14="","",ROUND(I14*玩法行为规划!H14,2)) | AM14: =IF(J14="","",ROUND(J14*玩法行为规划!I14,2)) | ... BH14: =IF(AE14="","",ROUND(AE14*玩法行为规划!AD14,2)) | BI14: =SUM(AF14:BF14) -> 64.83 | BJ14: =B14*BI14 -> 311184 | BK14: =ROUND(B14*(4+MAX(A14-30,0)*0.6),-2) -> 19200 | BL14: =IF(--RIGHT(A14,1)=0,SUM(BK14:BK23),"") | BM14: =BK14/BN14 -> 1 | BN14: =INT(BJ14*升级节奏!G14+BK14) -> 19200 | BO14: =ROUND(B14/90,0) -> 53
A15: 13 | B15: =升级节奏!C15 -> 5200 | C15: =IF(VLOOKUP(C$2,行为概览!$D$3:$J$33,7,0)="","",VLOOKUP(C$2,行为概览!$D$3:$J$33,7,0)) -> 50 | D15: =IF(VLOOKUP(D$2,行为概览!$D$3:$J$33,7,0)="","",VLOOKUP(D$2,行为概览!$D$3:$J$33,7,0)) -> 3.3 | E15: =IF(VLOOKUP(E$2,行为概览!$D$3:$J$33,7,0)="","",VLOOKUP(E$2,行为概览!$D$3:$J$33,7,0)) -> 30 | F15: =IF(VLOOKUP(F$2,行为概览!$D$3:$J$33,7,0)="","",VLOOKUP(F$2,行为概览!$D$3:$J$33,7,0)) -> 15 | G15: =IF(VLOOKUP(G$2,行为概览!$D$3:$J$33,7,0)="","",VLOOKUP(G$2,行为概览!$D$3:$J$33,7,0)) | H15: =IF(VLOOKUP(H$2,行为概览!$D$3:$J$33,7,0)="","",VLOOKUP(H$2,行为概览!$D$3:$J$33,7,0)) | I15: =IF(VLOOKUP(I$2,行为概览!$D$3:$J$33,7,0)="","",VLOOKUP(I$2,行为概览!$D$3:$J$33,7,0)) | J15: =IF(VLOOKUP(J$2,行为概览!$D$3:$J$33,7,0)="","",VLOOKUP(J$2,行为概览!$D$3:$J$33,7,0)) | ... AE15: =IF(VLOOKUP(AE$2,行为概览!$D$3:$J$33,7,0)="","",VLOOKUP(AE$2,行为概览!$D$3:$J$33,7,0)) | AF15: =IF(C15="","",ROUND(C15*玩法行为规划!B15,2)) -> 0 | AG15: =IF(D15="","",ROUND(D15*玩法行为规划!C15,2)) -> 0 | AH15: =IF(E15="","",ROUND(E15*玩法行为规划!D15,2)) -> 0 | AI15: =IF(F15="","",ROUND(F15*玩法行为规划!E15,2)) -> 0 | AJ15: =IF(G15="","",ROUND(G15*玩法行为规划!F15,2)) | AK15: =IF(H15="","",ROUND(H15*玩法行为规划!G15,2)) | AL15: =IF(I15="","",ROUND(I15*玩法行为规划!H15,2)) | AM15: =IF(J15="","",ROUND(J15*玩法行为规划!I15,2)) | ... BH15: =IF(AE15="","",ROUND(AE15*玩法行为规划!AD15,2)) | BI15: =SUM(AF15:BF15) -> 64.83 | BJ15: =B15*BI15 -> 337116 | BK15: =ROUND(B15*(4+MAX(A15-30,0)*0.6),-2) -> 20800 | BL15: =IF(--RIGHT(A15,1)=0,SUM(BK15:BK24),"") | BM15: =BK15/BN15 -> 1 | BN15: =INT(BJ15*升级节奏!G15+BK15) -> 20800 | BO15: =ROUND(B15/90,0) -> 58
A16: 14 | B16: =升级节奏!C16 -> 5600 | C16: =IF(VLOOKUP(C$2,行为概览!$D$3:$J$33,7,0)="","",VLOOKUP(C$2,行为概览!$D$3:$J$33,7,0)) -> 50 | D16: =IF(VLOOKUP(D$2,行为概览!$D$3:$J$33,7,0)="","",VLOOKUP(D$2,行为概览!$D$3:$J$33,7,0)) -> 3.3 | E16: =IF(VLOOKUP(E$2,行为概览!$D$3:$J$33,7,0)="","",VLOOKUP(E$2,行为概览!$D$3:$J$33,7,0)) -> 30 | F16: =IF(VLOOKUP(F$2,行为概览!$D$3:$J$33,7,0)="","",VLOOKUP(F$2,行为概览!$D$3:$J$33,7,0)) -> 15 | G16: =IF(VLOOKUP(G$2,行为概览!$D$3:$J$33,7,0)="","",VLOOKUP(G$2,行为概览!$D$3:$J$33,7,0)) | H16: =IF(VLOOKUP(H$2,行为概览!$D$3:$J$33,7,0)="","",VLOOKUP(H$2,行为概览!$D$3:$J$33,7,0)) | I16: =IF(VLOOKUP(I$2,行为概览!$D$3:$J$33,7,0)="","",VLOOKUP(I$2,行为概览!$D$3:$J$33,7,0)) | J16: =IF(VLOOKUP(J$2,行为概览!$D$3:$J$33,7,0)="","",VLOOKUP(J$2,行为概览!$D$3:$J$33,7,0)) | ... AE16: =IF(VLOOKUP(AE$2,行为概览!$D$3:$J$33,7,0)="","",VLOOKUP(AE$2,行为概览!$D$3:$J$33,7,0)) | AF16: =IF(C16="","",ROUND(C16*玩法行为规划!B16,2)) -> 0 | AG16: =IF(D16="","",ROUND(D16*玩法行为规划!C16,2)) -> 0 | AH16: =IF(E16="","",ROUND(E16*玩法行为规划!D16,2)) -> 0 | AI16: =IF(F16="","",ROUND(F16*玩法行为规划!E16,2)) -> 0 | AJ16: =IF(G16="","",ROUND(G16*玩法行为规划!F16,2)) | AK16: =IF(H16="","",ROUND(H16*玩法行为规划!G16,2)) | AL16: =IF(I16="","",ROUND(I16*玩法行为规划!H16,2)) | AM16: =IF(J16="","",ROUND(J16*玩法行为规划!I16,2)) | ... BH16: =IF(AE16="","",ROUND(AE16*玩法行为规划!AD16,2)) | BI16: =SUM(AF16:BF16) -> 64.83 | BJ16: =B16*BI16 -> 363048 | BK16: =ROUND(B16*(4+MAX(A16-30,0)*0.6),-2) -> 22400 | BL16: =IF(--RIGHT(A16,1)=0,SUM(BK16:BK25),"") | BM16: =BK16/BN16 -> 1 | BN16: =INT(BJ16*升级节奏!G16+BK16) -> 22400 | BO16: =ROUND(B16/90,0) -> 62
A17: 15 | B17: =升级节奏!C17 -> 6000 | C17: =IF(VLOOKUP(C$2,行为概览!$D$3:$J$33,7,0)="","",VLOOKUP(C$2,行为概览!$D$3:$J$33,7,0)) -> 50 | D17: =IF(VLOOKUP(D$2,行为概览!$D$3:$J$33,7,0)="","",VLOOKUP(D$2,行为概览!$D$3:$J$33,7,0)) -> 3.3 | E17: =IF(VLOOKUP(E$2,行为概览!$D$3:$J$33,7,0)="","",VLOOKUP(E$2,行为概览!$D$3:$J$33,7,0)) -> 30 | F17: =IF(VLOOKUP(F$2,行为概览!$D$3:$J$33,7,0)="","",VLOOKUP(F$2,行为概览!$D$3:$J$33,7,0)) -> 15 | G17: =IF(VLOOKUP(G$2,行为概览!$D$3:$J$33,7,0)="","",VLOOKUP(G$2,行为概览!$D$3:$J$33,7,0)) | H17: =IF(VLOOKUP(H$2,行为概览!$D$3:$J$33,7,0)="","",VLOOKUP(H$2,行为概览!$D$3:$J$33,7,0)) | I17: =IF(VLOOKUP(I$2,行为概览!$D$3:$J$33,7,0)="","",VLOOKUP(I$2,行为概览!$D$3:$J$33,7,0)) | J17: =IF(VLOOKUP(J$2,行为概览!$D$3:$J$33,7,0)="","",VLOOKUP(J$2,行为概览!$D$3:$J$33,7,0)) | ... AE17: =IF(VLOOKUP(AE$2,行为概览!$D$3:$J$33,7,0)="","",VLOOKUP(AE$2,行为概览!$D$3:$J$33,7,0)) | AF17: =IF(C17="","",ROUND(C17*玩法行为规划!B17,2)) -> 16.67 | AG17: =IF(D17="","",ROUND(D17*玩法行为规划!C17,2)) -> 0 | AH17: =IF(E17="","",ROUND(E17*玩法行为规划!D17,2)) -> 0 | AI17: =IF(F17="","",ROUND(F17*玩法行为规划!E17,2)) -> 0 | AJ17: =IF(G17="","",ROUND(G17*玩法行为规划!F17,2)) | AK17: =IF(H17="","",ROUND(H17*玩法行为规划!G17,2)) | AL17: =IF(I17="","",ROUND(I17*玩法行为规划!H17,2)) | AM17: =IF(J17="","",ROUND(J17*玩法行为规划!I17,2)) | ... BH17: =IF(AE17="","",ROUND(AE17*玩法行为规划!AD17,2)) | BI17: =SUM(AF17:BF17) -> 81.5 | BJ17: =B17*BI17 -> 489000 | BK17: =ROUND(B17*(4+MAX(A17-30,0)*0.6),-2) -> 24000 | BL17: =IF(--RIGHT(A17,1)=0,SUM(BK17:BK26),"") | BM17: =BK17/BN17 -> 1 | BN17: =INT(BJ17*升级节奏!G17+BK17) -> 24000 | BO17: =ROUND(B17/90,0) -> 67
A18: 16 | B18: =升级节奏!C18 -> 6400 | C18: =IF(VLOOKUP(C$2,行为概览!$D$3:$J$33,7,0)="","",VLOOKUP(C$2,行为概览!$D$3:$J$33,7,0)) -> 50 | D18: =IF(VLOOKUP(D$2,行为概览!$D$3:$J$33,7,0)="","",VLOOKUP(D$2,行为概览!$D$3:$J$33,7,0)) -> 3.3 | E18: =IF(VLOOKUP(E$2,行为概览!$D$3:$J$33,7,0)="","",VLOOKUP(E$2,行为概览!$D$3:$J$33,7,0)) -> 30 | F18: =IF(VLOOKUP(F$2,行为概览!$D$3:$J$33,7,0)="","",VLOOKUP(F$2,行为概览!$D$3:$J$33,7,0)) -> 15 | G18: =IF(VLOOKUP(G$2,行为概览!$D$3:$J$33,7,0)="","",VLOOKUP(G$2,行为概览!$D$3:$J$33,7,0)) | H18: =IF(VLOOKUP(H$2,行为概览!$D$3:$J$33,7,0)="","",VLOOKUP(H$2,行为概览!$D$3:$J$33,7,0)) | I18: =IF(VLOOKUP(I$2,行为概览!$D$3:$J$33,7,0)="","",VLOOKUP(I$2,行为概览!$D$3:$J$33,7,0)) | J18: =IF(VLOOKUP(J$2,行为概览!$D$3:$J$33,7,0)="","",VLOOKUP(J$2,行为概览!$D$3:$J$33,7,0)) | ... AE18: =IF(VLOOKUP(AE$2,行为概览!$D$3:$J$33,7,0)="","",VLOOKUP(AE$2,行为概览!$D$3:$J$33,7,0)) | AF18: =IF(C18="","",ROUND(C18*玩法行为规划!B18,2)) -> 16.67 | AG18: =IF(D18="","",ROUND(D18*玩法行为规划!C18,2)) -> 0 | AH18: =IF(E18="","",ROUND(E18*玩法行为规划!D18,2)) -> 0 | AI18: =IF(F18="","",ROUND(F18*玩法行为规划!E18,2)) -> 0 | AJ18: =IF(G18="","",ROUND(G18*玩法行为规划!F18,2)) | AK18: =IF(H18="","",ROUND(H18*玩法行为规划!G18,2)) | AL18: =IF(I18="","",ROUND(I18*玩法行为规划!H18,2)) | AM18: =IF(J18="","",ROUND(J18*玩法行为规划!I18,2)) | ... BH18: =IF(AE18="","",ROUND(AE18*玩法行为规划!AD18,2)) | BI18: =SUM(AF18:BF18) -> 81.5 | BJ18: =B18*BI18 -> 521600 | BK18: =ROUND(B18*(4+MAX(A18-30,0)*0.6),-2) -> 25600 | BL18: =IF(--RIGHT(A18,1)=0,SUM(BK18:BK27),"") | BM18: =BK18/BN18 -> 1 | BN18: =INT(BJ18*升级节奏!G18+BK18) -> 25600 | BO18: =ROUND(B18/90,0) -> 71
A19: 17 | B19: =升级节奏!C19 -> 6800 | C19: =IF(VLOOKUP(C$2,行为概览!$D$3:$J$33,7,0)="","",VLOOKUP(C$2,行为概览!$D$3:$J$33,7,0)) -> 50 | D19: =IF(VLOOKUP(D$2,行为概览!$D$3:$J$33,7,0)="","",VLOOKUP(D$2,行为概览!$D$3:$J$33,7,0)) -> 3.3 | E19: =IF(VLOOKUP(E$2,行为概览!$D$3:$J$33,7,0)="","",VLOOKUP(E$2,行为概览!$D$3:$J$33,7,0)) -> 30 | F19: =IF(VLOOKUP(F$2,行为概览!$D$3:$J$33,7,0)="","",VLOOKUP(F$2,行为概览!$D$3:$J$33,7,0)) -> 15 | G19: =IF(VLOOKUP(G$2,行为概览!$D$3:$J$33,7,0)="","",VLOOKUP(G$2,行为概览!$D$3:$J$33,7,0)) | H19: =IF(VLOOKUP(H$2,行为概览!$D$3:$J$33,7,0)="","",VLOOKUP(H$2,行为概览!$D$3:$J$33,7,0)) | I19: =IF(VLOOKUP(I$2,行为概览!$D$3:$J$33,7,0)="","",VLOOKUP(I$2,行为概览!$D$3:$J$33,7,0)) | J19: =IF(VLOOKUP(J$2,行为概览!$D$3:$J$33,7,0)="","",VLOOKUP(J$2,行为概览!$D$3:$J$33,7,0)) | ... AE19: =IF(VLOOKUP(AE$2,行为概览!$D$3:$J$33,7,0)="","",VLOOKUP(AE$2,行为概览!$D$3:$J$33,7,0)) | AF19: =IF(C19="","",ROUND(C19*玩法行为规划!B19,2)) -> 16.67 | AG19: =IF(D19="","",ROUND(D19*玩法行为规划!C19,2)) -> 0 | AH19: =IF(E19="","",ROUND(E19*玩法行为规划!D19,2)) -> 0 | AI19: =IF(F19="","",ROUND(F19*玩法行为规划!E19,2)) -> 0 | AJ19: =IF(G19="","",ROUND(G19*玩法行为规划!F19,2)) | AK19: =IF(H19="","",ROUND(H19*玩法行为规划!G19,2)) | AL19: =IF(I19="","",ROUND(I19*玩法行为规划!H19,2)) | AM19: =IF(J19="","",ROUND(J19*玩法行为规划!I19,2)) | ... BH19: =IF(AE19="","",ROUND(AE19*玩法行为规划!AD19,2)) | BI19: =SUM(AF19:BF19) -> 81.5 | BJ19: =B19*BI19 -> 554200 | BK19: =ROUND(B19*(4+MAX(A19-30,0)*0.6),-2) -> 27200 | BL19: =IF(--RIGHT(A19,1)=0,SUM(BK19:BK28),"") | BM19: =BK19/BN19 -> 1 | BN19: =INT(BJ19*升级节奏!G19+BK19) -> 27200 | BO19: =ROUND(B19/90,0) -> 76
A20: 18 | B20: =升级节奏!C20 -> 7200 | C20: =IF(VLOOKUP(C$2,行为概览!$D$3:$J$33,7,0)="","",VLOOKUP(C$2,行为概览!$D$3:$J$33,7,0)) -> 50 | D20: =IF(VLOOKUP(D$2,行为概览!$D$3:$J$33,7,0)="","",VLOOKUP(D$2,行为概览!$D$3:$J$33,7,0)) -> 3.3 | E20: =IF(VLOOKUP(E$2,行为概览!$D$3:$J$33,7,0)="","",VLOOKUP(E$2,行为概览!$D$3:$J$33,7,0)) -> 30 | F20: =IF(VLOOKUP(F$2,行为概览!$D$3:$J$33,7,0)="","",VLOOKUP(F$2,行为概览!$D$3:$J$33,7,0)) -> 15 | G20: =IF(VLOOKUP(G$2,行为概览!$D$3:$J$33,7,0)="","",VLOOKUP(G$2,行为概览!$D$3:$J$33,7,0)) | H20: =IF(VLOOKUP(H$2,行为概览!$D$3:$J$33,7,0)="","",VLOOKUP(H$2,行为概览!$D$3:$J$33,7,0)) | I20: =IF(VLOOKUP(I$2,行为概览!$D$3:$J$33,7,0)="","",VLOOKUP(I$2,行为概览!$D$3:$J$33,7,0)) | J20: =IF(VLOOKUP(J$2,行为概览!$D$3:$J$33,7,0)="","",VLOOKUP(J$2,行为概览!$D$3:$J$33,7,0)) | ... AE20: =IF(VLOOKUP(AE$2,行为概览!$D$3:$J$33,7,0)="","",VLOOKUP(AE$2,行为概览!$D$3:$J$33,7,0)) | AF20: =IF(C20="","",ROUND(C20*玩法行为规划!B20,2)) -> 16.67 | AG20: =IF(D20="","",ROUND(D20*玩法行为规划!C20,2)) -> 0 | AH20: =IF(E20="","",ROUND(E20*玩法行为规划!D20,2)) -> 0 | AI20: =IF(F20="","",ROUND(F20*玩法行为规划!E20,2)) -> 0 | AJ20: =IF(G20="","",ROUND(G20*玩法行为规划!F20,2)) | AK20: =IF(H20="","",ROUND(H20*玩法行为规划!G20,2)) | AL20: =IF(I20="","",ROUND(I20*玩法行为规划!H20,2)) | AM20: =IF(J20="","",ROUND(J20*玩法行为规划!I20,2)) | ... BH20: =IF(AE20="","",ROUND(AE20*玩法行为规划!AD20,2)) | BI20: =SUM(AF20:BF20) -> 81.5 | BJ20: =B20*BI20 -> 586800 | BK20: =ROUND(B20*(4+MAX(A20-30,0)*0.6),-2) -> 28800 | BL20: =IF(--RIGHT(A20,1)=0,SUM(BK20:BK29),"") | BM20: =BK20/BN20 -> 1 | BN20: =INT(BJ20*升级节奏!G20+BK20) -> 28800 | BO20: =ROUND(B20/90,0) -> 80
A21: 19 | B21: =升级节奏!C21 -> 7600 | C21: =IF(VLOOKUP(C$2,行为概览!$D$3:$J$33,7,0)="","",VLOOKUP(C$2,行为概览!$D$3:$J$33,7,0)) -> 50 | D21: =IF(VLOOKUP(D$2,行为概览!$D$3:$J$33,7,0)="","",VLOOKUP(D$2,行为概览!$D$3:$J$33,7,0)) -> 3.3 | E21: =IF(VLOOKUP(E$2,行为概览!$D$3:$J$33,7,0)="","",VLOOKUP(E$2,行为概览!$D$3:$J$33,7,0)) -> 30 | F21: =IF(VLOOKUP(F$2,行为概览!$D$3:$J$33,7,0)="","",VLOOKUP(F$2,行为概览!$D$3:$J$33,7,0)) -> 15 | G21: =IF(VLOOKUP(G$2,行为概览!$D$3:$J$33,7,0)="","",VLOOKUP(G$2,行为概览!$D$3:$J$33,7,0)) | H21: =IF(VLOOKUP(H$2,行为概览!$D$3:$J$33,7,0)="","",VLOOKUP(H$2,行为概览!$D$3:$J$33,7,0)) | I21: =IF(VLOOKUP(I$2,行为概览!$D$3:$J$33,7,0)="","",VLOOKUP(I$2,行为概览!$D$3:$J$33,7,0)) | J21: =IF(VLOOKUP(J$2,行为概览!$D$3:$J$33,7,0)="","",VLOOKUP(J$2,行为概览!$D$3:$J$33,7,0)) | ... AE21: =IF(VLOOKUP(AE$2,行为概览!$D$3:$J$33,7,0)="","",VLOOKUP(AE$2,行为概览!$D$3:$J$33,7,0)) | AF21: =IF(C21="","",ROUND(C21*玩法行为规划!B21,2)) -> 16.67 | AG21: =IF(D21="","",ROUND(D21*玩法行为规划!C21,2)) -> 0 | AH21: =IF(E21="","",ROUND(E21*玩法行为规划!D21,2)) -> 0 | AI21: =IF(F21="","",ROUND(F21*玩法行为规划!E21,2)) -> 0 | AJ21: =IF(G21="","",ROUND(G21*玩法行为规划!F21,2)) | AK21: =IF(H21="","",ROUND(H21*玩法行为规划!G21,2)) | AL21: =IF(I21="","",ROUND(I21*玩法行为规划!H21,2)) | AM21: =IF(J21="","",ROUND(J21*玩法行为规划!I21,2)) | ... BH21: =IF(AE21="","",ROUND(AE21*玩法行为规划!AD21,2)) | BI21: =SUM(AF21:BF21) -> 81.5 | BJ21: =B21*BI21 -> 619400 | BK21: =ROUND(B21*(4+MAX(A21-30,0)*0.6),-2) -> 30400 | BL21: =IF(--RIGHT(A21,1)=0,SUM(BK21:BK30),"") | BM21: =BK21/BN21 -> 1 | BN21: =INT(BJ21*升级节奏!G21+BK21) -> 30400 | BO21: =ROUND(B21/90,0) -> 84
A22: 20 | B22: =升级节奏!C22 -> 8000 | C22: =IF(VLOOKUP(C$2,行为概览!$D$3:$J$33,7,0)="","",VLOOKUP(C$2,行为概览!$D$3:$J$33,7,0)) -> 50 | D22: =IF(VLOOKUP(D$2,行为概览!$D$3:$J$33,7,0)="","",VLOOKUP(D$2,行为概览!$D$3:$J$33,7,0)) -> 3.3 | E22: =IF(VLOOKUP(E$2,行为概览!$D$3:$J$33,7,0)="","",VLOOKUP(E$2,行为概览!$D$3:$J$33,7,0)) -> 30 | F22: =IF(VLOOKUP(F$2,行为概览!$D$3:$J$33,7,0)="","",VLOOKUP(F$2,行为概览!$D$3:$J$33,7,0)) -> 15 | G22: =IF(VLOOKUP(G$2,行为概览!$D$3:$J$33,7,0)="","",VLOOKUP(G$2,行为概览!$D$3:$J$33,7,0)) | H22: =IF(VLOOKUP(H$2,行为概览!$D$3:$J$33,7,0)="","",VLOOKUP(H$2,行为概览!$D$3:$J$33,7,0)) | I22: =IF(VLOOKUP(I$2,行为概览!$D$3:$J$33,7,0)="","",VLOOKUP(I$2,行为概览!$D$3:$J$33,7,0)) | J22: =IF(VLOOKUP(J$2,行为概览!$D$3:$J$33,7,0)="","",VLOOKUP(J$2,行为概览!$D$3:$J$33,7,0)) | ... AE22: =IF(VLOOKUP(AE$2,行为概览!$D$3:$J$33,7,0)="","",VLOOKUP(AE$2,行为概览!$D$3:$J$33,7,0)) | AF22: =IF(C22="","",ROUND(C22*玩法行为规划!B22,2)) -> 16.67 | AG22: =IF(D22="","",ROUND(D22*玩法行为规划!C22,2)) -> 6.6 | AH22: =IF(E22="","",ROUND(E22*玩法行为规划!D22,2)) -> 2.5 | AI22: =IF(F22="","",ROUND(F22*玩法行为规划!E22,2)) -> 0 | AJ22: =IF(G22="","",ROUND(G22*玩法行为规划!F22,2)) | AK22: =IF(H22="","",ROUND(H22*玩法行为规划!G22,2)) | AL22: =IF(I22="","",ROUND(I22*玩法行为规划!H22,2)) | AM22: =IF(J22="","",ROUND(J22*玩法行为规划!I22,2)) | ... BH22: =IF(AE22="","",ROUND(AE22*玩法行为规划!AD22,2)) | BI22: =SUM(AF22:BF22) -> 103.1 | BJ22: =B22*BI22 -> 824800 | BK22: =ROUND(B22*(4+MAX(A22-30,0)*0.6),-2) -> 32000 | BL22: =IF(--RIGHT(A22,1)=0,SUM(BK22:BK31),"") -> 392000 | BM22: =BK22/BN22 -> 1 | BN22: =INT(BJ22*升级节奏!G22+BK22) -> 32000 | BO22: =ROUND(B22/90,0) -> 89
A23: 21 | B23: =升级节奏!C23 -> 8400 | C23: =IF(VLOOKUP(C$2,行为概览!$D$3:$J$33,7,0)="","",VLOOKUP(C$2,行为概览!$D$3:$J$33,7,0)) -> 50 | D23: =IF(VLOOKUP(D$2,行为概览!$D$3:$J$33,7,0)="","",VLOOKUP(D$2,行为概览!$D$3:$J$33,7,0)) -> 3.3 | E23: =IF(VLOOKUP(E$2,行为概览!$D$3:$J$33,7,0)="","",VLOOKUP(E$2,行为概览!$D$3:$J$33,7,0)) -> 30 | F23: =IF(VLOOKUP(F$2,行为概览!$D$3:$J$33,7,0)="","",VLOOKUP(F$2,行为概览!$D$3:$J$33,7,0)) -> 15 | G23: =IF(VLOOKUP(G$2,行为概览!$D$3:$J$33,7,0)="","",VLOOKUP(G$2,行为概览!$D$3:$J$33,7,0)) | H23: =IF(VLOOKUP(H$2,行为概览!$D$3:$J$33,7,0)="","",VLOOKUP(H$2,行为概览!$D$3:$J$33,7,0)) | I23: =IF(VLOOKUP(I$2,行为概览!$D$3:$J$33,7,0)="","",VLOOKUP(I$2,行为概览!$D$3:$J$33,7,0)) | J23: =IF(VLOOKUP(J$2,行为概览!$D$3:$J$33,7,0)="","",VLOOKUP(J$2,行为概览!$D$3:$J$33,7,0)) | ... AE23: =IF(VLOOKUP(AE$2,行为概览!$D$3:$J$33,7,0)="","",VLOOKUP(AE$2,行为概览!$D$3:$J$33,7,0)) | AF23: =IF(C23="","",ROUND(C23*玩法行为规划!B23,2)) -> 16.67 | AG23: =IF(D23="","",ROUND(D23*玩法行为规划!C23,2)) -> 6.6 | AH23: =IF(E23="","",ROUND(E23*玩法行为规划!D23,2)) -> 2.5 | AI23: =IF(F23="","",ROUND(F23*玩法行为规划!E23,2)) -> 0 | AJ23: =IF(G23="","",ROUND(G23*玩法行为规划!F23,2)) | AK23: =IF(H23="","",ROUND(H23*玩法行为规划!G23,2)) | AL23: =IF(I23="","",ROUND(I23*玩法行为规划!H23,2)) | AM23: =IF(J23="","",ROUND(J23*玩法行为规划!I23,2)) | ... BH23: =IF(AE23="","",ROUND(AE23*玩法行为规划!AD23,2)) | BI23: =SUM(AF23:BF23) -> 103.1 | BJ23: =B23*BI23 -> 866040 | BK23: =ROUND(B23*(4+MAX(A23-30,0)*0.6),-2) -> 33600 | BL23: =IF(--RIGHT(A23,1)=0,SUM(BK23:BK32),"") | BM23: =BK23/BN23 -> 1 | BN23: =INT(BJ23*升级节奏!G23+BK23) -> 33600 | BO23: =ROUND(B23/90,0) -> 93
... A61: 59 | B61: =升级节奏!C61 -> 23600 | C61: =IF(VLOOKUP(C$2,行为概览!$D$3:$J$33,7,0)="","",VLOOKUP(C$2,行为概览!$D$3:$J$33,7,0)) -> 50 | D61: =IF(VLOOKUP(D$2,行为概览!$D$3:$J$33,7,0)="","",VLOOKUP(D$2,行为概览!$D$3:$J$33,7,0)) -> 3.3 | E61: =IF(VLOOKUP(E$2,行为概览!$D$3:$J$33,7,0)="","",VLOOKUP(E$2,行为概览!$D$3:$J$33,7,0)) -> 30 | F61: =IF(VLOOKUP(F$2,行为概览!$D$3:$J$33,7,0)="","",VLOOKUP(F$2,行为概览!$D$3:$J$33,7,0)) -> 15 | G61: =IF(VLOOKUP(G$2,行为概览!$D$3:$J$33,7,0)="","",VLOOKUP(G$2,行为概览!$D$3:$J$33,7,0)) | H61: =IF(VLOOKUP(H$2,行为概览!$D$3:$J$33,7,0)="","",VLOOKUP(H$2,行为概览!$D$3:$J$33,7,0)) | I61: =IF(VLOOKUP(I$2,行为概览!$D$3:$J$33,7,0)="","",VLOOKUP(I$2,行为概览!$D$3:$J$33,7,0)) | J61: =IF(VLOOKUP(J$2,行为概览!$D$3:$J$33,7,0)="","",VLOOKUP(J$2,行为概览!$D$3:$J$33,7,0)) | ... AE61: =IF(VLOOKUP(AE$2,行为概览!$D$3:$J$33,7,0)="","",VLOOKUP(AE$2,行为概览!$D$3:$J$33,7,0)) | AF61: =IF(C61="","",ROUND(C61*玩法行为规划!B61,2)) -> 16.67 | AG61: =IF(D61="","",ROUND(D61*玩法行为规划!C61,2)) -> 6.6 | AH61: =IF(E61="","",ROUND(E61*玩法行为规划!D61,2)) -> 2.5 | AI61: =IF(F61="","",ROUND(F61*玩法行为规划!E61,2)) -> 15 | AJ61: =IF(G61="","",ROUND(G61*玩法行为规划!F61,2)) | AK61: =IF(H61="","",ROUND(H61*玩法行为规划!G61,2)) | AL61: =IF(I61="","",ROUND(I61*玩法行为规划!H61,2)) | AM61: =IF(J61="","",ROUND(J61*玩法行为规划!I61,2)) | ... BH61: =IF(AE61="","",ROUND(AE61*玩法行为规划!AD61,2)) | BI61: =SUM(AF61:BF61) -> 200.77 | BJ61: =B61*BI61 -> 4738172 | BK61: =ROUND(B61*(4+MAX(A61-30,0)*0.6),-2) -> 505000 | BL61: =IF(--RIGHT(A61,1)=0,SUM(BK61:BK70),"") | BM61: =BK61/BN61 -> 0.10638639 | BN61: =INT(BJ61*升级节奏!G61+BK61) -> 4746848 | BO61: =ROUND(B61/90,0) -> 262
A62: 60 | B62: =升级节奏!C62 -> 24000 | C62: =IF(VLOOKUP(C$2,行为概览!$D$3:$J$33,7,0)="","",VLOOKUP(C$2,行为概览!$D$3:$J$33,7,0)) -> 50 | D62: =IF(VLOOKUP(D$2,行为概览!$D$3:$J$33,7,0)="","",VLOOKUP(D$2,行为概览!$D$3:$J$33,7,0)) -> 3.3 | E62: =IF(VLOOKUP(E$2,行为概览!$D$3:$J$33,7,0)="","",VLOOKUP(E$2,行为概览!$D$3:$J$33,7,0)) -> 30 | F62: =IF(VLOOKUP(F$2,行为概览!$D$3:$J$33,7,0)="","",VLOOKUP(F$2,行为概览!$D$3:$J$33,7,0)) -> 15 | G62: =IF(VLOOKUP(G$2,行为概览!$D$3:$J$33,7,0)="","",VLOOKUP(G$2,行为概览!$D$3:$J$33,7,0)) | H62: =IF(VLOOKUP(H$2,行为概览!$D$3:$J$33,7,0)="","",VLOOKUP(H$2,行为概览!$D$3:$J$33,7,0)) | I62: =IF(VLOOKUP(I$2,行为概览!$D$3:$J$33,7,0)="","",VLOOKUP(I$2,行为概览!$D$3:$J$33,7,0)) | J62: =IF(VLOOKUP(J$2,行为概览!$D$3:$J$33,7,0)="","",VLOOKUP(J$2,行为概览!$D$3:$J$33,7,0)) | ... AE62: =IF(VLOOKUP(AE$2,行为概览!$D$3:$J$33,7,0)="","",VLOOKUP(AE$2,行为概览!$D$3:$J$33,7,0)) | AF62: =IF(C62="","",ROUND(C62*玩法行为规划!B62,2)) -> 16.67 | AG62: =IF(D62="","",ROUND(D62*玩法行为规划!C62,2)) -> 6.6 | AH62: =IF(E62="","",ROUND(E62*玩法行为规划!D62,2)) -> 2.5 | AI62: =IF(F62="","",ROUND(F62*玩法行为规划!E62,2)) -> 15 | AJ62: =IF(G62="","",ROUND(G62*玩法行为规划!F62,2)) | AK62: =IF(H62="","",ROUND(H62*玩法行为规划!G62,2)) | AL62: =IF(I62="","",ROUND(I62*玩法行为规划!H62,2)) | AM62: =IF(J62="","",ROUND(J62*玩法行为规划!I62,2)) | ... BH62: =IF(AE62="","",ROUND(AE62*玩法行为规划!AD62,2)) | BI62: =SUM(AF62:BF62) -> 200.77 | BJ62: =B62*BI62 -> 4818480 | BK62: =ROUND(B62*(5+MAX(A62-30,0)*1),-2) -> 840000 | BL62: =IF(--RIGHT(A62,1)=0,SUM(BK62:BK71),"") -> 10224000 | BM62: =BK62/BN62 -> 0.12384281 | BN62: =INT(BJ62*升级节奏!G62+BK62) -> 6782792 | BO62: =ROUND(B62/90,0) -> 267
A63: 61 | B63: =升级节奏!C63 -> 24400 | C63: =IF(VLOOKUP(C$2,行为概览!$D$3:$J$33,7,0)="","",VLOOKUP(C$2,行为概览!$D$3:$J$33,7,0)) -> 50 | D63: =IF(VLOOKUP(D$2,行为概览!$D$3:$J$33,7,0)="","",VLOOKUP(D$2,行为概览!$D$3:$J$33,7,0)) -> 3.3 | E63: =IF(VLOOKUP(E$2,行为概览!$D$3:$J$33,7,0)="","",VLOOKUP(E$2,行为概览!$D$3:$J$33,7,0)) -> 30 | F63: =IF(VLOOKUP(F$2,行为概览!$D$3:$J$33,7,0)="","",VLOOKUP(F$2,行为概览!$D$3:$J$33,7,0)) -> 15 | G63: =IF(VLOOKUP(G$2,行为概览!$D$3:$J$33,7,0)="","",VLOOKUP(G$2,行为概览!$D$3:$J$33,7,0)) | H63: =IF(VLOOKUP(H$2,行为概览!$D$3:$J$33,7,0)="","",VLOOKUP(H$2,行为概览!$D$3:$J$33,7,0)) | I63: =IF(VLOOKUP(I$2,行为概览!$D$3:$J$33,7,0)="","",VLOOKUP(I$2,行为概览!$D$3:$J$33,7,0)) | J63: =IF(VLOOKUP(J$2,行为概览!$D$3:$J$33,7,0)="","",VLOOKUP(J$2,行为概览!$D$3:$J$33,7,0)) | ... AE63: =IF(VLOOKUP(AE$2,行为概览!$D$3:$J$33,7,0)="","",VLOOKUP(AE$2,行为概览!$D$3:$J$33,7,0)) | AF63: =IF(C63="","",ROUND(C63*玩法行为规划!B63,2)) -> 16.67 | AG63: =IF(D63="","",ROUND(D63*玩法行为规划!C63,2)) -> 6.6 | AH63: =IF(E63="","",ROUND(E63*玩法行为规划!D63,2)) -> 2.5 | AI63: =IF(F63="","",ROUND(F63*玩法行为规划!E63,2)) -> 15 | AJ63: =IF(G63="","",ROUND(G63*玩法行为规划!F63,2)) | AK63: =IF(H63="","",ROUND(H63*玩法行为规划!G63,2)) | AL63: =IF(I63="","",ROUND(I63*玩法行为规划!H63,2)) | AM63: =IF(J63="","",ROUND(J63*玩法行为规划!I63,2)) | ... BH63: =IF(AE63="","",ROUND(AE63*玩法行为规划!AD63,2)) | BI63: =SUM(AF63:BF63) -> 200.77 | BJ63: =B63*BI63 -> 4898788 | BK63: =ROUND(B63*(5+MAX(A63-30,0)*1),-2) -> 878400 | BL63: =IF(--RIGHT(A63,1)=0,SUM(BK63:BK72),"") | BM63: =BK63/BN63 -> 0.10122524 | BN63: =INT(BJ63*升级节奏!G63+BK63) -> 8677678 | BO63: =ROUND(B63/90,0) -> 271
A64: 62 | B64: =升级节奏!C64 -> 24800 | C64: =IF(VLOOKUP(C$2,行为概览!$D$3:$J$33,7,0)="","",VLOOKUP(C$2,行为概览!$D$3:$J$33,7,0)) -> 50 | D64: =IF(VLOOKUP(D$2,行为概览!$D$3:$J$33,7,0)="","",VLOOKUP(D$2,行为概览!$D$3:$J$33,7,0)) -> 3.3 | E64: =IF(VLOOKUP(E$2,行为概览!$D$3:$J$33,7,0)="","",VLOOKUP(E$2,行为概览!$D$3:$J$33,7,0)) -> 30 | F64: =IF(VLOOKUP(F$2,行为概览!$D$3:$J$33,7,0)="","",VLOOKUP(F$2,行为概览!$D$3:$J$33,7,0)) -> 15 | G64: =IF(VLOOKUP(G$2,行为概览!$D$3:$J$33,7,0)="","",VLOOKUP(G$2,行为概览!$D$3:$J$33,7,0)) | H64: =IF(VLOOKUP(H$2,行为概览!$D$3:$J$33,7,0)="","",VLOOKUP(H$2,行为概览!$D$3:$J$33,7,0)) | I64: =IF(VLOOKUP(I$2,行为概览!$D$3:$J$33,7,0)="","",VLOOKUP(I$2,行为概览!$D$3:$J$33,7,0)) | J64: =IF(VLOOKUP(J$2,行为概览!$D$3:$J$33,7,0)="","",VLOOKUP(J$2,行为概览!$D$3:$J$33,7,0)) | ... AE64: =IF(VLOOKUP(AE$2,行为概览!$D$3:$J$33,7,0)="","",VLOOKUP(AE$2,行为概览!$D$3:$J$33,7,0)) | AF64: =IF(C64="","",ROUND(C64*玩法行为规划!B64,2)) -> 16.67 | AG64: =IF(D64="","",ROUND(D64*玩法行为规划!C64,2)) -> 6.6 | AH64: =IF(E64="","",ROUND(E64*玩法行为规划!D64,2)) -> 2.5 | AI64: =IF(F64="","",ROUND(F64*玩法行为规划!E64,2)) -> 15 | AJ64: =IF(G64="","",ROUND(G64*玩法行为规划!F64,2)) | AK64: =IF(H64="","",ROUND(H64*玩法行为规划!G64,2)) | AL64: =IF(I64="","",ROUND(I64*玩法行为规划!H64,2)) | AM64: =IF(J64="","",ROUND(J64*玩法行为规划!I64,2)) | ... BH64: =IF(AE64="","",ROUND(AE64*玩法行为规划!AD64,2)) | BI64: =SUM(AF64:BF64) -> 200.77 | BJ64: =B64*BI64 -> 4979096 | BK64: =ROUND(B64*(5+MAX(A64-30,0)*1),-2) -> 917600 | BL64: =IF(--RIGHT(A64,1)=0,SUM(BK64:BK73),"") | BM64: =BK64/BN64 -> 0.085466447 | BN64: =INT(BJ64*升级节奏!G64+BK64) -> 10736377 | BO64: =ROUND(B64/90,0) -> 276
A65: 63 | B65: =升级节奏!C65 -> 25200 | C65: =IF(VLOOKUP(C$2,行为概览!$D$3:$J$33,7,0)="","",VLOOKUP(C$2,行为概览!$D$3:$J$33,7,0)) -> 50 | D65: =IF(VLOOKUP(D$2,行为概览!$D$3:$J$33,7,0)="","",VLOOKUP(D$2,行为概览!$D$3:$J$33,7,0)) -> 3.3 | E65: =IF(VLOOKUP(E$2,行为概览!$D$3:$J$33,7,0)="","",VLOOKUP(E$2,行为概览!$D$3:$J$33,7,0)) -> 30 | F65: =IF(VLOOKUP(F$2,行为概览!$D$3:$J$33,7,0)="","",VLOOKUP(F$2,行为概览!$D$3:$J$33,7,0)) -> 15 | G65: =IF(VLOOKUP(G$2,行为概览!$D$3:$J$33,7,0)="","",VLOOKUP(G$2,行为概览!$D$3:$J$33,7,0)) | H65: =IF(VLOOKUP(H$2,行为概览!$D$3:$J$33,7,0)="","",VLOOKUP(H$2,行为概览!$D$3:$J$33,7,0)) | I65: =IF(VLOOKUP(I$2,行为概览!$D$3:$J$33,7,0)="","",VLOOKUP(I$2,行为概览!$D$3:$J$33,7,0)) | J65: =IF(VLOOKUP(J$2,行为概览!$D$3:$J$33,7,0)="","",VLOOKUP(J$2,行为概览!$D$3:$J$33,7,0)) | ... AE65: =IF(VLOOKUP(AE$2,行为概览!$D$3:$J$33,7,0)="","",VLOOKUP(AE$2,行为概览!$D$3:$J$33,7,0)) | AF65: =IF(C65="","",ROUND(C65*玩法行为规划!B65,2)) -> 16.67 | AG65: =IF(D65="","",ROUND(D65*玩法行为规划!C65,2)) -> 6.6 | AH65: =IF(E65="","",ROUND(E65*玩法行为规划!D65,2)) -> 2.5 | AI65: =IF(F65="","",ROUND(F65*玩法行为规划!E65,2)) -> 15 | AJ65: =IF(G65="","",ROUND(G65*玩法行为规划!F65,2)) | AK65: =IF(H65="","",ROUND(H65*玩法行为规划!G65,2)) | AL65: =IF(I65="","",ROUND(I65*玩法行为规划!H65,2)) | AM65: =IF(J65="","",ROUND(J65*玩法行为规划!I65,2)) | ... BH65: =IF(AE65="","",ROUND(AE65*玩法行为规划!AD65,2)) | BI65: =SUM(AF65:BF65) -> 200.77 | BJ65: =B65*BI65 -> 5059404 | BK65: =ROUND(B65*(5+MAX(A65-30,0)*1),-2) -> 957600 | BL65: =IF(--RIGHT(A65,1)=0,SUM(BK65:BK74),"") | BM65: =BK65/BN65 -> 0.073851752 | BN65: =INT(BJ65*升级节奏!G65+BK65) -> 12966517 | BO65: =ROUND(B65/90,0) -> 280
A66: 64 | B66: =升级节奏!C66 -> 25600 | C66: =IF(VLOOKUP(C$2,行为概览!$D$3:$J$33,7,0)="","",VLOOKUP(C$2,行为概览!$D$3:$J$33,7,0)) -> 50 | D66: =IF(VLOOKUP(D$2,行为概览!$D$3:$J$33,7,0)="","",VLOOKUP(D$2,行为概览!$D$3:$J$33,7,0)) -> 3.3 | E66: =IF(VLOOKUP(E$2,行为概览!$D$3:$J$33,7,0)="","",VLOOKUP(E$2,行为概览!$D$3:$J$33,7,0)) -> 30 | F66: =IF(VLOOKUP(F$2,行为概览!$D$3:$J$33,7,0)="","",VLOOKUP(F$2,行为概览!$D$3:$J$33,7,0)) -> 15 | G66: =IF(VLOOKUP(G$2,行为概览!$D$3:$J$33,7,0)="","",VLOOKUP(G$2,行为概览!$D$3:$J$33,7,0)) | H66: =IF(VLOOKUP(H$2,行为概览!$D$3:$J$33,7,0)="","",VLOOKUP(H$2,行为概览!$D$3:$J$33,7,0)) | I66: =IF(VLOOKUP(I$2,行为概览!$D$3:$J$33,7,0)="","",VLOOKUP(I$2,行为概览!$D$3:$J$33,7,0)) | J66: =IF(VLOOKUP(J$2,行为概览!$D$3:$J$33,7,0)="","",VLOOKUP(J$2,行为概览!$D$3:$J$33,7,0)) | ... AE66: =IF(VLOOKUP(AE$2,行为概览!$D$3:$J$33,7,0)="","",VLOOKUP(AE$2,行为概览!$D$3:$J$33,7,0)) | AF66: =IF(C66="","",ROUND(C66*玩法行为规划!B66,2)) -> 16.67 | AG66: =IF(D66="","",ROUND(D66*玩法行为规划!C66,2)) -> 6.6 | AH66: =IF(E66="","",ROUND(E66*玩法行为规划!D66,2)) -> 2.5 | AI66: =IF(F66="","",ROUND(F66*玩法行为规划!E66,2)) -> 15 | AJ66: =IF(G66="","",ROUND(G66*玩法行为规划!F66,2)) | AK66: =IF(H66="","",ROUND(H66*玩法行为规划!G66,2)) | AL66: =IF(I66="","",ROUND(I66*玩法行为规划!H66,2)) | AM66: =IF(J66="","",ROUND(J66*玩法行为规划!I66,2)) | ... BH66: =IF(AE66="","",ROUND(AE66*玩法行为规划!AD66,2)) | BI66: =SUM(AF66:BF66) -> 200.77 | BJ66: =B66*BI66 -> 5139712 | BK66: =ROUND(B66*(5+MAX(A66-30,0)*1),-2) -> 998400 | BL66: =IF(--RIGHT(A66,1)=0,SUM(BK66:BK75),"") | BM66: =BK66/BN66 -> 0.064932839 | BN66: =INT(BJ66*升级节奏!G66+BK66) -> 15375887 | BO66: =ROUND(B66/90,0) -> 284
A67: 65 | B67: =升级节奏!C67 -> 26000 | C67: =IF(VLOOKUP(C$2,行为概览!$D$3:$J$33,7,0)="","",VLOOKUP(C$2,行为概览!$D$3:$J$33,7,0)) -> 50 | D67: =IF(VLOOKUP(D$2,行为概览!$D$3:$J$33,7,0)="","",VLOOKUP(D$2,行为概览!$D$3:$J$33,7,0)) -> 3.3 | E67: =IF(VLOOKUP(E$2,行为概览!$D$3:$J$33,7,0)="","",VLOOKUP(E$2,行为概览!$D$3:$J$33,7,0)) -> 30 | F67: =IF(VLOOKUP(F$2,行为概览!$D$3:$J$33,7,0)="","",VLOOKUP(F$2,行为概览!$D$3:$J$33,7,0)) -> 15 | G67: =IF(VLOOKUP(G$2,行为概览!$D$3:$J$33,7,0)="","",VLOOKUP(G$2,行为概览!$D$3:$J$33,7,0)) | H67: =IF(VLOOKUP(H$2,行为概览!$D$3:$J$33,7,0)="","",VLOOKUP(H$2,行为概览!$D$3:$J$33,7,0)) | I67: =IF(VLOOKUP(I$2,行为概览!$D$3:$J$33,7,0)="","",VLOOKUP(I$2,行为概览!$D$3:$J$33,7,0)) | J67: =IF(VLOOKUP(J$2,行为概览!$D$3:$J$33,7,0)="","",VLOOKUP(J$2,行为概览!$D$3:$J$33,7,0)) | ... AE67: =IF(VLOOKUP(AE$2,行为概览!$D$3:$J$33,7,0)="","",VLOOKUP(AE$2,行为概览!$D$3:$J$33,7,0)) | AF67: =IF(C67="","",ROUND(C67*玩法行为规划!B67,2)) -> 16.67 | AG67: =IF(D67="","",ROUND(D67*玩法行为规划!C67,2)) -> 6.6 | AH67: =IF(E67="","",ROUND(E67*玩法行为规划!D67,2)) -> 2.5 | AI67: =IF(F67="","",ROUND(F67*玩法行为规划!E67,2)) -> 15 | AJ67: =IF(G67="","",ROUND(G67*玩法行为规划!F67,2)) | AK67: =IF(H67="","",ROUND(H67*玩法行为规划!G67,2)) | AL67: =IF(I67="","",ROUND(I67*玩法行为规划!H67,2)) | AM67: =IF(J67="","",ROUND(J67*玩法行为规划!I67,2)) | ... BH67: =IF(AE67="","",ROUND(AE67*玩法行为规划!AD67,2)) | BI67: =SUM(AF67:BF67) -> 200.77 | BJ67: =B67*BI67 -> 5220020 | BK67: =ROUND(B67*(5+MAX(A67-30,0)*1),-2) -> 1040000 | BL67: =IF(--RIGHT(A67,1)=0,SUM(BK67:BK76),"") | BM67: =BK67/BN67 -> 0.057866381 | BN67: =INT(BJ67*升级节奏!G67+BK67) -> 17972439 | BO67: =ROUND(B67/90,0) -> 289
A68: 66 | B68: =升级节奏!C68 -> 26400 | C68: =IF(VLOOKUP(C$2,行为概览!$D$3:$J$33,7,0)="","",VLOOKUP(C$2,行为概览!$D$3:$J$33,7,0)) -> 50 | D68: =IF(VLOOKUP(D$2,行为概览!$D$3:$J$33,7,0)="","",VLOOKUP(D$2,行为概览!$D$3:$J$33,7,0)) -> 3.3 | E68: =IF(VLOOKUP(E$2,行为概览!$D$3:$J$33,7,0)="","",VLOOKUP(E$2,行为概览!$D$3:$J$33,7,0)) -> 30 | F68: =IF(VLOOKUP(F$2,行为概览!$D$3:$J$33,7,0)="","",VLOOKUP(F$2,行为概览!$D$3:$J$33,7,0)) -> 15 | G68: =IF(VLOOKUP(G$2,行为概览!$D$3:$J$33,7,0)="","",VLOOKUP(G$2,行为概览!$D$3:$J$33,7,0)) | H68: =IF(VLOOKUP(H$2,行为概览!$D$3:$J$33,7,0)="","",VLOOKUP(H$2,行为概览!$D$3:$J$33,7,0)) | I68: =IF(VLOOKUP(I$2,行为概览!$D$3:$J$33,7,0)="","",VLOOKUP(I$2,行为概览!$D$3:$J$33,7,0)) | J68: =IF(VLOOKUP(J$2,行为概览!$D$3:$J$33,7,0)="","",VLOOKUP(J$2,行为概览!$D$3:$J$33,7,0)) | ... AE68: =IF(VLOOKUP(AE$2,行为概览!$D$3:$J$33,7,0)="","",VLOOKUP(AE$2,行为概览!$D$3:$J$33,7,0)) | AF68: =IF(C68="","",ROUND(C68*玩法行为规划!B68,2)) -> 16.67 | AG68: =IF(D68="","",ROUND(D68*玩法行为规划!C68,2)) -> 6.6 | AH68: =IF(E68="","",ROUND(E68*玩法行为规划!D68,2)) -> 2.5 | AI68: =IF(F68="","",ROUND(F68*玩法行为规划!E68,2)) -> 15 | AJ68: =IF(G68="","",ROUND(G68*玩法行为规划!F68,2)) | AK68: =IF(H68="","",ROUND(H68*玩法行为规划!G68,2)) | AL68: =IF(I68="","",ROUND(I68*玩法行为规划!H68,2)) | AM68: =IF(J68="","",ROUND(J68*玩法行为规划!I68,2)) | ... BH68: =IF(AE68="","",ROUND(AE68*玩法行为规划!AD68,2)) | BI68: =SUM(AF68:BF68) -> 200.77 | BJ68: =B68*BI68 -> 5300328 | BK68: =ROUND(B68*(5+MAX(A68-30,0)*1),-2) -> 1082400 | BL68: =IF(--RIGHT(A68,1)=0,SUM(BK68:BK77),"") | BM68: =BK68/BN68 -> 0.047614705 | BN68: =INT(BJ68*升级节奏!G68+BK68) -> 22732473 | BO68: =ROUND(B68/90,0) -> 293
A69: 67 | B69: =升级节奏!C69 -> 26800 | C69: =IF(VLOOKUP(C$2,行为概览!$D$3:$J$33,7,0)="","",VLOOKUP(C$2,行为概览!$D$3:$J$33,7,0)) -> 50 | D69: =IF(VLOOKUP(D$2,行为概览!$D$3:$J$33,7,0)="","",VLOOKUP(D$2,行为概览!$D$3:$J$33,7,0)) -> 3.3 | E69: =IF(VLOOKUP(E$2,行为概览!$D$3:$J$33,7,0)="","",VLOOKUP(E$2,行为概览!$D$3:$J$33,7,0)) -> 30 | F69: =IF(VLOOKUP(F$2,行为概览!$D$3:$J$33,7,0)="","",VLOOKUP(F$2,行为概览!$D$3:$J$33,7,0)) -> 15 | G69: =IF(VLOOKUP(G$2,行为概览!$D$3:$J$33,7,0)="","",VLOOKUP(G$2,行为概览!$D$3:$J$33,7,0)) | H69: =IF(VLOOKUP(H$2,行为概览!$D$3:$J$33,7,0)="","",VLOOKUP(H$2,行为概览!$D$3:$J$33,7,0)) | I69: =IF(VLOOKUP(I$2,行为概览!$D$3:$J$33,7,0)="","",VLOOKUP(I$2,行为概览!$D$3:$J$33,7,0)) | J69: =IF(VLOOKUP(J$2,行为概览!$D$3:$J$33,7,0)="","",VLOOKUP(J$2,行为概览!$D$3:$J$33,7,0)) | ... AE69: =IF(VLOOKUP(AE$2,行为概览!$D$3:$J$33,7,0)="","",VLOOKUP(AE$2,行为概览!$D$3:$J$33,7,0)) | AF69: =IF(C69="","",ROUND(C69*玩法行为规划!B69,2)) -> 16.67 | AG69: =IF(D69="","",ROUND(D69*玩法行为规划!C69,2)) -> 6.6 | AH69: =IF(E69="","",ROUND(E69*玩法行为规划!D69,2)) -> 2.5 | AI69: =IF(F69="","",ROUND(F69*玩法行为规划!E69,2)) -> 15 | AJ69: =IF(G69="","",ROUND(G69*玩法行为规划!F69,2)) | AK69: =IF(H69="","",ROUND(H69*玩法行为规划!G69,2)) | AL69: =IF(I69="","",ROUND(I69*玩法行为规划!H69,2)) | AM69: =IF(J69="","",ROUND(J69*玩法行为规划!I69,2)) | ... BH69: =IF(AE69="","",ROUND(AE69*玩法行为规划!AD69,2)) | BI69: =SUM(AF69:BF69) -> 200.77 | BJ69: =B69*BI69 -> 5380636 | BK69: =ROUND(B69*(5+MAX(A69-30,0)*1),-2) -> 1125600 | BL69: =IF(--RIGHT(A69,1)=0,SUM(BK69:BK78),"") | BM69: =BK69/BN69 -> 0.040380294 | BN69: =INT(BJ69*升级节奏!G69+BK69) -> 27874983 | BO69: =ROUND(B69/90,0) -> 298
A70: 68 | B70: =升级节奏!C70 -> 27200 | C70: =IF(VLOOKUP(C$2,行为概览!$D$3:$J$33,7,0)="","",VLOOKUP(C$2,行为概览!$D$3:$J$33,7,0)) -> 50 | D70: =IF(VLOOKUP(D$2,行为概览!$D$3:$J$33,7,0)="","",VLOOKUP(D$2,行为概览!$D$3:$J$33,7,0)) -> 3.3 | E70: =IF(VLOOKUP(E$2,行为概览!$D$3:$J$33,7,0)="","",VLOOKUP(E$2,行为概览!$D$3:$J$33,7,0)) -> 30 | F70: =IF(VLOOKUP(F$2,行为概览!$D$3:$J$33,7,0)="","",VLOOKUP(F$2,行为概览!$D$3:$J$33,7,0)) -> 15 | G70: =IF(VLOOKUP(G$2,行为概览!$D$3:$J$33,7,0)="","",VLOOKUP(G$2,行为概览!$D$3:$J$33,7,0)) | H70: =IF(VLOOKUP(H$2,行为概览!$D$3:$J$33,7,0)="","",VLOOKUP(H$2,行为概览!$D$3:$J$33,7,0)) | I70: =IF(VLOOKUP(I$2,行为概览!$D$3:$J$33,7,0)="","",VLOOKUP(I$2,行为概览!$D$3:$J$33,7,0)) | J70: =IF(VLOOKUP(J$2,行为概览!$D$3:$J$33,7,0)="","",VLOOKUP(J$2,行为概览!$D$3:$J$33,7,0)) | ... AE70: =IF(VLOOKUP(AE$2,行为概览!$D$3:$J$33,7,0)="","",VLOOKUP(AE$2,行为概览!$D$3:$J$33,7,0)) | AF70: =IF(C70="","",ROUND(C70*玩法行为规划!B70,2)) -> 16.67 | AG70: =IF(D70="","",ROUND(D70*玩法行为规划!C70,2)) -> 6.6 | AH70: =IF(E70="","",ROUND(E70*玩法行为规划!D70,2)) -> 2.5 | AI70: =IF(F70="","",ROUND(F70*玩法行为规划!E70,2)) -> 15 | AJ70: =IF(G70="","",ROUND(G70*玩法行为规划!F70,2)) | AK70: =IF(H70="","",ROUND(H70*玩法行为规划!G70,2)) | AL70: =IF(I70="","",ROUND(I70*玩法行为规划!H70,2)) | AM70: =IF(J70="","",ROUND(J70*玩法行为规划!I70,2)) | ... BH70: =IF(AE70="","",ROUND(AE70*玩法行为规划!AD70,2)) | BI70: =SUM(AF70:BF70) -> 200.77 | BJ70: =B70*BI70 -> 5460944 | BK70: =ROUND(B70*(5+MAX(A70-30,0)*1),-2) -> 1169600 | BL70: =IF(--RIGHT(A70,1)=0,SUM(BK70:BK79),"") | BM70: =BK70/BN70 -> 0.035000701 | BN70: =INT(BJ70*升级节奏!G70+BK70) -> 33416474 | BO70: =ROUND(B70/90,0) -> 302
A71: 69 | B71: =升级节奏!C71 -> 27600 | C71: =IF(VLOOKUP(C$2,行为概览!$D$3:$J$33,7,0)="","",VLOOKUP(C$2,行为概览!$D$3:$J$33,7,0)) -> 50 | D71: =IF(VLOOKUP(D$2,行为概览!$D$3:$J$33,7,0)="","",VLOOKUP(D$2,行为概览!$D$3:$J$33,7,0)) -> 3.3 | E71: =IF(VLOOKUP(E$2,行为概览!$D$3:$J$33,7,0)="","",VLOOKUP(E$2,行为概览!$D$3:$J$33,7,0)) -> 30 | F71: =IF(VLOOKUP(F$2,行为概览!$D$3:$J$33,7,0)="","",VLOOKUP(F$2,行为概览!$D$3:$J$33,7,0)) -> 15 | G71: =IF(VLOOKUP(G$2,行为概览!$D$3:$J$33,7,0)="","",VLOOKUP(G$2,行为概览!$D$3:$J$33,7,0)) | H71: =IF(VLOOKUP(H$2,行为概览!$D$3:$J$33,7,0)="","",VLOOKUP(H$2,行为概览!$D$3:$J$33,7,0)) | I71: =IF(VLOOKUP(I$2,行为概览!$D$3:$J$33,7,0)="","",VLOOKUP(I$2,行为概览!$D$3:$J$33,7,0)) | J71: =IF(VLOOKUP(J$2,行为概览!$D$3:$J$33,7,0)="","",VLOOKUP(J$2,行为概览!$D$3:$J$33,7,0)) | ... AE71: =IF(VLOOKUP(AE$2,行为概览!$D$3:$J$33,7,0)="","",VLOOKUP(AE$2,行为概览!$D$3:$J$33,7,0)) | AF71: =IF(C71="","",ROUND(C71*玩法行为规划!B71,2)) -> 16.67 | AG71: =IF(D71="","",ROUND(D71*玩法行为规划!C71,2)) -> 6.6 | AH71: =IF(E71="","",ROUND(E71*玩法行为规划!D71,2)) -> 2.5 | AI71: =IF(F71="","",ROUND(F71*玩法行为规划!E71,2)) -> 15 | AJ71: =IF(G71="","",ROUND(G71*玩法行为规划!F71,2)) | AK71: =IF(H71="","",ROUND(H71*玩法行为规划!G71,2)) | AL71: =IF(I71="","",ROUND(I71*玩法行为规划!H71,2)) | AM71: =IF(J71="","",ROUND(J71*玩法行为规划!I71,2)) | ... BH71: =IF(AE71="","",ROUND(AE71*玩法行为规划!AD71,2)) | BI71: =SUM(AF71:BF71) -> 200.77 | BJ71: =B71*BI71 -> 5541252 | BK71: =ROUND(B71*(5+MAX(A71-30,0)*1),-2) -> 1214400 | BL71: =IF(--RIGHT(A71,1)=0,SUM(BK71:BK80),"") | BM71: =BK71/BN71 -> 0.030842868 | BN71: =INT(BJ71*升级节奏!G71+BK71) -> 39373770 | BO71: =ROUND(B71/90,0) -> 307
A72: 70 | B72: =升级节奏!C72 -> 28000 | C72: =IF(VLOOKUP(C$2,行为概览!$D$3:$J$33,7,0)="","",VLOOKUP(C$2,行为概览!$D$3:$J$33,7,0)) -> 50 | D72: =IF(VLOOKUP(D$2,行为概览!$D$3:$J$33,7,0)="","",VLOOKUP(D$2,行为概览!$D$3:$J$33,7,0)) -> 3.3 | E72: =IF(VLOOKUP(E$2,行为概览!$D$3:$J$33,7,0)="","",VLOOKUP(E$2,行为概览!$D$3:$J$33,7,0)) -> 30 | F72: =IF(VLOOKUP(F$2,行为概览!$D$3:$J$33,7,0)="","",VLOOKUP(F$2,行为概览!$D$3:$J$33,7,0)) -> 15 | G72: =IF(VLOOKUP(G$2,行为概览!$D$3:$J$33,7,0)="","",VLOOKUP(G$2,行为概览!$D$3:$J$33,7,0)) | H72: =IF(VLOOKUP(H$2,行为概览!$D$3:$J$33,7,0)="","",VLOOKUP(H$2,行为概览!$D$3:$J$33,7,0)) | I72: =IF(VLOOKUP(I$2,行为概览!$D$3:$J$33,7,0)="","",VLOOKUP(I$2,行为概览!$D$3:$J$33,7,0)) | J72: =IF(VLOOKUP(J$2,行为概览!$D$3:$J$33,7,0)="","",VLOOKUP(J$2,行为概览!$D$3:$J$33,7,0)) | ... AE72: =IF(VLOOKUP(AE$2,行为概览!$D$3:$J$33,7,0)="","",VLOOKUP(AE$2,行为概览!$D$3:$J$33,7,0)) | AF72: =IF(C72="","",ROUND(C72*玩法行为规划!B72,2)) -> 16.67 | AG72: =IF(D72="","",ROUND(D72*玩法行为规划!C72,2)) -> 6.6 | AH72: =IF(E72="","",ROUND(E72*玩法行为规划!D72,2)) -> 2.5 | AI72: =IF(F72="","",ROUND(F72*玩法行为规划!E72,2)) -> 15 | AJ72: =IF(G72="","",ROUND(G72*玩法行为规划!F72,2)) | AK72: =IF(H72="","",ROUND(H72*玩法行为规划!G72,2)) | AL72: =IF(I72="","",ROUND(I72*玩法行为规划!H72,2)) | AM72: =IF(J72="","",ROUND(J72*玩法行为规划!I72,2)) | ... BH72: =IF(AE72="","",ROUND(AE72*玩法行为规划!AD72,2)) | BI72: =SUM(AF72:BF72) -> 200.77 | BJ72: =B72*BI72 -> 5621560 | BK72: =ROUND(B72*(6+MAX(A72-30,0)*1.1),-2) -> 1400000 | BL72: =IF(--RIGHT(A72,1)=0,SUM(BK72:BK81),"") -> 16411400 | BM72: =BK72/BN72 -> 0.033964603 | BN72: =INT(BJ72*升级节奏!G72+BK72) -> 41219383 | BO72: =ROUND(B72/90,0) -> 311
A73: 71 | B73: =升级节奏!C73 -> 28400 | C73: =IF(VLOOKUP(C$2,行为概览!$D$3:$J$33,7,0)="","",VLOOKUP(C$2,行为概览!$D$3:$J$33,7,0)) -> 50 | D73: =IF(VLOOKUP(D$2,行为概览!$D$3:$J$33,7,0)="","",VLOOKUP(D$2,行为概览!$D$3:$J$33,7,0)) -> 3.3 | E73: =IF(VLOOKUP(E$2,行为概览!$D$3:$J$33,7,0)="","",VLOOKUP(E$2,行为概览!$D$3:$J$33,7,0)) -> 30 | F73: =IF(VLOOKUP(F$2,行为概览!$D$3:$J$33,7,0)="","",VLOOKUP(F$2,行为概览!$D$3:$J$33,7,0)) -> 15 | G73: =IF(VLOOKUP(G$2,行为概览!$D$3:$J$33,7,0)="","",VLOOKUP(G$2,行为概览!$D$3:$J$33,7,0)) | H73: =IF(VLOOKUP(H$2,行为概览!$D$3:$J$33,7,0)="","",VLOOKUP(H$2,行为概览!$D$3:$J$33,7,0)) | I73: =IF(VLOOKUP(I$2,行为概览!$D$3:$J$33,7,0)="","",VLOOKUP(I$2,行为概览!$D$3:$J$33,7,0)) | J73: =IF(VLOOKUP(J$2,行为概览!$D$3:$J$33,7,0)="","",VLOOKUP(J$2,行为概览!$D$3:$J$33,7,0)) | ... AE73: =IF(VLOOKUP(AE$2,行为概览!$D$3:$J$33,7,0)="","",VLOOKUP(AE$2,行为概览!$D$3:$J$33,7,0)) | AF73: =IF(C73="","",ROUND(C73*玩法行为规划!B73,2)) -> 16.67 | AG73: =IF(D73="","",ROUND(D73*玩法行为规划!C73,2)) -> 6.6 | AH73: =IF(E73="","",ROUND(E73*玩法行为规划!D73,2)) -> 2.5 | AI73: =IF(F73="","",ROUND(F73*玩法行为规划!E73,2)) -> 15 | AJ73: =IF(G73="","",ROUND(G73*玩法行为规划!F73,2)) | AK73: =IF(H73="","",ROUND(H73*玩法行为规划!G73,2)) | AL73: =IF(I73="","",ROUND(I73*玩法行为规划!H73,2)) | AM73: =IF(J73="","",ROUND(J73*玩法行为规划!I73,2)) | ... BH73: =IF(AE73="","",ROUND(AE73*玩法行为规划!AD73,2)) | BI73: =SUM(AF73:BF73) -> 200.77 | BJ73: =B73*BI73 -> 5701868 | BK73: =ROUND(B73*(6+MAX(A73-30,0)*1.1),-2) -> 1451200 | BL73: =IF(--RIGHT(A73,1)=0,SUM(BK73:BK82),"") | BM73: =BK73/BN73 -> 0.033765815 | BN73: =INT(BJ73*升级节奏!G73+BK73) -> 42978379 | BO73: =ROUND(B73/90,0) -> 316
A74: 72 | B74: =升级节奏!C74 -> 28800 | C74: =IF(VLOOKUP(C$2,行为概览!$D$3:$J$33,7,0)="","",VLOOKUP(C$2,行为概览!$D$3:$J$33,7,0)) -> 50 | D74: =IF(VLOOKUP(D$2,行为概览!$D$3:$J$33,7,0)="","",VLOOKUP(D$2,行为概览!$D$3:$J$33,7,0)) -> 3.3 | E74: =IF(VLOOKUP(E$2,行为概览!$D$3:$J$33,7,0)="","",VLOOKUP(E$2,行为概览!$D$3:$J$33,7,0)) -> 30 | F74: =IF(VLOOKUP(F$2,行为概览!$D$3:$J$33,7,0)="","",VLOOKUP(F$2,行为概览!$D$3:$J$33,7,0)) -> 15 | G74: =IF(VLOOKUP(G$2,行为概览!$D$3:$J$33,7,0)="","",VLOOKUP(G$2,行为概览!$D$3:$J$33,7,0)) | H74: =IF(VLOOKUP(H$2,行为概览!$D$3:$J$33,7,0)="","",VLOOKUP(H$2,行为概览!$D$3:$J$33,7,0)) | I74: =IF(VLOOKUP(I$2,行为概览!$D$3:$J$33,7,0)="","",VLOOKUP(I$2,行为概览!$D$3:$J$33,7,0)) | J74: =IF(VLOOKUP(J$2,行为概览!$D$3:$J$33,7,0)="","",VLOOKUP(J$2,行为概览!$D$3:$J$33,7,0)) | ... AE74: =IF(VLOOKUP(AE$2,行为概览!$D$3:$J$33,7,0)="","",VLOOKUP(AE$2,行为概览!$D$3:$J$33,7,0)) | AF74: =IF(C74="","",ROUND(C74*玩法行为规划!B74,2)) -> 16.67 | AG74: =IF(D74="","",ROUND(D74*玩法行为规划!C74,2)) -> 6.6 | AH74: =IF(E74="","",ROUND(E74*玩法行为规划!D74,2)) -> 2.5 | AI74: =IF(F74="","",ROUND(F74*玩法行为规划!E74,2)) -> 15 | AJ74: =IF(G74="","",ROUND(G74*玩法行为规划!F74,2)) | AK74: =IF(H74="","",ROUND(H74*玩法行为规划!G74,2)) | AL74: =IF(I74="","",ROUND(I74*玩法行为规划!H74,2)) | AM74: =IF(J74="","",ROUND(J74*玩法行为规划!I74,2)) | ... BH74: =IF(AE74="","",ROUND(AE74*玩法行为规划!AD74,2)) | BI74: =SUM(AF74:BF74) -> 200.77 | BJ74: =B74*BI74 -> 5782176 | BK74: =ROUND(B74*(6+MAX(A74-30,0)*1.1),-2) -> 1503400 | BL74: =IF(--RIGHT(A74,1)=0,SUM(BK74:BK83),"") | BM74: =BK74/BN74 -> 0.033567895 | BN74: =INT(BJ74*升级节奏!G74+BK74) -> 44786842 | BO74: =ROUND(B74/90,0) -> 320
A75: 73 | B75: =升级节奏!C75 -> 29200 | C75: =IF(VLOOKUP(C$2,行为概览!$D$3:$J$33,7,0)="","",VLOOKUP(C$2,行为概览!$D$3:$J$33,7,0)) -> 50 | D75: =IF(VLOOKUP(D$2,行为概览!$D$3:$J$33,7,0)="","",VLOOKUP(D$2,行为概览!$D$3:$J$33,7,0)) -> 3.3 | E75: =IF(VLOOKUP(E$2,行为概览!$D$3:$J$33,7,0)="","",VLOOKUP(E$2,行为概览!$D$3:$J$33,7,0)) -> 30 | F75: =IF(VLOOKUP(F$2,行为概览!$D$3:$J$33,7,0)="","",VLOOKUP(F$2,行为概览!$D$3:$J$33,7,0)) -> 15 | G75: =IF(VLOOKUP(G$2,行为概览!$D$3:$J$33,7,0)="","",VLOOKUP(G$2,行为概览!$D$3:$J$33,7,0)) | H75: =IF(VLOOKUP(H$2,行为概览!$D$3:$J$33,7,0)="","",VLOOKUP(H$2,行为概览!$D$3:$J$33,7,0)) | I75: =IF(VLOOKUP(I$2,行为概览!$D$3:$J$33,7,0)="","",VLOOKUP(I$2,行为概览!$D$3:$J$33,7,0)) | J75: =IF(VLOOKUP(J$2,行为概览!$D$3:$J$33,7,0)="","",VLOOKUP(J$2,行为概览!$D$3:$J$33,7,0)) | ... AE75: =IF(VLOOKUP(AE$2,行为概览!$D$3:$J$33,7,0)="","",VLOOKUP(AE$2,行为概览!$D$3:$J$33,7,0)) | AF75: =IF(C75="","",ROUND(C75*玩法行为规划!B75,2)) -> 16.67 | AG75: =IF(D75="","",ROUND(D75*玩法行为规划!C75,2)) -> 6.6 | AH75: =IF(E75="","",ROUND(E75*玩法行为规划!D75,2)) -> 2.5 | AI75: =IF(F75="","",ROUND(F75*玩法行为规划!E75,2)) -> 15 | AJ75: =IF(G75="","",ROUND(G75*玩法行为规划!F75,2)) | AK75: =IF(H75="","",ROUND(H75*玩法行为规划!G75,2)) | AL75: =IF(I75="","",ROUND(I75*玩法行为规划!H75,2)) | AM75: =IF(J75="","",ROUND(J75*玩法行为规划!I75,2)) | ... BH75: =IF(AE75="","",ROUND(AE75*玩法行为规划!AD75,2)) | BI75: =SUM(AF75:BF75) -> 200.77 | BJ75: =B75*BI75 -> 5862484 | BK75: =ROUND(B75*(6+MAX(A75-30,0)*1.1),-2) -> 1556400 | BL75: =IF(--RIGHT(A75,1)=0,SUM(BK75:BK84),"") | BM75: =BK75/BN75 -> 0.03336674 | BN75: =INT(BJ75*升级节奏!G75+BK75) -> 46645252 | BO75: =ROUND(B75/90,0) -> 324
A76: 74 | B76: =升级节奏!C76 -> 29600 | C76: =IF(VLOOKUP(C$2,行为概览!$D$3:$J$33,7,0)="","",VLOOKUP(C$2,行为概览!$D$3:$J$33,7,0)) -> 50 | D76: =IF(VLOOKUP(D$2,行为概览!$D$3:$J$33,7,0)="","",VLOOKUP(D$2,行为概览!$D$3:$J$33,7,0)) -> 3.3 | E76: =IF(VLOOKUP(E$2,行为概览!$D$3:$J$33,7,0)="","",VLOOKUP(E$2,行为概览!$D$3:$J$33,7,0)) -> 30 | F76: =IF(VLOOKUP(F$2,行为概览!$D$3:$J$33,7,0)="","",VLOOKUP(F$2,行为概览!$D$3:$J$33,7,0)) -> 15 | G76: =IF(VLOOKUP(G$2,行为概览!$D$3:$J$33,7,0)="","",VLOOKUP(G$2,行为概览!$D$3:$J$33,7,0)) | H76: =IF(VLOOKUP(H$2,行为概览!$D$3:$J$33,7,0)="","",VLOOKUP(H$2,行为概览!$D$3:$J$33,7,0)) | I76: =IF(VLOOKUP(I$2,行为概览!$D$3:$J$33,7,0)="","",VLOOKUP(I$2,行为概览!$D$3:$J$33,7,0)) | J76: =IF(VLOOKUP(J$2,行为概览!$D$3:$J$33,7,0)="","",VLOOKUP(J$2,行为概览!$D$3:$J$33,7,0)) | ... AE76: =IF(VLOOKUP(AE$2,行为概览!$D$3:$J$33,7,0)="","",VLOOKUP(AE$2,行为概览!$D$3:$J$33,7,0)) | AF76: =IF(C76="","",ROUND(C76*玩法行为规划!B76,2)) -> 16.67 | AG76: =IF(D76="","",ROUND(D76*玩法行为规划!C76,2)) -> 6.6 | AH76: =IF(E76="","",ROUND(E76*玩法行为规划!D76,2)) -> 2.5 | AI76: =IF(F76="","",ROUND(F76*玩法行为规划!E76,2)) -> 15 | AJ76: =IF(G76="","",ROUND(G76*玩法行为规划!F76,2)) | AK76: =IF(H76="","",ROUND(H76*玩法行为规划!G76,2)) | AL76: =IF(I76="","",ROUND(I76*玩法行为规划!H76,2)) | AM76: =IF(J76="","",ROUND(J76*玩法行为规划!I76,2)) | ... BH76: =IF(AE76="","",ROUND(AE76*玩法行为规划!AD76,2)) | BI76: =SUM(AF76:BF76) -> 200.77 | BJ76: =B76*BI76 -> 5942792 | BK76: =ROUND(B76*(6+MAX(A76-30,0)*1.1),-2) -> 1610200 | BL76: =IF(--RIGHT(A76,1)=0,SUM(BK76:BK85),"") | BM76: =BK76/BN76 -> 0.033162875 | BN76: =INT(BJ76*升级节奏!G76+BK76) -> 48554294 | BO76: =ROUND(B76/90,0) -> 329
A77: 75 | B77: =升级节奏!C77 -> 30000 | C77: =IF(VLOOKUP(C$2,行为概览!$D$3:$J$33,7,0)="","",VLOOKUP(C$2,行为概览!$D$3:$J$33,7,0)) -> 50 | D77: =IF(VLOOKUP(D$2,行为概览!$D$3:$J$33,7,0)="","",VLOOKUP(D$2,行为概览!$D$3:$J$33,7,0)) -> 3.3 | E77: =IF(VLOOKUP(E$2,行为概览!$D$3:$J$33,7,0)="","",VLOOKUP(E$2,行为概览!$D$3:$J$33,7,0)) -> 30 | F77: =IF(VLOOKUP(F$2,行为概览!$D$3:$J$33,7,0)="","",VLOOKUP(F$2,行为概览!$D$3:$J$33,7,0)) -> 15 | G77: =IF(VLOOKUP(G$2,行为概览!$D$3:$J$33,7,0)="","",VLOOKUP(G$2,行为概览!$D$3:$J$33,7,0)) | H77: =IF(VLOOKUP(H$2,行为概览!$D$3:$J$33,7,0)="","",VLOOKUP(H$2,行为概览!$D$3:$J$33,7,0)) | I77: =IF(VLOOKUP(I$2,行为概览!$D$3:$J$33,7,0)="","",VLOOKUP(I$2,行为概览!$D$3:$J$33,7,0)) | J77: =IF(VLOOKUP(J$2,行为概览!$D$3:$J$33,7,0)="","",VLOOKUP(J$2,行为概览!$D$3:$J$33,7,0)) | ... AE77: =IF(VLOOKUP(AE$2,行为概览!$D$3:$J$33,7,0)="","",VLOOKUP(AE$2,行为概览!$D$3:$J$33,7,0)) | AF77: =IF(C77="","",ROUND(C77*玩法行为规划!B77,2)) -> 16.67 | AG77: =IF(D77="","",ROUND(D77*玩法行为规划!C77,2)) -> 6.6 | AH77: =IF(E77="","",ROUND(E77*玩法行为规划!D77,2)) -> 2.5 | AI77: =IF(F77="","",ROUND(F77*玩法行为规划!E77,2)) -> 15 | AJ77: =IF(G77="","",ROUND(G77*玩法行为规划!F77,2)) | AK77: =IF(H77="","",ROUND(H77*玩法行为规划!G77,2)) | AL77: =IF(I77="","",ROUND(I77*玩法行为规划!H77,2)) | AM77: =IF(J77="","",ROUND(J77*玩法行为规划!I77,2)) | ... BH77: =IF(AE77="","",ROUND(AE77*玩法行为规划!AD77,2)) | BI77: =SUM(AF77:BF77) -> 200.77 | BJ77: =B77*BI77 -> 6023100 | BK77: =ROUND(B77*(6+MAX(A77-30,0)*1.1),-2) -> 1665000 | BL77: =IF(--RIGHT(A77,1)=0,SUM(BK77:BK86),"") | BM77: =BK77/BN77 -> 0.032960605 | BN77: =INT(BJ77*升级节奏!G77+BK77) -> 50514850 | BO77: =ROUND(B77/90,0) -> 333
A78: 76 | B78: =升级节奏!C78 -> 30400 | C78: =IF(VLOOKUP(C$2,行为概览!$D$3:$J$33,7,0)="","",VLOOKUP(C$2,行为概览!$D$3:$J$33,7,0)) -> 50 | D78: =IF(VLOOKUP(D$2,行为概览!$D$3:$J$33,7,0)="","",VLOOKUP(D$2,行为概览!$D$3:$J$33,7,0)) -> 3.3 | E78: =IF(VLOOKUP(E$2,行为概览!$D$3:$J$33,7,0)="","",VLOOKUP(E$2,行为概览!$D$3:$J$33,7,0)) -> 30 | F78: =IF(VLOOKUP(F$2,行为概览!$D$3:$J$33,7,0)="","",VLOOKUP(F$2,行为概览!$D$3:$J$33,7,0)) -> 15 | G78: =IF(VLOOKUP(G$2,行为概览!$D$3:$J$33,7,0)="","",VLOOKUP(G$2,行为概览!$D$3:$J$33,7,0)) | H78: =IF(VLOOKUP(H$2,行为概览!$D$3:$J$33,7,0)="","",VLOOKUP(H$2,行为概览!$D$3:$J$33,7,0)) | I78: =IF(VLOOKUP(I$2,行为概览!$D$3:$J$33,7,0)="","",VLOOKUP(I$2,行为概览!$D$3:$J$33,7,0)) | J78: =IF(VLOOKUP(J$2,行为概览!$D$3:$J$33,7,0)="","",VLOOKUP(J$2,行为概览!$D$3:$J$33,7,0)) | ... AE78: =IF(VLOOKUP(AE$2,行为概览!$D$3:$J$33,7,0)="","",VLOOKUP(AE$2,行为概览!$D$3:$J$33,7,0)) | AF78: =IF(C78="","",ROUND(C78*玩法行为规划!B78,2)) -> 16.67 | AG78: =IF(D78="","",ROUND(D78*玩法行为规划!C78,2)) -> 6.6 | AH78: =IF(E78="","",ROUND(E78*玩法行为规划!D78,2)) -> 2.5 | AI78: =IF(F78="","",ROUND(F78*玩法行为规划!E78,2)) -> 15 | AJ78: =IF(G78="","",ROUND(G78*玩法行为规划!F78,2)) | AK78: =IF(H78="","",ROUND(H78*玩法行为规划!G78,2)) | AL78: =IF(I78="","",ROUND(I78*玩法行为规划!H78,2)) | AM78: =IF(J78="","",ROUND(J78*玩法行为规划!I78,2)) | ... BH78: =IF(AE78="","",ROUND(AE78*玩法行为规划!AD78,2)) | BI78: =SUM(AF78:BF78) -> 200.77 | BJ78: =B78*BI78 -> 6103408 | BK78: =ROUND(B78*(6+MAX(A78-30,0)*1.1),-2) -> 1720600 | BL78: =IF(--RIGHT(A78,1)=0,SUM(BK78:BK87),"") | BM78: =BK78/BN78 -> 0.032756236 | BN78: =INT(BJ78*升级节奏!G78+BK78) -> 52527402 | BO78: =ROUND(B78/90,0) -> 338
A79: 77 | B79: =升级节奏!C79 -> 30800 | C79: =IF(VLOOKUP(C$2,行为概览!$D$3:$J$33,7,0)="","",VLOOKUP(C$2,行为概览!$D$3:$J$33,7,0)) -> 50 | D79: =IF(VLOOKUP(D$2,行为概览!$D$3:$J$33,7,0)="","",VLOOKUP(D$2,行为概览!$D$3:$J$33,7,0)) -> 3.3 | E79: =IF(VLOOKUP(E$2,行为概览!$D$3:$J$33,7,0)="","",VLOOKUP(E$2,行为概览!$D$3:$J$33,7,0)) -> 30 | F79: =IF(VLOOKUP(F$2,行为概览!$D$3:$J$33,7,0)="","",VLOOKUP(F$2,行为概览!$D$3:$J$33,7,0)) -> 15 | G79: =IF(VLOOKUP(G$2,行为概览!$D$3:$J$33,7,0)="","",VLOOKUP(G$2,行为概览!$D$3:$J$33,7,0)) | H79: =IF(VLOOKUP(H$2,行为概览!$D$3:$J$33,7,0)="","",VLOOKUP(H$2,行为概览!$D$3:$J$33,7,0)) | I79: =IF(VLOOKUP(I$2,行为概览!$D$3:$J$33,7,0)="","",VLOOKUP(I$2,行为概览!$D$3:$J$33,7,0)) | J79: =IF(VLOOKUP(J$2,行为概览!$D$3:$J$33,7,0)="","",VLOOKUP(J$2,行为概览!$D$3:$J$33,7,0)) | ... AE79: =IF(VLOOKUP(AE$2,行为概览!$D$3:$J$33,7,0)="","",VLOOKUP(AE$2,行为概览!$D$3:$J$33,7,0)) | AF79: =IF(C79="","",ROUND(C79*玩法行为规划!B79,2)) -> 16.67 | AG79: =IF(D79="","",ROUND(D79*玩法行为规划!C79,2)) -> 6.6 | AH79: =IF(E79="","",ROUND(E79*玩法行为规划!D79,2)) -> 2.5 | AI79: =IF(F79="","",ROUND(F79*玩法行为规划!E79,2)) -> 15 | AJ79: =IF(G79="","",ROUND(G79*玩法行为规划!F79,2)) | AK79: =IF(H79="","",ROUND(H79*玩法行为规划!G79,2)) | AL79: =IF(I79="","",ROUND(I79*玩法行为规划!H79,2)) | AM79: =IF(J79="","",ROUND(J79*玩法行为规划!I79,2)) | ... BH79: =IF(AE79="","",ROUND(AE79*玩法行为规划!AD79,2)) | BI79: =SUM(AF79:BF79) -> 200.77 | BJ79: =B79*BI79 -> 6183716 | BK79: =ROUND(B79*(6+MAX(A79-30,0)*1.1),-2) -> 1777200 | BL79: =IF(--RIGHT(A79,1)=0,SUM(BK79:BK88),"") | BM79: =BK79/BN79 -> 0.032553724 | BN79: =INT(BJ79*升级节奏!G79+BK79) -> 54592833 | BO79: =ROUND(B79/90,0) -> 342
A80: 78 | B80: =升级节奏!C80 -> 31200 | C80: =IF(VLOOKUP(C$2,行为概览!$D$3:$J$33,7,0)="","",VLOOKUP(C$2,行为概览!$D$3:$J$33,7,0)) -> 50 | D80: =IF(VLOOKUP(D$2,行为概览!$D$3:$J$33,7,0)="","",VLOOKUP(D$2,行为概览!$D$3:$J$33,7,0)) -> 3.3 | E80: =IF(VLOOKUP(E$2,行为概览!$D$3:$J$33,7,0)="","",VLOOKUP(E$2,行为概览!$D$3:$J$33,7,0)) -> 30 | F80: =IF(VLOOKUP(F$2,行为概览!$D$3:$J$33,7,0)="","",VLOOKUP(F$2,行为概览!$D$3:$J$33,7,0)) -> 15 | G80: =IF(VLOOKUP(G$2,行为概览!$D$3:$J$33,7,0)="","",VLOOKUP(G$2,行为概览!$D$3:$J$33,7,0)) | H80: =IF(VLOOKUP(H$2,行为概览!$D$3:$J$33,7,0)="","",VLOOKUP(H$2,行为概览!$D$3:$J$33,7,0)) | I80: =IF(VLOOKUP(I$2,行为概览!$D$3:$J$33,7,0)="","",VLOOKUP(I$2,行为概览!$D$3:$J$33,7,0)) | J80: =IF(VLOOKUP(J$2,行为概览!$D$3:$J$33,7,0)="","",VLOOKUP(J$2,行为概览!$D$3:$J$33,7,0)) | ... AE80: =IF(VLOOKUP(AE$2,行为概览!$D$3:$J$33,7,0)="","",VLOOKUP(AE$2,行为概览!$D$3:$J$33,7,0)) | AF80: =IF(C80="","",ROUND(C80*玩法行为规划!B80,2)) -> 16.67 | AG80: =IF(D80="","",ROUND(D80*玩法行为规划!C80,2)) -> 6.6 | AH80: =IF(E80="","",ROUND(E80*玩法行为规划!D80,2)) -> 2.5 | AI80: =IF(F80="","",ROUND(F80*玩法行为规划!E80,2)) -> 15 | AJ80: =IF(G80="","",ROUND(G80*玩法行为规划!F80,2)) | AK80: =IF(H80="","",ROUND(H80*玩法行为规划!G80,2)) | AL80: =IF(I80="","",ROUND(I80*玩法行为规划!H80,2)) | AM80: =IF(J80="","",ROUND(J80*玩法行为规划!I80,2)) | ... BH80: =IF(AE80="","",ROUND(AE80*玩法行为规划!AD80,2)) | BI80: =SUM(AF80:BF80) -> 200.77 | BJ80: =B80*BI80 -> 6264024 | BK80: =ROUND(B80*(6+MAX(A80-30,0)*1.1),-2) -> 1834600 | BL80: =IF(--RIGHT(A80,1)=0,SUM(BK80:BK89),"") | BM80: =BK80/BN80 -> 0.032349628 | BN80: =INT(BJ80*升级节奏!G80+BK80) -> 56711626 | BO80: =ROUND(B80/90,0) -> 347
A81: 79 | B81: =升级节奏!C81 -> 31600 | C81: =IF(VLOOKUP(C$2,行为概览!$D$3:$J$33,7,0)="","",VLOOKUP(C$2,行为概览!$D$3:$J$33,7,0)) -> 50 | D81: =IF(VLOOKUP(D$2,行为概览!$D$3:$J$33,7,0)="","",VLOOKUP(D$2,行为概览!$D$3:$J$33,7,0)) -> 3.3 | E81: =IF(VLOOKUP(E$2,行为概览!$D$3:$J$33,7,0)="","",VLOOKUP(E$2,行为概览!$D$3:$J$33,7,0)) -> 30 | F81: =IF(VLOOKUP(F$2,行为概览!$D$3:$J$33,7,0)="","",VLOOKUP(F$2,行为概览!$D$3:$J$33,7,0)) -> 15 | G81: =IF(VLOOKUP(G$2,行为概览!$D$3:$J$33,7,0)="","",VLOOKUP(G$2,行为概览!$D$3:$J$33,7,0)) | H81: =IF(VLOOKUP(H$2,行为概览!$D$3:$J$33,7,0)="","",VLOOKUP(H$2,行为概览!$D$3:$J$33,7,0)) | I81: =IF(VLOOKUP(I$2,行为概览!$D$3:$J$33,7,0)="","",VLOOKUP(I$2,行为概览!$D$3:$J$33,7,0)) | J81: =IF(VLOOKUP(J$2,行为概览!$D$3:$J$33,7,0)="","",VLOOKUP(J$2,行为概览!$D$3:$J$33,7,0)) | ... AE81: =IF(VLOOKUP(AE$2,行为概览!$D$3:$J$33,7,0)="","",VLOOKUP(AE$2,行为概览!$D$3:$J$33,7,0)) | AF81: =IF(C81="","",ROUND(C81*玩法行为规划!B81,2)) -> 16.67 | AG81: =IF(D81="","",ROUND(D81*玩法行为规划!C81,2)) -> 6.6 | AH81: =IF(E81="","",ROUND(E81*玩法行为规划!D81,2)) -> 2.5 | AI81: =IF(F81="","",ROUND(F81*玩法行为规划!E81,2)) -> 15 | AJ81: =IF(G81="","",ROUND(G81*玩法行为规划!F81,2)) | AK81: =IF(H81="","",ROUND(H81*玩法行为规划!G81,2)) | AL81: =IF(I81="","",ROUND(I81*玩法行为规划!H81,2)) | AM81: =IF(J81="","",ROUND(J81*玩法行为规划!I81,2)) | ... BH81: =IF(AE81="","",ROUND(AE81*玩法行为规划!AD81,2)) | BI81: =SUM(AF81:BF81) -> 200.77 | BJ81: =B81*BI81 -> 6344332 | BK81: =ROUND(B81*(6+MAX(A81-30,0)*1.1),-2) -> 1892800 | BL81: =IF(--RIGHT(A81,1)=0,SUM(BK81:BK90),"") | BM81: =BK81/BN81 -> 0.032144303 | BN81: =INT(BJ81*升级节奏!G81+BK81) -> 58884463 | BO81: =ROUND(B81/90,0) -> 351
A82: 80 | B82: =升级节奏!C82 -> 32000 | C82: =IF(VLOOKUP(C$2,行为概览!$D$3:$J$33,7,0)="","",VLOOKUP(C$2,行为概览!$D$3:$J$33,7,0)) -> 50 | D82: =IF(VLOOKUP(D$2,行为概览!$D$3:$J$33,7,0)="","",VLOOKUP(D$2,行为概览!$D$3:$J$33,7,0)) -> 3.3 | E82: =IF(VLOOKUP(E$2,行为概览!$D$3:$J$33,7,0)="","",VLOOKUP(E$2,行为概览!$D$3:$J$33,7,0)) -> 30 | F82: =IF(VLOOKUP(F$2,行为概览!$D$3:$J$33,7,0)="","",VLOOKUP(F$2,行为概览!$D$3:$J$33,7,0)) -> 15 | G82: =IF(VLOOKUP(G$2,行为概览!$D$3:$J$33,7,0)="","",VLOOKUP(G$2,行为概览!$D$3:$J$33,7,0)) | H82: =IF(VLOOKUP(H$2,行为概览!$D$3:$J$33,7,0)="","",VLOOKUP(H$2,行为概览!$D$3:$J$33,7,0)) | I82: =IF(VLOOKUP(I$2,行为概览!$D$3:$J$33,7,0)="","",VLOOKUP(I$2,行为概览!$D$3:$J$33,7,0)) | J82: =IF(VLOOKUP(J$2,行为概览!$D$3:$J$33,7,0)="","",VLOOKUP(J$2,行为概览!$D$3:$J$33,7,0)) | ... AE82: =IF(VLOOKUP(AE$2,行为概览!$D$3:$J$33,7,0)="","",VLOOKUP(AE$2,行为概览!$D$3:$J$33,7,0)) | AF82: =IF(C82="","",ROUND(C82*玩法行为规划!B82,2)) -> 16.67 | AG82: =IF(D82="","",ROUND(D82*玩法行为规划!C82,2)) -> 6.6 | AH82: =IF(E82="","",ROUND(E82*玩法行为规划!D82,2)) -> 2.5 | AI82: =IF(F82="","",ROUND(F82*玩法行为规划!E82,2)) -> 15 | AJ82: =IF(G82="","",ROUND(G82*玩法行为规划!F82,2)) | AK82: =IF(H82="","",ROUND(H82*玩法行为规划!G82,2)) | AL82: =IF(I82="","",ROUND(I82*玩法行为规划!H82,2)) | AM82: =IF(J82="","",ROUND(J82*玩法行为规划!I82,2)) | ... BH82: =IF(AE82="","",ROUND(AE82*玩法行为规划!AD82,2)) | BI82: =SUM(AF82:BF82) -> 200.77 | BJ82: =B82*BI82 -> 6424640 | BK82: =ROUND(B82*(6+MAX(A82-30,0)*1.1),-2) -> 1952000 | BL82: =IF(--RIGHT(A82,1)=0,SUM(BK82:BK91),"") -> 22327400 | BM82: =BK82/BN82 -> 0.031941235 | BN82: =INT(BJ82*升级节奏!G82+BK82) -> 61112226 | BO82: =ROUND(B82/90,0) -> 356
A83: 81 | B83: =升级节奏!C83 -> 32400 | C83: =IF(VLOOKUP(C$2,行为概览!$D$3:$J$33,7,0)="","",VLOOKUP(C$2,行为概览!$D$3:$J$33,7,0)) -> 50 | D83: =IF(VLOOKUP(D$2,行为概览!$D$3:$J$33,7,0)="","",VLOOKUP(D$2,行为概览!$D$3:$J$33,7,0)) -> 3.3 | E83: =IF(VLOOKUP(E$2,行为概览!$D$3:$J$33,7,0)="","",VLOOKUP(E$2,行为概览!$D$3:$J$33,7,0)) -> 30 | F83: =IF(VLOOKUP(F$2,行为概览!$D$3:$J$33,7,0)="","",VLOOKUP(F$2,行为概览!$D$3:$J$33,7,0)) -> 15 | G83: =IF(VLOOKUP(G$2,行为概览!$D$3:$J$33,7,0)="","",VLOOKUP(G$2,行为概览!$D$3:$J$33,7,0)) | H83: =IF(VLOOKUP(H$2,行为概览!$D$3:$J$33,7,0)="","",VLOOKUP(H$2,行为概览!$D$3:$J$33,7,0)) | I83: =IF(VLOOKUP(I$2,行为概览!$D$3:$J$33,7,0)="","",VLOOKUP(I$2,行为概览!$D$3:$J$33,7,0)) | J83: =IF(VLOOKUP(J$2,行为概览!$D$3:$J$33,7,0)="","",VLOOKUP(J$2,行为概览!$D$3:$J$33,7,0)) | ... AE83: =IF(VLOOKUP(AE$2,行为概览!$D$3:$J$33,7,0)="","",VLOOKUP(AE$2,行为概览!$D$3:$J$33,7,0)) | AF83: =IF(C83="","",ROUND(C83*玩法行为规划!B83,2)) -> 16.67 | AG83: =IF(D83="","",ROUND(D83*玩法行为规划!C83,2)) -> 6.6 | AH83: =IF(E83="","",ROUND(E83*玩法行为规划!D83,2)) -> 2.5 | AI83: =IF(F83="","",ROUND(F83*玩法行为规划!E83,2)) -> 15 | AJ83: =IF(G83="","",ROUND(G83*玩法行为规划!F83,2)) | AK83: =IF(H83="","",ROUND(H83*玩法行为规划!G83,2)) | AL83: =IF(I83="","",ROUND(I83*玩法行为规划!H83,2)) | AM83: =IF(J83="","",ROUND(J83*玩法行为规划!I83,2)) | ... BH83: =IF(AE83="","",ROUND(AE83*玩法行为规划!AD83,2)) | BI83: =SUM(AF83:BF83) -> 200.77 | BJ83: =B83*BI83 -> 6504948 | BK83: =ROUND(B83*(6+MAX(A83-30,0)*1.1),-2) -> 2012000 | BL83: =IF(--RIGHT(A83,1)=0,SUM(BK83:BK92),"") | BM83: =BK83/BN83 -> 0.031737319 | BN83: =INT(BJ83*升级节奏!G83+BK83) -> 63395399 | BO83: =ROUND(B83/90,0) -> 360
... A152: 150 | B152: =升级节奏!C152 -> 60000 | C152: =IF(VLOOKUP(C$2,行为概览!$D$3:$J$33,7,0)="","",VLOOKUP(C$2,行为概览!$D$3:$J$33,7,0)) -> 50 | D152: =IF(VLOOKUP(D$2,行为概览!$D$3:$J$33,7,0)="","",VLOOKUP(D$2,行为概览!$D$3:$J$33,7,0)) -> 3.3 | E152: =IF(VLOOKUP(E$2,行为概览!$D$3:$J$33,7,0)="","",VLOOKUP(E$2,行为概览!$D$3:$J$33,7,0)) -> 30 | F152: =IF(VLOOKUP(F$2,行为概览!$D$3:$J$33,7,0)="","",VLOOKUP(F$2,行为概览!$D$3:$J$33,7,0)) -> 15 | G152: =IF(VLOOKUP(G$2,行为概览!$D$3:$J$33,7,0)="","",VLOOKUP(G$2,行为概览!$D$3:$J$33,7,0)) | H152: =IF(VLOOKUP(H$2,行为概览!$D$3:$J$33,7,0)="","",VLOOKUP(H$2,行为概览!$D$3:$J$33,7,0)) | I152: =IF(VLOOKUP(I$2,行为概览!$D$3:$J$33,7,0)="","",VLOOKUP(I$2,行为概览!$D$3:$J$33,7,0)) | J152: =IF(VLOOKUP(J$2,行为概览!$D$3:$J$33,7,0)="","",VLOOKUP(J$2,行为概览!$D$3:$J$33,7,0)) | ... AE152: =IF(VLOOKUP(AE$2,行为概览!$D$3:$J$33,7,0)="","",VLOOKUP(AE$2,行为概览!$D$3:$J$33,7,0)) | AF152: =IF(C152="","",ROUND(C152*玩法行为规划!B152,2)) -> 16.67 | AG152: =IF(D152="","",ROUND(D152*玩法行为规划!C152,2)) -> 6.6 | AH152: =IF(E152="","",ROUND(E152*玩法行为规划!D152,2)) -> 2.5 | AI152: =IF(F152="","",ROUND(F152*玩法行为规划!E152,2)) -> 15 | AJ152: =IF(G152="","",ROUND(G152*玩法行为规划!F152,2)) | AK152: =IF(H152="","",ROUND(H152*玩法行为规划!G152,2)) | AL152: =IF(I152="","",ROUND(I152*玩法行为规划!H152,2)) | AM152: =IF(J152="","",ROUND(J152*玩法行为规划!I152,2)) | ... BH152: =IF(AE152="","",ROUND(AE152*玩法行为规划!AD152,2)) | BI152: =SUM(AF152:BF152) -> 200.77 | BJ152: =B152*BI152 -> 12046200 | BK152: =ROUND(B152*(6+MAX(A152-30,0)*1.1),-2) -> 8280000 | BL152: =IF(--RIGHT(A152,1)=0,SUM(BK152:BK161),"") -> 8280000 | BM152: =BK152/BN152 -> 0.021017406 | BN152: =INT(BJ152*升级节奏!G152+BK152) -> 393959170 | BO152: =ROUND(B152/90,0) -> 667

Sheet 宠物经验
C1: 日常活动每日宠物经验权重 | S1: 定时活动每日经验权重 | AD1: 节日活动每日经验权重
A2: 等级 | B2: 基准效率1小时获得宠物经验(h) | C2: 职业日常 | D2: 日常副本 | E2: 英雄试炼 | F2: 冰封王座 | G2: 考古 | H2: 运镖 | I2: 卡拉赞系列 | J2: 卡拉赞精英 | K2: 精英副本 | L2: 公会任务(周7轮) | M2: 暗夜马戏团(周20轮) | N2: 野外挂机/离线经验 | O2: 经验道具 | P2: 分享 | Q2: 双倍点数 | R2: 援助战斗和道具 | S2: 古神爪牙 | T2: 幼龙 | U2: 屠龙 | V2: 古神 | W2: 艾泽拉斯地理探索 | X2: 艾泽拉斯百科竞赛 | Y2: 职业闯关(周2次) | Z2: 竞技场（周5次） | AA2: 公会副本(周1次) | AB2: 帮派强盗 | AC2: 帮派采药 | AD2: 节日活动1 | AE2: 节日活动2 | AF2: 每日循环总量 | AG2: 每日循环收益 | AH2: 剧情任务收益 | AI2: 剧情任务分段宠物经验 | AJ2: 宠物升级经验 | AK2: 升级时间可额外同时练几只宠 | AL2: 升级停留时间可回头练几只宠 | AM2: 宠物经验总循环收益 | AN2: 总升级时间总共可额外练几只宠 | AO2: 刷野战斗宠物经验 | AP2: 野怪战斗多少场升级
A3: 1 | B3: =升级节奏!D3 -> 5000 | C3: =IF(VLOOKUP(C$2,行为概览!$D$3:$K$33,8,0)="","",VLOOKUP(C$2,行为概览!$D$3:$K$33,8,0)*玩法行为规划!B3) -> 0 | D3: =IF(VLOOKUP(D$2,行为概览!$D$3:$K$33,8,0)="","",VLOOKUP(D$2,行为概览!$D$3:$K$33,8,0)*玩法行为规划!C3) -> 0 | E3: =IF(VLOOKUP(E$2,行为概览!$D$3:$K$33,8,0)="","",VLOOKUP(E$2,行为概览!$D$3:$K$33,8,0)*玩法行为规划!D3) | F3: =IF(VLOOKUP(F$2,行为概览!$D$3:$K$33,8,0)="","",VLOOKUP(F$2,行为概览!$D$3:$K$33,8,0)*玩法行为规划!E3) -> 0 | G3: =IF(VLOOKUP(G$2,行为概览!$D$3:$K$33,8,0)="","",VLOOKUP(G$2,行为概览!$D$3:$K$33,8,0)*玩法行为规划!F3) -> 0 | H3: =IF(VLOOKUP(H$2,行为概览!$D$3:$K$33,8,0)="","",VLOOKUP(H$2,行为概览!$D$3:$K$33,8,0)*玩法行为规划!G3) | I3: =IF(VLOOKUP(I$2,行为概览!$D$3:$K$33,8,0)="","",VLOOKUP(I$2,行为概览!$D$3:$K$33,8,0)*玩法行为规划!H3) | J3: =IF(VLOOKUP(J$2,行为概览!$D$3:$K$33,8,0)="","",VLOOKUP(J$2,行为概览!$D$3:$K$33,8,0)*玩法行为规划!I3) | ... AE3: =IF(VLOOKUP(AE$2,行为概览!$D$3:$K$33,8,0)="","",VLOOKUP(AE$2,行为概览!$D$3:$K$33,8,0)*玩法行为规划!AD3) | AF3: =SUM(C3:AC3) -> 5.2 | AG3: =INT(B3*AF3) -> 26000 | AH3: =AJ8 -> 1820 | AI3: =SUM($AH$3:AH11) -> 48180 | AJ3: =20+50*A3^2 -> 70 | AK3: =ROUND(AG3*升级节奏!G3/AJ3,2) -> 0 | AL3: =ROUND(AG3*升级节奏!G3/SUM($AJ$3:AJ3),2) -> 0 | AM3: =ROUND(AG3*升级节奏!G3,2) -> 0 | AN3: =ROUND(AG3*升级节奏!H3/SUM($AJ$3:AJ3),2) -> 0 | AO3: =ROUND(B3/60,0) -> 83 | AP3: =ROUND(AJ3/AO3,0) -> 1
A4: 2 | B4: =升级节奏!D4 -> 10000 | C4: =IF(VLOOKUP(C$2,行为概览!$D$3:$K$33,8,0)="","",VLOOKUP(C$2,行为概览!$D$3:$K$33,8,0)*玩法行为规划!B4) -> 0 | D4: =IF(VLOOKUP(D$2,行为概览!$D$3:$K$33,8,0)="","",VLOOKUP(D$2,行为概览!$D$3:$K$33,8,0)*玩法行为规划!C4) -> 0 | E4: =IF(VLOOKUP(E$2,行为概览!$D$3:$K$33,8,0)="","",VLOOKUP(E$2,行为概览!$D$3:$K$33,8,0)*玩法行为规划!D4) | F4: =IF(VLOOKUP(F$2,行为概览!$D$3:$K$33,8,0)="","",VLOOKUP(F$2,行为概览!$D$3:$K$33,8,0)*玩法行为规划!E4) -> 0 | G4: =IF(VLOOKUP(G$2,行为概览!$D$3:$K$33,8,0)="","",VLOOKUP(G$2,行为概览!$D$3:$K$33,8,0)*玩法行为规划!F4) -> 0 | H4: =IF(VLOOKUP(H$2,行为概览!$D$3:$K$33,8,0)="","",VLOOKUP(H$2,行为概览!$D$3:$K$33,8,0)*玩法行为规划!G4) | I4: =IF(VLOOKUP(I$2,行为概览!$D$3:$K$33,8,0)="","",VLOOKUP(I$2,行为概览!$D$3:$K$33,8,0)*玩法行为规划!H4) | J4: =IF(VLOOKUP(J$2,行为概览!$D$3:$K$33,8,0)="","",VLOOKUP(J$2,行为概览!$D$3:$K$33,8,0)*玩法行为规划!I4) | ... AE4: =IF(VLOOKUP(AE$2,行为概览!$D$3:$K$33,8,0)="","",VLOOKUP(AE$2,行为概览!$D$3:$K$33,8,0)*玩法行为规划!AD4) | AF4: =SUM(C4:AC4) -> 5.2 | AG4: =INT(B4*AF4) -> 52000 | AH4: =AJ9 -> 2470 | AJ4: =20+50*A4^2 -> 220 | AK4: =ROUND(AG4*升级节奏!G4/AJ4,2) -> 0 | AL4: =ROUND(AG4*升级节奏!G4/SUM($AJ$3:AJ4),2) -> 0 | AM4: =ROUND(AG4*升级节奏!G4,2) -> 0 | AN4: =ROUND(AG4*升级节奏!H4/SUM($AJ$3:AJ4),2) -> 0 | AO4: =ROUND(B4/60,0) -> 167 | AP4: =ROUND(AJ4/AO4,0) -> 1
A5: 3 | B5: =升级节奏!D5 -> 15000 | C5: =IF(VLOOKUP(C$2,行为概览!$D$3:$K$33,8,0)="","",VLOOKUP(C$2,行为概览!$D$3:$K$33,8,0)*玩法行为规划!B5) -> 0 | D5: =IF(VLOOKUP(D$2,行为概览!$D$3:$K$33,8,0)="","",VLOOKUP(D$2,行为概览!$D$3:$K$33,8,0)*玩法行为规划!C5) -> 0 | E5: =IF(VLOOKUP(E$2,行为概览!$D$3:$K$33,8,0)="","",VLOOKUP(E$2,行为概览!$D$3:$K$33,8,0)*玩法行为规划!D5) | F5: =IF(VLOOKUP(F$2,行为概览!$D$3:$K$33,8,0)="","",VLOOKUP(F$2,行为概览!$D$3:$K$33,8,0)*玩法行为规划!E5) -> 0 | G5: =IF(VLOOKUP(G$2,行为概览!$D$3:$K$33,8,0)="","",VLOOKUP(G$2,行为概览!$D$3:$K$33,8,0)*玩法行为规划!F5) -> 0 | H5: =IF(VLOOKUP(H$2,行为概览!$D$3:$K$33,8,0)="","",VLOOKUP(H$2,行为概览!$D$3:$K$33,8,0)*玩法行为规划!G5) | I5: =IF(VLOOKUP(I$2,行为概览!$D$3:$K$33,8,0)="","",VLOOKUP(I$2,行为概览!$D$3:$K$33,8,0)*玩法行为规划!H5) | J5: =IF(VLOOKUP(J$2,行为概览!$D$3:$K$33,8,0)="","",VLOOKUP(J$2,行为概览!$D$3:$K$33,8,0)*玩法行为规划!I5) | ... AE5: =IF(VLOOKUP(AE$2,行为概览!$D$3:$K$33,8,0)="","",VLOOKUP(AE$2,行为概览!$D$3:$K$33,8,0)*玩法行为规划!AD5) | AF5: =SUM(C5:AC5) -> 5.2 | AG5: =INT(B5*AF5) -> 78000 | AH5: =AJ10 -> 3220 | AJ5: =20+50*A5^2 -> 470 | AK5: =ROUND(AG5*升级节奏!G5/AJ5,2) -> 0 | AL5: =ROUND(AG5*升级节奏!G5/SUM($AJ$3:AJ5),2) -> 0 | AM5: =ROUND(AG5*升级节奏!G5,2) -> 0 | AN5: =ROUND(AG5*升级节奏!H5/SUM($AJ$3:AJ5),2) -> 0 | AO5: =ROUND(B5/60,0) -> 250 | AP5: =ROUND(AJ5/AO5,0) -> 2
A6: 4 | B6: =升级节奏!D6 -> 20000 | C6: =IF(VLOOKUP(C$2,行为概览!$D$3:$K$33,8,0)="","",VLOOKUP(C$2,行为概览!$D$3:$K$33,8,0)*玩法行为规划!B6) -> 0 | D6: =IF(VLOOKUP(D$2,行为概览!$D$3:$K$33,8,0)="","",VLOOKUP(D$2,行为概览!$D$3:$K$33,8,0)*玩法行为规划!C6) -> 0 | E6: =IF(VLOOKUP(E$2,行为概览!$D$3:$K$33,8,0)="","",VLOOKUP(E$2,行为概览!$D$3:$K$33,8,0)*玩法行为规划!D6) | F6: =IF(VLOOKUP(F$2,行为概览!$D$3:$K$33,8,0)="","",VLOOKUP(F$2,行为概览!$D$3:$K$33,8,0)*玩法行为规划!E6) -> 0 | G6: =IF(VLOOKUP(G$2,行为概览!$D$3:$K$33,8,0)="","",VLOOKUP(G$2,行为概览!$D$3:$K$33,8,0)*玩法行为规划!F6) -> 0 | H6: =IF(VLOOKUP(H$2,行为概览!$D$3:$K$33,8,0)="","",VLOOKUP(H$2,行为概览!$D$3:$K$33,8,0)*玩法行为规划!G6) | I6: =IF(VLOOKUP(I$2,行为概览!$D$3:$K$33,8,0)="","",VLOOKUP(I$2,行为概览!$D$3:$K$33,8,0)*玩法行为规划!H6) | J6: =IF(VLOOKUP(J$2,行为概览!$D$3:$K$33,8,0)="","",VLOOKUP(J$2,行为概览!$D$3:$K$33,8,0)*玩法行为规划!I6) | ... AE6: =IF(VLOOKUP(AE$2,行为概览!$D$3:$K$33,8,0)="","",VLOOKUP(AE$2,行为概览!$D$3:$K$33,8,0)*玩法行为规划!AD6) | AF6: =SUM(C6:AC6) -> 5.2 | AG6: =INT(B6*AF6) -> 104000 | AH6: =AJ11 -> 4070 | AJ6: =20+50*A6^2 -> 820 | AK6: =ROUND(AG6*升级节奏!G6/AJ6,2) -> 0 | AL6: =ROUND(AG6*升级节奏!G6/SUM($AJ$3:AJ6),2) -> 0 | AM6: =ROUND(AG6*升级节奏!G6,2) -> 0 | AN6: =ROUND(AG6*升级节奏!H6/SUM($AJ$3:AJ6),2) -> 0 | AO6: =ROUND(B6/60,0) -> 333 | AP6: =ROUND(AJ6/AO6,0) -> 2
A7: 5 | B7: =升级节奏!D7 -> 25000 | C7: =IF(VLOOKUP(C$2,行为概览!$D$3:$K$33,8,0)="","",VLOOKUP(C$2,行为概览!$D$3:$K$33,8,0)*玩法行为规划!B7) -> 0 | D7: =IF(VLOOKUP(D$2,行为概览!$D$3:$K$33,8,0)="","",VLOOKUP(D$2,行为概览!$D$3:$K$33,8,0)*玩法行为规划!C7) -> 0 | E7: =IF(VLOOKUP(E$2,行为概览!$D$3:$K$33,8,0)="","",VLOOKUP(E$2,行为概览!$D$3:$K$33,8,0)*玩法行为规划!D7) | F7: =IF(VLOOKUP(F$2,行为概览!$D$3:$K$33,8,0)="","",VLOOKUP(F$2,行为概览!$D$3:$K$33,8,0)*玩法行为规划!E7) -> 0 | G7: =IF(VLOOKUP(G$2,行为概览!$D$3:$K$33,8,0)="","",VLOOKUP(G$2,行为概览!$D$3:$K$33,8,0)*玩法行为规划!F7) -> 0 | H7: =IF(VLOOKUP(H$2,行为概览!$D$3:$K$33,8,0)="","",VLOOKUP(H$2,行为概览!$D$3:$K$33,8,0)*玩法行为规划!G7) | I7: =IF(VLOOKUP(I$2,行为概览!$D$3:$K$33,8,0)="","",VLOOKUP(I$2,行为概览!$D$3:$K$33,8,0)*玩法行为规划!H7) | J7: =IF(VLOOKUP(J$2,行为概览!$D$3:$K$33,8,0)="","",VLOOKUP(J$2,行为概览!$D$3:$K$33,8,0)*玩法行为规划!I7) | ... AE7: =IF(VLOOKUP(AE$2,行为概览!$D$3:$K$33,8,0)="","",VLOOKUP(AE$2,行为概览!$D$3:$K$33,8,0)*玩法行为规划!AD7) | AF7: =SUM(C7:AC7) -> 5.2 | AG7: =INT(B7*AF7) -> 130000 | AH7: =AJ12 -> 5020 | AJ7: =20+50*A7^2 -> 1270 | AK7: =ROUND(AG7*升级节奏!G7/AJ7,2) -> 0 | AL7: =ROUND(AG7*升级节奏!G7/SUM($AJ$3:AJ7),2) -> 0 | AM7: =ROUND(AG7*升级节奏!G7,2) -> 0 | AN7: =ROUND(AG7*升级节奏!H7/SUM($AJ$3:AJ7),2) -> 0 | AO7: =ROUND(B7/60,0) -> 417 | AP7: =ROUND(AJ7/AO7,0) -> 3
A8: 6 | B8: =升级节奏!D8 -> 30000 | C8: =IF(VLOOKUP(C$2,行为概览!$D$3:$K$33,8,0)="","",VLOOKUP(C$2,行为概览!$D$3:$K$33,8,0)*玩法行为规划!B8) -> 0 | D8: =IF(VLOOKUP(D$2,行为概览!$D$3:$K$33,8,0)="","",VLOOKUP(D$2,行为概览!$D$3:$K$33,8,0)*玩法行为规划!C8) -> 0 | E8: =IF(VLOOKUP(E$2,行为概览!$D$3:$K$33,8,0)="","",VLOOKUP(E$2,行为概览!$D$3:$K$33,8,0)*玩法行为规划!D8) | F8: =IF(VLOOKUP(F$2,行为概览!$D$3:$K$33,8,0)="","",VLOOKUP(F$2,行为概览!$D$3:$K$33,8,0)*玩法行为规划!E8) -> 0 | G8: =IF(VLOOKUP(G$2,行为概览!$D$3:$K$33,8,0)="","",VLOOKUP(G$2,行为概览!$D$3:$K$33,8,0)*玩法行为规划!F8) -> 0 | H8: =IF(VLOOKUP(H$2,行为概览!$D$3:$K$33,8,0)="","",VLOOKUP(H$2,行为概览!$D$3:$K$33,8,0)*玩法行为规划!G8) | I8: =IF(VLOOKUP(I$2,行为概览!$D$3:$K$33,8,0)="","",VLOOKUP(I$2,行为概览!$D$3:$K$33,8,0)*玩法行为规划!H8) | J8: =IF(VLOOKUP(J$2,行为概览!$D$3:$K$33,8,0)="","",VLOOKUP(J$2,行为概览!$D$3:$K$33,8,0)*玩法行为规划!I8) | ... AE8: =IF(VLOOKUP(AE$2,行为概览!$D$3:$K$33,8,0)="","",VLOOKUP(AE$2,行为概览!$D$3:$K$33,8,0)*玩法行为规划!AD8) | AF8: =SUM(C8:AC8) -> 5.2 | AG8: =INT(B8*AF8) -> 156000 | AH8: =AJ13 -> 6070 | AJ8: =20+50*A8^2 -> 1820 | AK8: =ROUND(AG8*升级节奏!G8/AJ8,2) -> 0 | AL8: =ROUND(AG8*升级节奏!G8/SUM($AJ$3:AJ8),2) -> 0 | AM8: =ROUND(AG8*升级节奏!G8,2) -> 0 | AN8: =ROUND(AG8*升级节奏!H8/SUM($AJ$3:AJ8),2) -> 0 | AO8: =ROUND(B8/60,0) -> 500 | AP8: =ROUND(AJ8/AO8,0) -> 4
A9: 7 | B9: =升级节奏!D9 -> 35000 | C9: =IF(VLOOKUP(C$2,行为概览!$D$3:$K$33,8,0)="","",VLOOKUP(C$2,行为概览!$D$3:$K$33,8,0)*玩法行为规划!B9) -> 0 | D9: =IF(VLOOKUP(D$2,行为概览!$D$3:$K$33,8,0)="","",VLOOKUP(D$2,行为概览!$D$3:$K$33,8,0)*玩法行为规划!C9) -> 0 | E9: =IF(VLOOKUP(E$2,行为概览!$D$3:$K$33,8,0)="","",VLOOKUP(E$2,行为概览!$D$3:$K$33,8,0)*玩法行为规划!D9) | F9: =IF(VLOOKUP(F$2,行为概览!$D$3:$K$33,8,0)="","",VLOOKUP(F$2,行为概览!$D$3:$K$33,8,0)*玩法行为规划!E9) -> 0 | G9: =IF(VLOOKUP(G$2,行为概览!$D$3:$K$33,8,0)="","",VLOOKUP(G$2,行为概览!$D$3:$K$33,8,0)*玩法行为规划!F9) -> 0 | H9: =IF(VLOOKUP(H$2,行为概览!$D$3:$K$33,8,0)="","",VLOOKUP(H$2,行为概览!$D$3:$K$33,8,0)*玩法行为规划!G9) | I9: =IF(VLOOKUP(I$2,行为概览!$D$3:$K$33,8,0)="","",VLOOKUP(I$2,行为概览!$D$3:$K$33,8,0)*玩法行为规划!H9) | J9: =IF(VLOOKUP(J$2,行为概览!$D$3:$K$33,8,0)="","",VLOOKUP(J$2,行为概览!$D$3:$K$33,8,0)*玩法行为规划!I9) | ... AE9: =IF(VLOOKUP(AE$2,行为概览!$D$3:$K$33,8,0)="","",VLOOKUP(AE$2,行为概览!$D$3:$K$33,8,0)*玩法行为规划!AD9) | AF9: =SUM(C9:AC9) -> 5.2 | AG9: =INT(B9*AF9) -> 182000 | AH9: =AJ14 -> 7220 | AJ9: =20+50*A9^2 -> 2470 | AK9: =ROUND(AG9*升级节奏!G9/AJ9,2) -> 0 | AL9: =ROUND(AG9*升级节奏!G9/SUM($AJ$3:AJ9),2) -> 0 | AM9: =ROUND(AG9*升级节奏!G9,2) -> 0 | AN9: =ROUND(AG9*升级节奏!H9/SUM($AJ$3:AJ9),2) -> 0 | AO9: =ROUND(B9/60,0) -> 583 | AP9: =ROUND(AJ9/AO9,0) -> 4
A10: 8 | B10: =升级节奏!D10 -> 40000 | C10: =IF(VLOOKUP(C$2,行为概览!$D$3:$K$33,8,0)="","",VLOOKUP(C$2,行为概览!$D$3:$K$33,8,0)*玩法行为规划!B10) -> 0 | D10: =IF(VLOOKUP(D$2,行为概览!$D$3:$K$33,8,0)="","",VLOOKUP(D$2,行为概览!$D$3:$K$33,8,0)*玩法行为规划!C10) -> 0 | E10: =IF(VLOOKUP(E$2,行为概览!$D$3:$K$33,8,0)="","",VLOOKUP(E$2,行为概览!$D$3:$K$33,8,0)*玩法行为规划!D10) | F10: =IF(VLOOKUP(F$2,行为概览!$D$3:$K$33,8,0)="","",VLOOKUP(F$2,行为概览!$D$3:$K$33,8,0)*玩法行为规划!E10) -> 0 | G10: =IF(VLOOKUP(G$2,行为概览!$D$3:$K$33,8,0)="","",VLOOKUP(G$2,行为概览!$D$3:$K$33,8,0)*玩法行为规划!F10) -> 0 | H10: =IF(VLOOKUP(H$2,行为概览!$D$3:$K$33,8,0)="","",VLOOKUP(H$2,行为概览!$D$3:$K$33,8,0)*玩法行为规划!G10) | I10: =IF(VLOOKUP(I$2,行为概览!$D$3:$K$33,8,0)="","",VLOOKUP(I$2,行为概览!$D$3:$K$33,8,0)*玩法行为规划!H10) | J10: =IF(VLOOKUP(J$2,行为概览!$D$3:$K$33,8,0)="","",VLOOKUP(J$2,行为概览!$D$3:$K$33,8,0)*玩法行为规划!I10) | ... AE10: =IF(VLOOKUP(AE$2,行为概览!$D$3:$K$33,8,0)="","",VLOOKUP(AE$2,行为概览!$D$3:$K$33,8,0)*玩法行为规划!AD10) | AF10: =SUM(C10:AC10) -> 5.2 | AG10: =INT(B10*AF10) -> 208000 | AH10: =AJ15 -> 8470 | AJ10: =20+50*A10^2 -> 3220 | AK10: =ROUND(AG10*升级节奏!G10/AJ10,2) -> 0 | AL10: =ROUND(AG10*升级节奏!G10/SUM($AJ$3:AJ10),2) -> 0 | AM10: =ROUND(AG10*升级节奏!G10,2) -> 0 | AN10: =ROUND(AG10*升级节奏!H10/SUM($AJ$3:AJ10),2) -> 0 | AO10: =ROUND(B10/60,0) -> 667 | AP10: =ROUND(AJ10/AO10,0) -> 5
A11: 9 | B11: =升级节奏!D11 -> 45000 | C11: =IF(VLOOKUP(C$2,行为概览!$D$3:$K$33,8,0)="","",VLOOKUP(C$2,行为概览!$D$3:$K$33,8,0)*玩法行为规划!B11) -> 0 | D11: =IF(VLOOKUP(D$2,行为概览!$D$3:$K$33,8,0)="","",VLOOKUP(D$2,行为概览!$D$3:$K$33,8,0)*玩法行为规划!C11) -> 0 | E11: =IF(VLOOKUP(E$2,行为概览!$D$3:$K$33,8,0)="","",VLOOKUP(E$2,行为概览!$D$3:$K$33,8,0)*玩法行为规划!D11) | F11: =IF(VLOOKUP(F$2,行为概览!$D$3:$K$33,8,0)="","",VLOOKUP(F$2,行为概览!$D$3:$K$33,8,0)*玩法行为规划!E11) -> 0 | G11: =IF(VLOOKUP(G$2,行为概览!$D$3:$K$33,8,0)="","",VLOOKUP(G$2,行为概览!$D$3:$K$33,8,0)*玩法行为规划!F11) -> 0 | H11: =IF(VLOOKUP(H$2,行为概览!$D$3:$K$33,8,0)="","",VLOOKUP(H$2,行为概览!$D$3:$K$33,8,0)*玩法行为规划!G11) | I11: =IF(VLOOKUP(I$2,行为概览!$D$3:$K$33,8,0)="","",VLOOKUP(I$2,行为概览!$D$3:$K$33,8,0)*玩法行为规划!H11) | J11: =IF(VLOOKUP(J$2,行为概览!$D$3:$K$33,8,0)="","",VLOOKUP(J$2,行为概览!$D$3:$K$33,8,0)*玩法行为规划!I11) | ... AE11: =IF(VLOOKUP(AE$2,行为概览!$D$3:$K$33,8,0)="","",VLOOKUP(AE$2,行为概览!$D$3:$K$33,8,0)*玩法行为规划!AD11) | AF11: =SUM(C11:AC11) -> 5.2 | AG11: =INT(B11*AF11) -> 234000 | AH11: =AJ16 -> 9820 | AJ11: =20+50*A11^2 -> 4070 | AK11: =ROUND(AG11*升级节奏!G11/AJ11,2) -> 0 | AL11: =ROUND(AG11*升级节奏!G11/SUM($AJ$3:AJ11),2) -> 0 | AM11: =ROUND(AG11*升级节奏!G11,2) -> 0 | AN11: =ROUND(AG11*升级节奏!H11/SUM($AJ$3:AJ11),2) -> 0 | AO11: =ROUND(B11/60,0) -> 750 | AP11: =ROUND(AJ11/AO11,0) -> 5
A12: 10 | B12: =升级节奏!D12 -> 50000 | C12: =IF(VLOOKUP(C$2,行为概览!$D$3:$K$33,8,0)="","",VLOOKUP(C$2,行为概览!$D$3:$K$33,8,0)*玩法行为规划!B12) -> 0 | D12: =IF(VLOOKUP(D$2,行为概览!$D$3:$K$33,8,0)="","",VLOOKUP(D$2,行为概览!$D$3:$K$33,8,0)*玩法行为规划!C12) -> 0 | E12: =IF(VLOOKUP(E$2,行为概览!$D$3:$K$33,8,0)="","",VLOOKUP(E$2,行为概览!$D$3:$K$33,8,0)*玩法行为规划!D12) | F12: =IF(VLOOKUP(F$2,行为概览!$D$3:$K$33,8,0)="","",VLOOKUP(F$2,行为概览!$D$3:$K$33,8,0)*玩法行为规划!E12) -> 0 | G12: =IF(VLOOKUP(G$2,行为概览!$D$3:$K$33,8,0)="","",VLOOKUP(G$2,行为概览!$D$3:$K$33,8,0)*玩法行为规划!F12) -> 0 | H12: =IF(VLOOKUP(H$2,行为概览!$D$3:$K$33,8,0)="","",VLOOKUP(H$2,行为概览!$D$3:$K$33,8,0)*玩法行为规划!G12) | I12: =IF(VLOOKUP(I$2,行为概览!$D$3:$K$33,8,0)="","",VLOOKUP(I$2,行为概览!$D$3:$K$33,8,0)*玩法行为规划!H12) | J12: =IF(VLOOKUP(J$2,行为概览!$D$3:$K$33,8,0)="","",VLOOKUP(J$2,行为概览!$D$3:$K$33,8,0)*玩法行为规划!I12) | ... AE12: =IF(VLOOKUP(AE$2,行为概览!$D$3:$K$33,8,0)="","",VLOOKUP(AE$2,行为概览!$D$3:$K$33,8,0)*玩法行为规划!AD12) | AF12: =SUM(C12:AC12) -> 17.2 | AG12: =INT(B12*AF12) -> 860000 | AH12: =AJ17 -> 11270 | AI12: =IF(--RIGHT(A12,1)=0,SUM(AH12:AH21),"") -> 194450 | AJ12: =20+50*A12^2 -> 5020 | AK12: =ROUND(AG12*升级节奏!G12/AJ12,2) -> 0 | AL12: =ROUND(AG12*升级节奏!G12/SUM($AJ$3:AJ12),2) -> 0 | AM12: =ROUND(AG12*升级节奏!G12,2) -> 0 | AN12: =ROUND(AG12*升级节奏!H12/SUM($AJ$3:AJ12),2) -> 0 | AO12: =ROUND(B12/60,0) -> 833 | AP12: =ROUND(AJ12/AO12,0) -> 6
A13: 11 | B13: =升级节奏!D13 -> 55000 | C13: =IF(VLOOKUP(C$2,行为概览!$D$3:$K$33,8,0)="","",VLOOKUP(C$2,行为概览!$D$3:$K$33,8,0)*玩法行为规划!B13) -> 0 | D13: =IF(VLOOKUP(D$2,行为概览!$D$3:$K$33,8,0)="","",VLOOKUP(D$2,行为概览!$D$3:$K$33,8,0)*玩法行为规划!C13) -> 0 | E13: =IF(VLOOKUP(E$2,行为概览!$D$3:$K$33,8,0)="","",VLOOKUP(E$2,行为概览!$D$3:$K$33,8,0)*玩法行为规划!D13) | F13: =IF(VLOOKUP(F$2,行为概览!$D$3:$K$33,8,0)="","",VLOOKUP(F$2,行为概览!$D$3:$K$33,8,0)*玩法行为规划!E13) -> 0 | G13: =IF(VLOOKUP(G$2,行为概览!$D$3:$K$33,8,0)="","",VLOOKUP(G$2,行为概览!$D$3:$K$33,8,0)*玩法行为规划!F13) -> 0 | H13: =IF(VLOOKUP(H$2,行为概览!$D$3:$K$33,8,0)="","",VLOOKUP(H$2,行为概览!$D$3:$K$33,8,0)*玩法行为规划!G13) | I13: =IF(VLOOKUP(I$2,行为概览!$D$3:$K$33,8,0)="","",VLOOKUP(I$2,行为概览!$D$3:$K$33,8,0)*玩法行为规划!H13) | J13: =IF(VLOOKUP(J$2,行为概览!$D$3:$K$33,8,0)="","",VLOOKUP(J$2,行为概览!$D$3:$K$33,8,0)*玩法行为规划!I13) | ... AE13: =IF(VLOOKUP(AE$2,行为概览!$D$3:$K$33,8,0)="","",VLOOKUP(AE$2,行为概览!$D$3:$K$33,8,0)*玩法行为规划!AD13) | AF13: =SUM(C13:AC13) -> 17.2 | AG13: =INT(B13*AF13) -> 946000 | AH13: =AJ18 -> 12820 | AI13: =IF(--RIGHT(A13,1)=0,SUM(AH13:AH22),"") | AJ13: =20+50*A13^2 -> 6070 | AK13: =ROUND(AG13*升级节奏!G13/AJ13,2) -> 0 | AL13: =ROUND(AG13*升级节奏!G13/SUM($AJ$3:AJ13),2) -> 0 | AM13: =ROUND(AG13*升级节奏!G13,2) -> 0 | AN13: =ROUND(AG13*升级节奏!H13/SUM($AJ$3:AJ13),2) -> 0 | AO13: =ROUND(B13/60,0) -> 917 | AP13: =ROUND(AJ13/AO13,0) -> 7
A14: 12 | B14: =升级节奏!D14 -> 60000 | C14: =IF(VLOOKUP(C$2,行为概览!$D$3:$K$33,8,0)="","",VLOOKUP(C$2,行为概览!$D$3:$K$33,8,0)*玩法行为规划!B14) -> 0 | D14: =IF(VLOOKUP(D$2,行为概览!$D$3:$K$33,8,0)="","",VLOOKUP(D$2,行为概览!$D$3:$K$33,8,0)*玩法行为规划!C14) -> 0 | E14: =IF(VLOOKUP(E$2,行为概览!$D$3:$K$33,8,0)="","",VLOOKUP(E$2,行为概览!$D$3:$K$33,8,0)*玩法行为规划!D14) | F14: =IF(VLOOKUP(F$2,行为概览!$D$3:$K$33,8,0)="","",VLOOKUP(F$2,行为概览!$D$3:$K$33,8,0)*玩法行为规划!E14) -> 0 | G14: =IF(VLOOKUP(G$2,行为概览!$D$3:$K$33,8,0)="","",VLOOKUP(G$2,行为概览!$D$3:$K$33,8,0)*玩法行为规划!F14) -> 0 | H14: =IF(VLOOKUP(H$2,行为概览!$D$3:$K$33,8,0)="","",VLOOKUP(H$2,行为概览!$D$3:$K$33,8,0)*玩法行为规划!G14) | I14: =IF(VLOOKUP(I$2,行为概览!$D$3:$K$33,8,0)="","",VLOOKUP(I$2,行为概览!$D$3:$K$33,8,0)*玩法行为规划!H14) | J14: =IF(VLOOKUP(J$2,行为概览!$D$3:$K$33,8,0)="","",VLOOKUP(J$2,行为概览!$D$3:$K$33,8,0)*玩法行为规划!I14) | ... AE14: =IF(VLOOKUP(AE$2,行为概览!$D$3:$K$33,8,0)="","",VLOOKUP(AE$2,行为概览!$D$3:$K$33,8,0)*玩法行为规划!AD14) | AF14: =SUM(C14:AC14) -> 17.2 | AG14: =INT(B14*AF14) -> 1032000 | AH14: =AJ19 -> 14470 | AI14: =IF(--RIGHT(A14,1)=0,SUM(AH14:AH23),"") | AJ14: =20+50*A14^2 -> 7220 | AK14: =ROUND(AG14*升级节奏!G14/AJ14,2) -> 0 | AL14: =ROUND(AG14*升级节奏!G14/SUM($AJ$3:AJ14),2) -> 0 | AM14: =ROUND(AG14*升级节奏!G14,2) -> 0 | AN14: =ROUND(AG14*升级节奏!H14/SUM($AJ$3:AJ14),2) -> 0 | AO14: =ROUND(B14/60,0) -> 1000 | AP14: =ROUND(AJ14/AO14,0) -> 7
A15: 13 | B15: =升级节奏!D15 -> 65000 | C15: =IF(VLOOKUP(C$2,行为概览!$D$3:$K$33,8,0)="","",VLOOKUP(C$2,行为概览!$D$3:$K$33,8,0)*玩法行为规划!B15) -> 0 | D15: =IF(VLOOKUP(D$2,行为概览!$D$3:$K$33,8,0)="","",VLOOKUP(D$2,行为概览!$D$3:$K$33,8,0)*玩法行为规划!C15) -> 0 | E15: =IF(VLOOKUP(E$2,行为概览!$D$3:$K$33,8,0)="","",VLOOKUP(E$2,行为概览!$D$3:$K$33,8,0)*玩法行为规划!D15) | F15: =IF(VLOOKUP(F$2,行为概览!$D$3:$K$33,8,0)="","",VLOOKUP(F$2,行为概览!$D$3:$K$33,8,0)*玩法行为规划!E15) -> 0 | G15: =IF(VLOOKUP(G$2,行为概览!$D$3:$K$33,8,0)="","",VLOOKUP(G$2,行为概览!$D$3:$K$33,8,0)*玩法行为规划!F15) -> 0 | H15: =IF(VLOOKUP(H$2,行为概览!$D$3:$K$33,8,0)="","",VLOOKUP(H$2,行为概览!$D$3:$K$33,8,0)*玩法行为规划!G15) | I15: =IF(VLOOKUP(I$2,行为概览!$D$3:$K$33,8,0)="","",VLOOKUP(I$2,行为概览!$D$3:$K$33,8,0)*玩法行为规划!H15) | J15: =IF(VLOOKUP(J$2,行为概览!$D$3:$K$33,8,0)="","",VLOOKUP(J$2,行为概览!$D$3:$K$33,8,0)*玩法行为规划!I15) | ... AE15: =IF(VLOOKUP(AE$2,行为概览!$D$3:$K$33,8,0)="","",VLOOKUP(AE$2,行为概览!$D$3:$K$33,8,0)*玩法行为规划!AD15) | AF15: =SUM(C15:AC15) -> 17.2 | AG15: =INT(B15*AF15) -> 1118000 | AH15: =AJ20 -> 16220 | AI15: =IF(--RIGHT(A15,1)=0,SUM(AH15:AH24),"") | AJ15: =20+50*A15^2 -> 8470 | AK15: =ROUND(AG15*升级节奏!G15/AJ15,2) -> 0 | AL15: =ROUND(AG15*升级节奏!G15/SUM($AJ$3:AJ15),2) -> 0 | AM15: =ROUND(AG15*升级节奏!G15,2) -> 0 | AN15: =ROUND(AG15*升级节奏!H15/SUM($AJ$3:AJ15),2) -> 0 | AO15: =ROUND(B15/60,0) -> 1083 | AP15: =ROUND(AJ15/AO15,0) -> 8
A16: 14 | B16: =升级节奏!D16 -> 70000 | C16: =IF(VLOOKUP(C$2,行为概览!$D$3:$K$33,8,0)="","",VLOOKUP(C$2,行为概览!$D$3:$K$33,8,0)*玩法行为规划!B16) -> 0 | D16: =IF(VLOOKUP(D$2,行为概览!$D$3:$K$33,8,0)="","",VLOOKUP(D$2,行为概览!$D$3:$K$33,8,0)*玩法行为规划!C16) -> 0 | E16: =IF(VLOOKUP(E$2,行为概览!$D$3:$K$33,8,0)="","",VLOOKUP(E$2,行为概览!$D$3:$K$33,8,0)*玩法行为规划!D16) | F16: =IF(VLOOKUP(F$2,行为概览!$D$3:$K$33,8,0)="","",VLOOKUP(F$2,行为概览!$D$3:$K$33,8,0)*玩法行为规划!E16) -> 0 | G16: =IF(VLOOKUP(G$2,行为概览!$D$3:$K$33,8,0)="","",VLOOKUP(G$2,行为概览!$D$3:$K$33,8,0)*玩法行为规划!F16) -> 0 | H16: =IF(VLOOKUP(H$2,行为概览!$D$3:$K$33,8,0)="","",VLOOKUP(H$2,行为概览!$D$3:$K$33,8,0)*玩法行为规划!G16) | I16: =IF(VLOOKUP(I$2,行为概览!$D$3:$K$33,8,0)="","",VLOOKUP(I$2,行为概览!$D$3:$K$33,8,0)*玩法行为规划!H16) | J16: =IF(VLOOKUP(J$2,行为概览!$D$3:$K$33,8,0)="","",VLOOKUP(J$2,行为概览!$D$3:$K$33,8,0)*玩法行为规划!I16) | ... AE16: =IF(VLOOKUP(AE$2,行为概览!$D$3:$K$33,8,0)="","",VLOOKUP(AE$2,行为概览!$D$3:$K$33,8,0)*玩法行为规划!AD16) | AF16: =SUM(C16:AC16) -> 17.2 | AG16: =INT(B16*AF16) -> 1204000 | AH16: =AJ21 -> 18070 | AI16: =IF(--RIGHT(A16,1)=0,SUM(AH16:AH25),"") | AJ16: =20+50*A16^2 -> 9820 | AK16: =ROUND(AG16*升级节奏!G16/AJ16,2) -> 0 | AL16: =ROUND(AG16*升级节奏!G16/SUM($AJ$3:AJ16),2) -> 0 | AM16: =ROUND(AG16*升级节奏!G16,2) -> 0 | AN16: =ROUND(AG16*升级节奏!H16/SUM($AJ$3:AJ16),2) -> 0 | AO16: =ROUND(B16/60,0) -> 1167 | AP16: =ROUND(AJ16/AO16,0) -> 8
A17: 15 | B17: =升级节奏!D17 -> 75000 | C17: =IF(VLOOKUP(C$2,行为概览!$D$3:$K$33,8,0)="","",VLOOKUP(C$2,行为概览!$D$3:$K$33,8,0)*玩法行为规划!B17) -> 0.9999 | D17: =IF(VLOOKUP(D$2,行为概览!$D$3:$K$33,8,0)="","",VLOOKUP(D$2,行为概览!$D$3:$K$33,8,0)*玩法行为规划!C17) -> 0 | E17: =IF(VLOOKUP(E$2,行为概览!$D$3:$K$33,8,0)="","",VLOOKUP(E$2,行为概览!$D$3:$K$33,8,0)*玩法行为规划!D17) | F17: =IF(VLOOKUP(F$2,行为概览!$D$3:$K$33,8,0)="","",VLOOKUP(F$2,行为概览!$D$3:$K$33,8,0)*玩法行为规划!E17) -> 0 | G17: =IF(VLOOKUP(G$2,行为概览!$D$3:$K$33,8,0)="","",VLOOKUP(G$2,行为概览!$D$3:$K$33,8,0)*玩法行为规划!F17) -> 0 | H17: =IF(VLOOKUP(H$2,行为概览!$D$3:$K$33,8,0)="","",VLOOKUP(H$2,行为概览!$D$3:$K$33,8,0)*玩法行为规划!G17) | I17: =IF(VLOOKUP(I$2,行为概览!$D$3:$K$33,8,0)="","",VLOOKUP(I$2,行为概览!$D$3:$K$33,8,0)*玩法行为规划!H17) | J17: =IF(VLOOKUP(J$2,行为概览!$D$3:$K$33,8,0)="","",VLOOKUP(J$2,行为概览!$D$3:$K$33,8,0)*玩法行为规划!I17) | ... AE17: =IF(VLOOKUP(AE$2,行为概览!$D$3:$K$33,8,0)="","",VLOOKUP(AE$2,行为概览!$D$3:$K$33,8,0)*玩法行为规划!AD17) | AF17: =SUM(C17:AC17) -> 18.1999 | AG17: =INT(B17*AF17) -> 1364992 | AH17: =AJ22 -> 20020 | AI17: =IF(--RIGHT(A17,1)=0,SUM(AH17:AH26),"") | AJ17: =20+50*A17^2 -> 11270 | AK17: =ROUND(AG17*升级节奏!G17/AJ17,2) -> 0 | AL17: =ROUND(AG17*升级节奏!G17/SUM($AJ$3:AJ17),2) -> 0 | AM17: =ROUND(AG17*升级节奏!G17,2) -> 0 | AN17: =ROUND(AG17*升级节奏!H17/SUM($AJ$3:AJ17),2) -> 0 | AO17: =ROUND(B17/60,0) -> 1250 | AP17: =ROUND(AJ17/AO17,0) -> 9
A18: 16 | B18: =升级节奏!D18 -> 80000 | C18: =IF(VLOOKUP(C$2,行为概览!$D$3:$K$33,8,0)="","",VLOOKUP(C$2,行为概览!$D$3:$K$33,8,0)*玩法行为规划!B18) -> 0.9999 | D18: =IF(VLOOKUP(D$2,行为概览!$D$3:$K$33,8,0)="","",VLOOKUP(D$2,行为概览!$D$3:$K$33,8,0)*玩法行为规划!C18) -> 0 | E18: =IF(VLOOKUP(E$2,行为概览!$D$3:$K$33,8,0)="","",VLOOKUP(E$2,行为概览!$D$3:$K$33,8,0)*玩法行为规划!D18) | F18: =IF(VLOOKUP(F$2,行为概览!$D$3:$K$33,8,0)="","",VLOOKUP(F$2,行为概览!$D$3:$K$33,8,0)*玩法行为规划!E18) -> 0 | G18: =IF(VLOOKUP(G$2,行为概览!$D$3:$K$33,8,0)="","",VLOOKUP(G$2,行为概览!$D$3:$K$33,8,0)*玩法行为规划!F18) -> 0 | H18: =IF(VLOOKUP(H$2,行为概览!$D$3:$K$33,8,0)="","",VLOOKUP(H$2,行为概览!$D$3:$K$33,8,0)*玩法行为规划!G18) | I18: =IF(VLOOKUP(I$2,行为概览!$D$3:$K$33,8,0)="","",VLOOKUP(I$2,行为概览!$D$3:$K$33,8,0)*玩法行为规划!H18) | J18: =IF(VLOOKUP(J$2,行为概览!$D$3:$K$33,8,0)="","",VLOOKUP(J$2,行为概览!$D$3:$K$33,8,0)*玩法行为规划!I18) | ... AE18: =IF(VLOOKUP(AE$2,行为概览!$D$3:$K$33,8,0)="","",VLOOKUP(AE$2,行为概览!$D$3:$K$33,8,0)*玩法行为规划!AD18) | AF18: =SUM(C18:AC18) -> 18.1999 | AG18: =INT(B18*AF18) -> 1455992 | AH18: =AJ23 -> 22070 | AI18: =IF(--RIGHT(A18,1)=0,SUM(AH18:AH27),"") | AJ18: =20+50*A18^2 -> 12820 | AK18: =ROUND(AG18*升级节奏!G18/AJ18,2) -> 0 | AL18: =ROUND(AG18*升级节奏!G18/SUM($AJ$3:AJ18),2) -> 0 | AM18: =ROUND(AG18*升级节奏!G18,2) -> 0 | AN18: =ROUND(AG18*升级节奏!H18/SUM($AJ$3:AJ18),2) -> 0 | AO18: =ROUND(B18/60,0) -> 1333 | AP18: =ROUND(AJ18/AO18,0) -> 10
A19: 17 | B19: =升级节奏!D19 -> 85000 | C19: =IF(VLOOKUP(C$2,行为概览!$D$3:$K$33,8,0)="","",VLOOKUP(C$2,行为概览!$D$3:$K$33,8,0)*玩法行为规划!B19) -> 0.9999 | D19: =IF(VLOOKUP(D$2,行为概览!$D$3:$K$33,8,0)="","",VLOOKUP(D$2,行为概览!$D$3:$K$33,8,0)*玩法行为规划!C19) -> 0 | E19: =IF(VLOOKUP(E$2,行为概览!$D$3:$K$33,8,0)="","",VLOOKUP(E$2,行为概览!$D$3:$K$33,8,0)*玩法行为规划!D19) | F19: =IF(VLOOKUP(F$2,行为概览!$D$3:$K$33,8,0)="","",VLOOKUP(F$2,行为概览!$D$3:$K$33,8,0)*玩法行为规划!E19) -> 0 | G19: =IF(VLOOKUP(G$2,行为概览!$D$3:$K$33,8,0)="","",VLOOKUP(G$2,行为概览!$D$3:$K$33,8,0)*玩法行为规划!F19) -> 0 | H19: =IF(VLOOKUP(H$2,行为概览!$D$3:$K$33,8,0)="","",VLOOKUP(H$2,行为概览!$D$3:$K$33,8,0)*玩法行为规划!G19) | I19: =IF(VLOOKUP(I$2,行为概览!$D$3:$K$33,8,0)="","",VLOOKUP(I$2,行为概览!$D$3:$K$33,8,0)*玩法行为规划!H19) | J19: =IF(VLOOKUP(J$2,行为概览!$D$3:$K$33,8,0)="","",VLOOKUP(J$2,行为概览!$D$3:$K$33,8,0)*玩法行为规划!I19) | ... AE19: =IF(VLOOKUP(AE$2,行为概览!$D$3:$K$33,8,0)="","",VLOOKUP(AE$2,行为概览!$D$3:$K$33,8,0)*玩法行为规划!AD19) | AF19: =SUM(C19:AC19) -> 18.1999 | AG19: =INT(B19*AF19) -> 1546991 | AH19: =AJ24 -> 24220 | AI19: =IF(--RIGHT(A19,1)=0,SUM(AH19:AH28),"") | AJ19: =20+50*A19^2 -> 14470 | AK19: =ROUND(AG19*升级节奏!G19/AJ19,2) -> 0 | AL19: =ROUND(AG19*升级节奏!G19/SUM($AJ$3:AJ19),2) -> 0 | AM19: =ROUND(AG19*升级节奏!G19,2) -> 0 | AN19: =ROUND(AG19*升级节奏!H19/SUM($AJ$3:AJ19),2) -> 0 | AO19: =ROUND(B19/60,0) -> 1417 | AP19: =ROUND(AJ19/AO19,0) -> 10
A20: 18 | B20: =升级节奏!D20 -> 90000 | C20: =IF(VLOOKUP(C$2,行为概览!$D$3:$K$33,8,0)="","",VLOOKUP(C$2,行为概览!$D$3:$K$33,8,0)*玩法行为规划!B20) -> 0.9999 | D20: =IF(VLOOKUP(D$2,行为概览!$D$3:$K$33,8,0)="","",VLOOKUP(D$2,行为概览!$D$3:$K$33,8,0)*玩法行为规划!C20) -> 0 | E20: =IF(VLOOKUP(E$2,行为概览!$D$3:$K$33,8,0)="","",VLOOKUP(E$2,行为概览!$D$3:$K$33,8,0)*玩法行为规划!D20) | F20: =IF(VLOOKUP(F$2,行为概览!$D$3:$K$33,8,0)="","",VLOOKUP(F$2,行为概览!$D$3:$K$33,8,0)*玩法行为规划!E20) -> 0 | G20: =IF(VLOOKUP(G$2,行为概览!$D$3:$K$33,8,0)="","",VLOOKUP(G$2,行为概览!$D$3:$K$33,8,0)*玩法行为规划!F20) -> 0 | H20: =IF(VLOOKUP(H$2,行为概览!$D$3:$K$33,8,0)="","",VLOOKUP(H$2,行为概览!$D$3:$K$33,8,0)*玩法行为规划!G20) | I20: =IF(VLOOKUP(I$2,行为概览!$D$3:$K$33,8,0)="","",VLOOKUP(I$2,行为概览!$D$3:$K$33,8,0)*玩法行为规划!H20) | J20: =IF(VLOOKUP(J$2,行为概览!$D$3:$K$33,8,0)="","",VLOOKUP(J$2,行为概览!$D$3:$K$33,8,0)*玩法行为规划!I20) | ... AE20: =IF(VLOOKUP(AE$2,行为概览!$D$3:$K$33,8,0)="","",VLOOKUP(AE$2,行为概览!$D$3:$K$33,8,0)*玩法行为规划!AD20) | AF20: =SUM(C20:AC20) -> 18.1999 | AG20: =INT(B20*AF20) -> 1637991 | AH20: =AJ25 -> 26470 | AI20: =IF(--RIGHT(A20,1)=0,SUM(AH20:AH29),"") | AJ20: =20+50*A20^2 -> 16220 | AK20: =ROUND(AG20*升级节奏!G20/AJ20,2) -> 0 | AL20: =ROUND(AG20*升级节奏!G20/SUM($AJ$3:AJ20),2) -> 0 | AM20: =ROUND(AG20*升级节奏!G20,2) -> 0 | AN20: =ROUND(AG20*升级节奏!H20/SUM($AJ$3:AJ20),2) -> 0 | AO20: =ROUND(B20/60,0) -> 1500 | AP20: =ROUND(AJ20/AO20,0) -> 11
A21: 19 | B21: =升级节奏!D21 -> 95000 | C21: =IF(VLOOKUP(C$2,行为概览!$D$3:$K$33,8,0)="","",VLOOKUP(C$2,行为概览!$D$3:$K$33,8,0)*玩法行为规划!B21) -> 0.9999 | D21: =IF(VLOOKUP(D$2,行为概览!$D$3:$K$33,8,0)="","",VLOOKUP(D$2,行为概览!$D$3:$K$33,8,0)*玩法行为规划!C21) -> 0 | E21: =IF(VLOOKUP(E$2,行为概览!$D$3:$K$33,8,0)="","",VLOOKUP(E$2,行为概览!$D$3:$K$33,8,0)*玩法行为规划!D21) | F21: =IF(VLOOKUP(F$2,行为概览!$D$3:$K$33,8,0)="","",VLOOKUP(F$2,行为概览!$D$3:$K$33,8,0)*玩法行为规划!E21) -> 0 | G21: =IF(VLOOKUP(G$2,行为概览!$D$3:$K$33,8,0)="","",VLOOKUP(G$2,行为概览!$D$3:$K$33,8,0)*玩法行为规划!F21) -> 0 | H21: =IF(VLOOKUP(H$2,行为概览!$D$3:$K$33,8,0)="","",VLOOKUP(H$2,行为概览!$D$3:$K$33,8,0)*玩法行为规划!G21) | I21: =IF(VLOOKUP(I$2,行为概览!$D$3:$K$33,8,0)="","",VLOOKUP(I$2,行为概览!$D$3:$K$33,8,0)*玩法行为规划!H21) | J21: =IF(VLOOKUP(J$2,行为概览!$D$3:$K$33,8,0)="","",VLOOKUP(J$2,行为概览!$D$3:$K$33,8,0)*玩法行为规划!I21) | ... AE21: =IF(VLOOKUP(AE$2,行为概览!$D$3:$K$33,8,0)="","",VLOOKUP(AE$2,行为概览!$D$3:$K$33,8,0)*玩法行为规划!AD21) | AF21: =SUM(C21:AC21) -> 18.1999 | AG21: =INT(B21*AF21) -> 1728990 | AH21: =AJ26 -> 28820 | AI21: =IF(--RIGHT(A21,1)=0,SUM(AH21:AH30),"") | AJ21: =20+50*A21^2 -> 18070 | AK21: =ROUND(AG21*升级节奏!G21/AJ21,2) -> 0 | AL21: =ROUND(AG21*升级节奏!G21/SUM($AJ$3:AJ21),2) -> 0 | AM21: =ROUND(AG21*升级节奏!G21,2) -> 0 | AN21: =ROUND(AG21*升级节奏!H21/SUM($AJ$3:AJ21),2) -> 0 | AO21: =ROUND(B21/60,0) -> 1583 | AP21: =ROUND(AJ21/AO21,0) -> 11
A22: 20 | B22: =升级节奏!D22 -> 100000 | C22: =IF(VLOOKUP(C$2,行为概览!$D$3:$K$33,8,0)="","",VLOOKUP(C$2,行为概览!$D$3:$K$33,8,0)*玩法行为规划!B22) -> 0.9999 | D22: =IF(VLOOKUP(D$2,行为概览!$D$3:$K$33,8,0)="","",VLOOKUP(D$2,行为概览!$D$3:$K$33,8,0)*玩法行为规划!C22) -> 1.1 | E22: =IF(VLOOKUP(E$2,行为概览!$D$3:$K$33,8,0)="","",VLOOKUP(E$2,行为概览!$D$3:$K$33,8,0)*玩法行为规划!D22) | F22: =IF(VLOOKUP(F$2,行为概览!$D$3:$K$33,8,0)="","",VLOOKUP(F$2,行为概览!$D$3:$K$33,8,0)*玩法行为规划!E22) -> 0 | G22: =IF(VLOOKUP(G$2,行为概览!$D$3:$K$33,8,0)="","",VLOOKUP(G$2,行为概览!$D$3:$K$33,8,0)*玩法行为规划!F22) -> 0 | H22: =IF(VLOOKUP(H$2,行为概览!$D$3:$K$33,8,0)="","",VLOOKUP(H$2,行为概览!$D$3:$K$33,8,0)*玩法行为规划!G22) | I22: =IF(VLOOKUP(I$2,行为概览!$D$3:$K$33,8,0)="","",VLOOKUP(I$2,行为概览!$D$3:$K$33,8,0)*玩法行为规划!H22) | J22: =IF(VLOOKUP(J$2,行为概览!$D$3:$K$33,8,0)="","",VLOOKUP(J$2,行为概览!$D$3:$K$33,8,0)*玩法行为规划!I22) | ... AE22: =IF(VLOOKUP(AE$2,行为概览!$D$3:$K$33,8,0)="","",VLOOKUP(AE$2,行为概览!$D$3:$K$33,8,0)*玩法行为规划!AD22) | AF22: =SUM(C22:AC22) -> 19.2999 | AG22: =INT(B22*AF22) -> 1929990 | AH22: =AJ27 -> 31270 | AI22: =IF(--RIGHT(A22,1)=0,SUM(AH22:AH31),"") -> 439450 | AJ22: =20+50*A22^2 -> 20020 | AK22: =ROUND(AG22*升级节奏!G22/AJ22,2) -> 0 | AL22: =ROUND(AG22*升级节奏!G22/SUM($AJ$3:AJ22),2) -> 0 | AM22: =ROUND(AG22*升级节奏!G22,2) -> 0 | AN22: =ROUND(AG22*升级节奏!H22/SUM($AJ$3:AJ22),2) -> 0 | AO22: =ROUND(B22/60,0) -> 1667 | AP22: =ROUND(AJ22/AO22,0) -> 12
A23: 21 | B23: =升级节奏!D23 -> 105000 | C23: =IF(VLOOKUP(C$2,行为概览!$D$3:$K$33,8,0)="","",VLOOKUP(C$2,行为概览!$D$3:$K$33,8,0)*玩法行为规划!B23) -> 0.9999 | D23: =IF(VLOOKUP(D$2,行为概览!$D$3:$K$33,8,0)="","",VLOOKUP(D$2,行为概览!$D$3:$K$33,8,0)*玩法行为规划!C23) -> 1.1 | E23: =IF(VLOOKUP(E$2,行为概览!$D$3:$K$33,8,0)="","",VLOOKUP(E$2,行为概览!$D$3:$K$33,8,0)*玩法行为规划!D23) | F23: =IF(VLOOKUP(F$2,行为概览!$D$3:$K$33,8,0)="","",VLOOKUP(F$2,行为概览!$D$3:$K$33,8,0)*玩法行为规划!E23) -> 0 | G23: =IF(VLOOKUP(G$2,行为概览!$D$3:$K$33,8,0)="","",VLOOKUP(G$2,行为概览!$D$3:$K$33,8,0)*玩法行为规划!F23) -> 0 | H23: =IF(VLOOKUP(H$2,行为概览!$D$3:$K$33,8,0)="","",VLOOKUP(H$2,行为概览!$D$3:$K$33,8,0)*玩法行为规划!G23) | I23: =IF(VLOOKUP(I$2,行为概览!$D$3:$K$33,8,0)="","",VLOOKUP(I$2,行为概览!$D$3:$K$33,8,0)*玩法行为规划!H23) | J23: =IF(VLOOKUP(J$2,行为概览!$D$3:$K$33,8,0)="","",VLOOKUP(J$2,行为概览!$D$3:$K$33,8,0)*玩法行为规划!I23) | ... AE23: =IF(VLOOKUP(AE$2,行为概览!$D$3:$K$33,8,0)="","",VLOOKUP(AE$2,行为概览!$D$3:$K$33,8,0)*玩法行为规划!AD23) | AF23: =SUM(C23:AC23) -> 19.2999 | AG23: =INT(B23*AF23) -> 2026489 | AH23: =AJ28 -> 33820 | AI23: =IF(--RIGHT(A23,1)=0,SUM(AH23:AH32),"") | AJ23: =20+50*A23^2 -> 22070 | AK23: =ROUND(AG23*升级节奏!G23/AJ23,2) -> 0 | AL23: =ROUND(AG23*升级节奏!G23/SUM($AJ$3:AJ23),2) -> 0 | AM23: =ROUND(AG23*升级节奏!G23,2) -> 0 | AN23: =ROUND(AG23*升级节奏!H23/SUM($AJ$3:AJ23),2) -> 0 | AO23: =ROUND(B23/60,0) -> 1750 | AP23: =ROUND(AJ23/AO23,0) -> 13
... A30: 28 | B30: =升级节奏!D30 -> 140000 | C30: =IF(VLOOKUP(C$2,行为概览!$D$3:$K$33,8,0)="","",VLOOKUP(C$2,行为概览!$D$3:$K$33,8,0)*玩法行为规划!B30) -> 0.9999 | D30: =IF(VLOOKUP(D$2,行为概览!$D$3:$K$33,8,0)="","",VLOOKUP(D$2,行为概览!$D$3:$K$33,8,0)*玩法行为规划!C30) -> 1.1 | E30: =IF(VLOOKUP(E$2,行为概览!$D$3:$K$33,8,0)="","",VLOOKUP(E$2,行为概览!$D$3:$K$33,8,0)*玩法行为规划!D30) | F30: =IF(VLOOKUP(F$2,行为概览!$D$3:$K$33,8,0)="","",VLOOKUP(F$2,行为概览!$D$3:$K$33,8,0)*玩法行为规划!E30) -> 0 | G30: =IF(VLOOKUP(G$2,行为概览!$D$3:$K$33,8,0)="","",VLOOKUP(G$2,行为概览!$D$3:$K$33,8,0)*玩法行为规划!F30) -> 0.6666 | H30: =IF(VLOOKUP(H$2,行为概览!$D$3:$K$33,8,0)="","",VLOOKUP(H$2,行为概览!$D$3:$K$33,8,0)*玩法行为规划!G30) | I30: =IF(VLOOKUP(I$2,行为概览!$D$3:$K$33,8,0)="","",VLOOKUP(I$2,行为概览!$D$3:$K$33,8,0)*玩法行为规划!H30) | J30: =IF(VLOOKUP(J$2,行为概览!$D$3:$K$33,8,0)="","",VLOOKUP(J$2,行为概览!$D$3:$K$33,8,0)*玩法行为规划!I30) | ... AE30: =IF(VLOOKUP(AE$2,行为概览!$D$3:$K$33,8,0)="","",VLOOKUP(AE$2,行为概览!$D$3:$K$33,8,0)*玩法行为规划!AD30) | AF30: =SUM(C30:AC30) -> 20.79985 | AG30: =INT(B30*AF30) -> 2911979 | AH30: =AJ35 -> 54470 | AI30: =IF(--RIGHT(A30,1)=0,SUM(AH30:AH39),"") | AJ30: =20+50*A30^2 -> 39220 | AK30: =ROUND(AG30*升级节奏!G30/AJ30,2) -> 2.19 | AL30: =ROUND(AG30*升级节奏!G30/SUM($AJ$3:AJ30),2) -> 0.22 | AM30: =ROUND(AG30*升级节奏!G30,2) -> 85806.31 | AN30: =ROUND(AG30*升级节奏!H30/SUM($AJ$3:AJ30),2) -> 0.33 | AO30: =ROUND(B30/60,0) -> 2333 | AP30: =ROUND(AJ30/AO30,0) -> 17
A31: 29 | B31: =升级节奏!D31 -> 145000 | C31: =IF(VLOOKUP(C$2,行为概览!$D$3:$K$33,8,0)="","",VLOOKUP(C$2,行为概览!$D$3:$K$33,8,0)*玩法行为规划!B31) -> 0.9999 | D31: =IF(VLOOKUP(D$2,行为概览!$D$3:$K$33,8,0)="","",VLOOKUP(D$2,行为概览!$D$3:$K$33,8,0)*玩法行为规划!C31) -> 1.1 | E31: =IF(VLOOKUP(E$2,行为概览!$D$3:$K$33,8,0)="","",VLOOKUP(E$2,行为概览!$D$3:$K$33,8,0)*玩法行为规划!D31) | F31: =IF(VLOOKUP(F$2,行为概览!$D$3:$K$33,8,0)="","",VLOOKUP(F$2,行为概览!$D$3:$K$33,8,0)*玩法行为规划!E31) -> 0 | G31: =IF(VLOOKUP(G$2,行为概览!$D$3:$K$33,8,0)="","",VLOOKUP(G$2,行为概览!$D$3:$K$33,8,0)*玩法行为规划!F31) -> 0.6666 | H31: =IF(VLOOKUP(H$2,行为概览!$D$3:$K$33,8,0)="","",VLOOKUP(H$2,行为概览!$D$3:$K$33,8,0)*玩法行为规划!G31) | I31: =IF(VLOOKUP(I$2,行为概览!$D$3:$K$33,8,0)="","",VLOOKUP(I$2,行为概览!$D$3:$K$33,8,0)*玩法行为规划!H31) | J31: =IF(VLOOKUP(J$2,行为概览!$D$3:$K$33,8,0)="","",VLOOKUP(J$2,行为概览!$D$3:$K$33,8,0)*玩法行为规划!I31) | ... AE31: =IF(VLOOKUP(AE$2,行为概览!$D$3:$K$33,8,0)="","",VLOOKUP(AE$2,行为概览!$D$3:$K$33,8,0)*玩法行为规划!AD31) | AF31: =SUM(C31:AC31) -> 20.79985 | AG31: =INT(B31*AF31) -> 3015978 | AH31: =AJ36 -> 57820 | AI31: =IF(--RIGHT(A31,1)=0,SUM(AH31:AH40),"") | AJ31: =20+50*A31^2 -> 42070 | AK31: =ROUND(AG31*升级节奏!G31/AJ36,2) -> 2.45 | AL31: =ROUND(AG31*升级节奏!G31/SUM($AJ$3:AJ36),2) -> 0.21 | AM31: =ROUND(AG31*升级节奏!G31,0) -> 141902 | AN31: =ROUND(SUM($AM$3:AM31)/SUM($AJ$3:AJ36),2) -> 0.39 | AO31: =ROUND(B31/60,0) -> 2417 | AP31: =ROUND(AJ31/AO31,0) -> 17
A32: 30 | B32: =升级节奏!D32 -> 150000 | C32: =IF(VLOOKUP(C$2,行为概览!$D$3:$K$33,8,0)="","",VLOOKUP(C$2,行为概览!$D$3:$K$33,8,0)*玩法行为规划!B32) -> 0.9999 | D32: =IF(VLOOKUP(D$2,行为概览!$D$3:$K$33,8,0)="","",VLOOKUP(D$2,行为概览!$D$3:$K$33,8,0)*玩法行为规划!C32) -> 1.1 | E32: =IF(VLOOKUP(E$2,行为概览!$D$3:$K$33,8,0)="","",VLOOKUP(E$2,行为概览!$D$3:$K$33,8,0)*玩法行为规划!D32) | F32: =IF(VLOOKUP(F$2,行为概览!$D$3:$K$33,8,0)="","",VLOOKUP(F$2,行为概览!$D$3:$K$33,8,0)*玩法行为规划!E32) -> 0 | G32: =IF(VLOOKUP(G$2,行为概览!$D$3:$K$33,8,0)="","",VLOOKUP(G$2,行为概览!$D$3:$K$33,8,0)*玩法行为规划!F32) -> 0.6666 | H32: =IF(VLOOKUP(H$2,行为概览!$D$3:$K$33,8,0)="","",VLOOKUP(H$2,行为概览!$D$3:$K$33,8,0)*玩法行为规划!G32) | I32: =IF(VLOOKUP(I$2,行为概览!$D$3:$K$33,8,0)="","",VLOOKUP(I$2,行为概览!$D$3:$K$33,8,0)*玩法行为规划!H32) | J32: =IF(VLOOKUP(J$2,行为概览!$D$3:$K$33,8,0)="","",VLOOKUP(J$2,行为概览!$D$3:$K$33,8,0)*玩法行为规划!I32) | ... AE32: =IF(VLOOKUP(AE$2,行为概览!$D$3:$K$33,8,0)="","",VLOOKUP(AE$2,行为概览!$D$3:$K$33,8,0)*玩法行为规划!AD32) | AF32: =SUM(C32:AC32) -> 21.79985 | AG32: =INT(B32*AF32) -> 3269977 | AH32: =AJ37 -> 61270 | AI32: =IF(--RIGHT(A32,1)=0,SUM(AH22:AH41),"") -> 1223900 | AJ32: =20+50*A32^2 -> 45020 | AK32: =ROUND(AG32*升级节奏!G32/AJ37,2) -> 3.56 | AL32: =ROUND(AG32*升级节奏!G32/SUM($AJ$3:AJ37),2) -> 0.29 | AM32: =ROUND(AG32*升级节奏!G32,0) -> 217998 | AN32: =ROUND(SUM($AM$3:AM32)/SUM($AJ$3:AJ37),2) -> 0.65 | AO32: =ROUND(B32/60,0) -> 2500 | AP32: =ROUND(AJ32/AO32,0) -> 18
A33: 31 | B33: =升级节奏!D33 -> 155000 | C33: =IF(VLOOKUP(C$2,行为概览!$D$3:$K$33,8,0)="","",VLOOKUP(C$2,行为概览!$D$3:$K$33,8,0)*玩法行为规划!B33) -> 0.9999 | D33: =IF(VLOOKUP(D$2,行为概览!$D$3:$K$33,8,0)="","",VLOOKUP(D$2,行为概览!$D$3:$K$33,8,0)*玩法行为规划!C33) -> 1.1 | E33: =IF(VLOOKUP(E$2,行为概览!$D$3:$K$33,8,0)="","",VLOOKUP(E$2,行为概览!$D$3:$K$33,8,0)*玩法行为规划!D33) | F33: =IF(VLOOKUP(F$2,行为概览!$D$3:$K$33,8,0)="","",VLOOKUP(F$2,行为概览!$D$3:$K$33,8,0)*玩法行为规划!E33) -> 0 | G33: =IF(VLOOKUP(G$2,行为概览!$D$3:$K$33,8,0)="","",VLOOKUP(G$2,行为概览!$D$3:$K$33,8,0)*玩法行为规划!F33) -> 0.6666 | H33: =IF(VLOOKUP(H$2,行为概览!$D$3:$K$33,8,0)="","",VLOOKUP(H$2,行为概览!$D$3:$K$33,8,0)*玩法行为规划!G33) | I33: =IF(VLOOKUP(I$2,行为概览!$D$3:$K$33,8,0)="","",VLOOKUP(I$2,行为概览!$D$3:$K$33,8,0)*玩法行为规划!H33) | J33: =IF(VLOOKUP(J$2,行为概览!$D$3:$K$33,8,0)="","",VLOOKUP(J$2,行为概览!$D$3:$K$33,8,0)*玩法行为规划!I33) | ... AE33: =IF(VLOOKUP(AE$2,行为概览!$D$3:$K$33,8,0)="","",VLOOKUP(AE$2,行为概览!$D$3:$K$33,8,0)*玩法行为规划!AD33) | AF33: =SUM(C33:AC33) -> 21.79985 | AG33: =INT(B33*AF33) -> 3378976 | AH33: =AJ38 -> 64820 | AI33: =IF(--RIGHT(A33,1)=0,SUM(AH23:AH42),"") | AJ33: =20+50*A33^2 -> 48070 | AK33: =ROUND(AG33*升级节奏!G33/AJ38,2) -> 4.61 | AL33: =ROUND(AG33*升级节奏!G33/SUM($AJ$3:AJ38),2) -> 0.37 | AM33: =ROUND(AG33*升级节奏!G33,0) -> 298758 | AN33: =ROUND(SUM($AM$3:AM33)/SUM($AJ$3:AJ38),2) -> 0.97 | AO33: =ROUND(B33/60,0) -> 2583 | AP33: =ROUND(AJ33/AO33,0) -> 19
A34: 32 | B34: =升级节奏!D34 -> 160000 | C34: =IF(VLOOKUP(C$2,行为概览!$D$3:$K$33,8,0)="","",VLOOKUP(C$2,行为概览!$D$3:$K$33,8,0)*玩法行为规划!B34) -> 0.9999 | D34: =IF(VLOOKUP(D$2,行为概览!$D$3:$K$33,8,0)="","",VLOOKUP(D$2,行为概览!$D$3:$K$33,8,0)*玩法行为规划!C34) -> 1.1 | E34: =IF(VLOOKUP(E$2,行为概览!$D$3:$K$33,8,0)="","",VLOOKUP(E$2,行为概览!$D$3:$K$33,8,0)*玩法行为规划!D34) | F34: =IF(VLOOKUP(F$2,行为概览!$D$3:$K$33,8,0)="","",VLOOKUP(F$2,行为概览!$D$3:$K$33,8,0)*玩法行为规划!E34) -> 0 | G34: =IF(VLOOKUP(G$2,行为概览!$D$3:$K$33,8,0)="","",VLOOKUP(G$2,行为概览!$D$3:$K$33,8,0)*玩法行为规划!F34) -> 0.6666 | H34: =IF(VLOOKUP(H$2,行为概览!$D$3:$K$33,8,0)="","",VLOOKUP(H$2,行为概览!$D$3:$K$33,8,0)*玩法行为规划!G34) | I34: =IF(VLOOKUP(I$2,行为概览!$D$3:$K$33,8,0)="","",VLOOKUP(I$2,行为概览!$D$3:$K$33,8,0)*玩法行为规划!H34) | J34: =IF(VLOOKUP(J$2,行为概览!$D$3:$K$33,8,0)="","",VLOOKUP(J$2,行为概览!$D$3:$K$33,8,0)*玩法行为规划!I34) | ... AE34: =IF(VLOOKUP(AE$2,行为概览!$D$3:$K$33,8,0)="","",VLOOKUP(AE$2,行为概览!$D$3:$K$33,8,0)*玩法行为规划!AD34) | AF34: =SUM(C34:AC34) -> 21.79985 | AG34: =INT(B34*AF34) -> 3487976 | AH34: =AJ39 -> 68470 | AI34: =IF(--RIGHT(A34,1)=0,SUM(AH24:AH43),"") | AJ34: =20+50*A34^2 -> 51220 | AK34: =ROUND(AG34*升级节奏!G34/AJ39,2) -> 4.77 | AL34: =ROUND(AG34*升级节奏!G34/SUM($AJ$3:AJ39),2) -> 0.37 | AM34: =ROUND(AG34*升级节奏!G34,0) -> 326707 | AN34: =ROUND(SUM($AM$3:AM34)/SUM($AJ$3:AJ39),2) -> 1.26 | AO34: =ROUND(B34/60,0) -> 2667 | AP34: =ROUND(AJ34/AO34,0) -> 19
A35: 33 | B35: =升级节奏!D35 -> 165000 | C35: =IF(VLOOKUP(C$2,行为概览!$D$3:$K$33,8,0)="","",VLOOKUP(C$2,行为概览!$D$3:$K$33,8,0)*玩法行为规划!B35) -> 0.9999 | D35: =IF(VLOOKUP(D$2,行为概览!$D$3:$K$33,8,0)="","",VLOOKUP(D$2,行为概览!$D$3:$K$33,8,0)*玩法行为规划!C35) -> 1.1 | E35: =IF(VLOOKUP(E$2,行为概览!$D$3:$K$33,8,0)="","",VLOOKUP(E$2,行为概览!$D$3:$K$33,8,0)*玩法行为规划!D35) | F35: =IF(VLOOKUP(F$2,行为概览!$D$3:$K$33,8,0)="","",VLOOKUP(F$2,行为概览!$D$3:$K$33,8,0)*玩法行为规划!E35) -> 0 | G35: =IF(VLOOKUP(G$2,行为概览!$D$3:$K$33,8,0)="","",VLOOKUP(G$2,行为概览!$D$3:$K$33,8,0)*玩法行为规划!F35) -> 0.6666 | H35: =IF(VLOOKUP(H$2,行为概览!$D$3:$K$33,8,0)="","",VLOOKUP(H$2,行为概览!$D$3:$K$33,8,0)*玩法行为规划!G35) | I35: =IF(VLOOKUP(I$2,行为概览!$D$3:$K$33,8,0)="","",VLOOKUP(I$2,行为概览!$D$3:$K$33,8,0)*玩法行为规划!H35) | J35: =IF(VLOOKUP(J$2,行为概览!$D$3:$K$33,8,0)="","",VLOOKUP(J$2,行为概览!$D$3:$K$33,8,0)*玩法行为规划!I35) | ... AE35: =IF(VLOOKUP(AE$2,行为概览!$D$3:$K$33,8,0)="","",VLOOKUP(AE$2,行为概览!$D$3:$K$33,8,0)*玩法行为规划!AD35) | AF35: =SUM(C35:AC35) -> 21.79985 | AG35: =INT(B35*AF35) -> 3596975 | AH35: =AJ40 -> 72220 | AI35: =IF(--RIGHT(A35,1)=0,SUM(AH25:AH44),"") | AJ35: =20+50*A35^2 -> 54470 | AK35: =ROUND(AG35*升级节奏!G35/AJ40,2) -> 4.93 | AL35: =ROUND(AG35*升级节奏!G35/SUM($AJ$3:AJ40),2) -> 0.37 | AM35: =ROUND(AG35*升级节奏!G35,0) -> 356400 | AN35: =ROUND(SUM($AM$3:AM35)/SUM($AJ$3:AJ40),2) -> 1.54 | AO35: =ROUND(B35/60,0) -> 2750 | AP35: =ROUND(AJ35/AO35,0) -> 20
A36: 34 | B36: =升级节奏!D36 -> 170000 | C36: =IF(VLOOKUP(C$2,行为概览!$D$3:$K$33,8,0)="","",VLOOKUP(C$2,行为概览!$D$3:$K$33,8,0)*玩法行为规划!B36) -> 0.9999 | D36: =IF(VLOOKUP(D$2,行为概览!$D$3:$K$33,8,0)="","",VLOOKUP(D$2,行为概览!$D$3:$K$33,8,0)*玩法行为规划!C36) -> 1.1 | E36: =IF(VLOOKUP(E$2,行为概览!$D$3:$K$33,8,0)="","",VLOOKUP(E$2,行为概览!$D$3:$K$33,8,0)*玩法行为规划!D36) | F36: =IF(VLOOKUP(F$2,行为概览!$D$3:$K$33,8,0)="","",VLOOKUP(F$2,行为概览!$D$3:$K$33,8,0)*玩法行为规划!E36) -> 0 | G36: =IF(VLOOKUP(G$2,行为概览!$D$3:$K$33,8,0)="","",VLOOKUP(G$2,行为概览!$D$3:$K$33,8,0)*玩法行为规划!F36) -> 0.6666 | H36: =IF(VLOOKUP(H$2,行为概览!$D$3:$K$33,8,0)="","",VLOOKUP(H$2,行为概览!$D$3:$K$33,8,0)*玩法行为规划!G36) | I36: =IF(VLOOKUP(I$2,行为概览!$D$3:$K$33,8,0)="","",VLOOKUP(I$2,行为概览!$D$3:$K$33,8,0)*玩法行为规划!H36) | J36: =IF(VLOOKUP(J$2,行为概览!$D$3:$K$33,8,0)="","",VLOOKUP(J$2,行为概览!$D$3:$K$33,8,0)*玩法行为规划!I36) | ... AE36: =IF(VLOOKUP(AE$2,行为概览!$D$3:$K$33,8,0)="","",VLOOKUP(AE$2,行为概览!$D$3:$K$33,8,0)*玩法行为规划!AD36) | AF36: =SUM(C36:AC36) -> 21.79985 | AG36: =INT(B36*AF36) -> 3705974 | AH36: =AJ41 -> 76070 | AI36: =IF(--RIGHT(A36,1)=0,SUM(AH26:AH45),"") | AJ36: =20+50*A36^2 -> 57820 | AK36: =ROUND(AG36*升级节奏!G36/AJ41,2) -> 5.61 | AL36: =ROUND(AG36*升级节奏!G36/SUM($AJ$3:AJ41),2) -> 0.42 | AM36: =ROUND(AG36*升级节奏!G36,0) -> 426681 | AN36: =ROUND(SUM($AM$3:AM36)/SUM($AJ$3:AJ41),2) -> 1.84 | AO36: =ROUND(B36/60,0) -> 2833 | AP36: =ROUND(AJ36/AO36,0) -> 20
A37: 35 | B37: =升级节奏!D37 -> 175000 | C37: =IF(VLOOKUP(C$2,行为概览!$D$3:$K$33,8,0)="","",VLOOKUP(C$2,行为概览!$D$3:$K$33,8,0)*玩法行为规划!B37) -> 0.9999 | D37: =IF(VLOOKUP(D$2,行为概览!$D$3:$K$33,8,0)="","",VLOOKUP(D$2,行为概览!$D$3:$K$33,8,0)*玩法行为规划!C37) -> 1.1 | E37: =IF(VLOOKUP(E$2,行为概览!$D$3:$K$33,8,0)="","",VLOOKUP(E$2,行为概览!$D$3:$K$33,8,0)*玩法行为规划!D37) | F37: =IF(VLOOKUP(F$2,行为概览!$D$3:$K$33,8,0)="","",VLOOKUP(F$2,行为概览!$D$3:$K$33,8,0)*玩法行为规划!E37) -> 0 | G37: =IF(VLOOKUP(G$2,行为概览!$D$3:$K$33,8,0)="","",VLOOKUP(G$2,行为概览!$D$3:$K$33,8,0)*玩法行为规划!F37) -> 0.6666 | H37: =IF(VLOOKUP(H$2,行为概览!$D$3:$K$33,8,0)="","",VLOOKUP(H$2,行为概览!$D$3:$K$33,8,0)*玩法行为规划!G37) | I37: =IF(VLOOKUP(I$2,行为概览!$D$3:$K$33,8,0)="","",VLOOKUP(I$2,行为概览!$D$3:$K$33,8,0)*玩法行为规划!H37) | J37: =IF(VLOOKUP(J$2,行为概览!$D$3:$K$33,8,0)="","",VLOOKUP(J$2,行为概览!$D$3:$K$33,8,0)*玩法行为规划!I37) | ... AE37: =IF(VLOOKUP(AE$2,行为概览!$D$3:$K$33,8,0)="","",VLOOKUP(AE$2,行为概览!$D$3:$K$33,8,0)*玩法行为规划!AD37) | AF37: =SUM(C37:AC37) -> 22.54985 | AG37: =INT(B37*AF37) -> 3946223 | AH37: =AJ42 -> 80020 | AI37: =IF(--RIGHT(A37,1)=0,SUM(AH27:AH46),"") | AJ37: =20+50*A37^2 -> 61270 | AK37: =ROUND(AG37*升级节奏!G37/AJ42,2) -> 5.99 | AL37: =ROUND(AG37*升级节奏!G37/SUM($AJ$3:AJ42),2) -> 0.43 | AM37: =ROUND(AG37*升级节奏!G37,0) -> 479302 | AN37: =ROUND(SUM($AM$3:AM37)/SUM($AJ$3:AJ42),2) -> 2.14 | AO37: =ROUND(B37/60,0) -> 2917 | AP37: =ROUND(AJ37/AO37,0) -> 21
A38: 36 | B38: =升级节奏!D38 -> 180000 | C38: =IF(VLOOKUP(C$2,行为概览!$D$3:$K$33,8,0)="","",VLOOKUP(C$2,行为概览!$D$3:$K$33,8,0)*玩法行为规划!B38) -> 0.9999 | D38: =IF(VLOOKUP(D$2,行为概览!$D$3:$K$33,8,0)="","",VLOOKUP(D$2,行为概览!$D$3:$K$33,8,0)*玩法行为规划!C38) -> 1.1 | E38: =IF(VLOOKUP(E$2,行为概览!$D$3:$K$33,8,0)="","",VLOOKUP(E$2,行为概览!$D$3:$K$33,8,0)*玩法行为规划!D38) | F38: =IF(VLOOKUP(F$2,行为概览!$D$3:$K$33,8,0)="","",VLOOKUP(F$2,行为概览!$D$3:$K$33,8,0)*玩法行为规划!E38) -> 0 | G38: =IF(VLOOKUP(G$2,行为概览!$D$3:$K$33,8,0)="","",VLOOKUP(G$2,行为概览!$D$3:$K$33,8,0)*玩法行为规划!F38) -> 0.6666 | H38: =IF(VLOOKUP(H$2,行为概览!$D$3:$K$33,8,0)="","",VLOOKUP(H$2,行为概览!$D$3:$K$33,8,0)*玩法行为规划!G38) | I38: =IF(VLOOKUP(I$2,行为概览!$D$3:$K$33,8,0)="","",VLOOKUP(I$2,行为概览!$D$3:$K$33,8,0)*玩法行为规划!H38) | J38: =IF(VLOOKUP(J$2,行为概览!$D$3:$K$33,8,0)="","",VLOOKUP(J$2,行为概览!$D$3:$K$33,8,0)*玩法行为规划!I38) | ... AE38: =IF(VLOOKUP(AE$2,行为概览!$D$3:$K$33,8,0)="","",VLOOKUP(AE$2,行为概览!$D$3:$K$33,8,0)*玩法行为规划!AD38) | AF38: =SUM(C38:AC38) -> 22.54985 | AG38: =INT(B38*AF38) -> 4058973 | AH38: =AJ43 -> 84070 | AI38: =IF(--RIGHT(A38,1)=0,SUM(AH28:AH47),"") | AJ38: =20+50*A38^2 -> 64820 | AK38: =ROUND(AG38*升级节奏!G38/AJ43,2) -> 6.18 | AL38: =ROUND(AG38*升级节奏!G38/SUM($AJ$3:AJ43),2) -> 0.44 | AM38: =ROUND(AG38*升级节奏!G38,0) -> 519413 | AN38: =ROUND(SUM($AM$3:AM38)/SUM($AJ$3:AJ43),2) -> 2.43 | AO38: =ROUND(B38/60,0) -> 3000 | AP38: =ROUND(AJ38/AO38,0) -> 22
A39: 37 | B39: =升级节奏!D39 -> 185000 | C39: =IF(VLOOKUP(C$2,行为概览!$D$3:$K$33,8,0)="","",VLOOKUP(C$2,行为概览!$D$3:$K$33,8,0)*玩法行为规划!B39) -> 0.9999 | D39: =IF(VLOOKUP(D$2,行为概览!$D$3:$K$33,8,0)="","",VLOOKUP(D$2,行为概览!$D$3:$K$33,8,0)*玩法行为规划!C39) -> 1.1 | E39: =IF(VLOOKUP(E$2,行为概览!$D$3:$K$33,8,0)="","",VLOOKUP(E$2,行为概览!$D$3:$K$33,8,0)*玩法行为规划!D39) | F39: =IF(VLOOKUP(F$2,行为概览!$D$3:$K$33,8,0)="","",VLOOKUP(F$2,行为概览!$D$3:$K$33,8,0)*玩法行为规划!E39) -> 0 | G39: =IF(VLOOKUP(G$2,行为概览!$D$3:$K$33,8,0)="","",VLOOKUP(G$2,行为概览!$D$3:$K$33,8,0)*玩法行为规划!F39) -> 0.6666 | H39: =IF(VLOOKUP(H$2,行为概览!$D$3:$K$33,8,0)="","",VLOOKUP(H$2,行为概览!$D$3:$K$33,8,0)*玩法行为规划!G39) | I39: =IF(VLOOKUP(I$2,行为概览!$D$3:$K$33,8,0)="","",VLOOKUP(I$2,行为概览!$D$3:$K$33,8,0)*玩法行为规划!H39) | J39: =IF(VLOOKUP(J$2,行为概览!$D$3:$K$33,8,0)="","",VLOOKUP(J$2,行为概览!$D$3:$K$33,8,0)*玩法行为规划!I39) | ... AE39: =IF(VLOOKUP(AE$2,行为概览!$D$3:$K$33,8,0)="","",VLOOKUP(AE$2,行为概览!$D$3:$K$33,8,0)*玩法行为规划!AD39) | AF39: =SUM(C39:AC39) -> 22.54985 | AG39: =INT(B39*AF39) -> 4171722 | AH39: =AJ44 -> 88220 | AI39: =IF(--RIGHT(A39,1)=0,SUM(AH29:AH48),"") | AJ39: =20+50*A39^2 -> 68470 | AK39: =ROUND(AG39*升级节奏!G39/AJ44,2) -> 6.37 | AL39: =ROUND(AG39*升级节奏!G39/SUM($AJ$3:AJ44),2) -> 0.44 | AM39: =ROUND(AG39*升级节奏!G39,0) -> 561757 | AN39: =ROUND(SUM($AM$3:AM39)/SUM($AJ$3:AJ44),2) -> 2.7 | AO39: =ROUND(B39/60,0) -> 3083 | AP39: =ROUND(AJ39/AO39,0) -> 22
A40: 38 | B40: =升级节奏!D40 -> 190000 | C40: =IF(VLOOKUP(C$2,行为概览!$D$3:$K$33,8,0)="","",VLOOKUP(C$2,行为概览!$D$3:$K$33,8,0)*玩法行为规划!B40) -> 0.9999 | D40: =IF(VLOOKUP(D$2,行为概览!$D$3:$K$33,8,0)="","",VLOOKUP(D$2,行为概览!$D$3:$K$33,8,0)*玩法行为规划!C40) -> 1.1 | E40: =IF(VLOOKUP(E$2,行为概览!$D$3:$K$33,8,0)="","",VLOOKUP(E$2,行为概览!$D$3:$K$33,8,0)*玩法行为规划!D40) | F40: =IF(VLOOKUP(F$2,行为概览!$D$3:$K$33,8,0)="","",VLOOKUP(F$2,行为概览!$D$3:$K$33,8,0)*玩法行为规划!E40) -> 0 | G40: =IF(VLOOKUP(G$2,行为概览!$D$3:$K$33,8,0)="","",VLOOKUP(G$2,行为概览!$D$3:$K$33,8,0)*玩法行为规划!F40) -> 0.6666 | H40: =IF(VLOOKUP(H$2,行为概览!$D$3:$K$33,8,0)="","",VLOOKUP(H$2,行为概览!$D$3:$K$33,8,0)*玩法行为规划!G40) | I40: =IF(VLOOKUP(I$2,行为概览!$D$3:$K$33,8,0)="","",VLOOKUP(I$2,行为概览!$D$3:$K$33,8,0)*玩法行为规划!H40) | J40: =IF(VLOOKUP(J$2,行为概览!$D$3:$K$33,8,0)="","",VLOOKUP(J$2,行为概览!$D$3:$K$33,8,0)*玩法行为规划!I40) | ... AE40: =IF(VLOOKUP(AE$2,行为概览!$D$3:$K$33,8,0)="","",VLOOKUP(AE$2,行为概览!$D$3:$K$33,8,0)*玩法行为规划!AD40) | AF40: =SUM(C40:AC40) -> 22.54985 | AG40: =INT(B40*AF40) -> 4284471 | AH40: =AJ45 -> 92470 | AI40: =IF(--RIGHT(A40,1)=0,SUM(AH30:AH49),"") | AJ40: =20+50*A40^2 -> 72220 | AK40: =ROUND(AG40*升级节奏!G40/AJ45,2) -> 6.56 | AL40: =ROUND(AG40*升级节奏!G40/SUM($AJ$3:AJ45),2) -> 0.44 | AM40: =ROUND(AG40*升级节奏!G40,0) -> 606395 | AN40: =ROUND(SUM($AM$3:AM40)/SUM($AJ$3:AJ45),2) -> 2.96 | AO40: =ROUND(B40/60,0) -> 3167 | AP40: =ROUND(AJ40/AO40,0) -> 23
A41: 39 | B41: =升级节奏!D41 -> 195000 | C41: =IF(VLOOKUP(C$2,行为概览!$D$3:$K$33,8,0)="","",VLOOKUP(C$2,行为概览!$D$3:$K$33,8,0)*玩法行为规划!B41) -> 0.9999 | D41: =IF(VLOOKUP(D$2,行为概览!$D$3:$K$33,8,0)="","",VLOOKUP(D$2,行为概览!$D$3:$K$33,8,0)*玩法行为规划!C41) -> 1.1 | E41: =IF(VLOOKUP(E$2,行为概览!$D$3:$K$33,8,0)="","",VLOOKUP(E$2,行为概览!$D$3:$K$33,8,0)*玩法行为规划!D41) | F41: =IF(VLOOKUP(F$2,行为概览!$D$3:$K$33,8,0)="","",VLOOKUP(F$2,行为概览!$D$3:$K$33,8,0)*玩法行为规划!E41) -> 0 | G41: =IF(VLOOKUP(G$2,行为概览!$D$3:$K$33,8,0)="","",VLOOKUP(G$2,行为概览!$D$3:$K$33,8,0)*玩法行为规划!F41) -> 0.6666 | H41: =IF(VLOOKUP(H$2,行为概览!$D$3:$K$33,8,0)="","",VLOOKUP(H$2,行为概览!$D$3:$K$33,8,0)*玩法行为规划!G41) | I41: =IF(VLOOKUP(I$2,行为概览!$D$3:$K$33,8,0)="","",VLOOKUP(I$2,行为概览!$D$3:$K$33,8,0)*玩法行为规划!H41) | J41: =IF(VLOOKUP(J$2,行为概览!$D$3:$K$33,8,0)="","",VLOOKUP(J$2,行为概览!$D$3:$K$33,8,0)*玩法行为规划!I41) | ... AE41: =IF(VLOOKUP(AE$2,行为概览!$D$3:$K$33,8,0)="","",VLOOKUP(AE$2,行为概览!$D$3:$K$33,8,0)*玩法行为规划!AD41) | AF41: =SUM(C41:AC41) -> 22.54985 | AG41: =INT(B41*AF41) -> 4397220 | AH41: =AJ46 -> 96820 | AI41: =IF(--RIGHT(A41,1)=0,SUM(AH31:AH50),"") | AJ41: =20+50*A41^2 -> 76070 | AK41: =ROUND(AG41*升级节奏!G41/AJ46,2) -> 7.98 | AL41: =ROUND(AG41*升级节奏!G41/SUM($AJ$3:AJ46),2) -> 0.53 | AM41: =ROUND(AG41*升级节奏!G41,0) -> 772188 | AN41: =ROUND(SUM($AM$3:AM41)/SUM($AJ$3:AJ46),2) -> 3.29 | AO41: =ROUND(B41/60,0) -> 3250 | AP41: =ROUND(AJ41/AO41,0) -> 23
A42: 40 | B42: =升级节奏!D42 -> 200000 | C42: =IF(VLOOKUP(C$2,行为概览!$D$3:$K$33,8,0)="","",VLOOKUP(C$2,行为概览!$D$3:$K$33,8,0)*玩法行为规划!B42) -> 0.9999 | D42: =IF(VLOOKUP(D$2,行为概览!$D$3:$K$33,8,0)="","",VLOOKUP(D$2,行为概览!$D$3:$K$33,8,0)*玩法行为规划!C42) -> 1.1 | E42: =IF(VLOOKUP(E$2,行为概览!$D$3:$K$33,8,0)="","",VLOOKUP(E$2,行为概览!$D$3:$K$33,8,0)*玩法行为规划!D42) | F42: =IF(VLOOKUP(F$2,行为概览!$D$3:$K$33,8,0)="","",VLOOKUP(F$2,行为概览!$D$3:$K$33,8,0)*玩法行为规划!E42) -> 1.5 | G42: =IF(VLOOKUP(G$2,行为概览!$D$3:$K$33,8,0)="","",VLOOKUP(G$2,行为概览!$D$3:$K$33,8,0)*玩法行为规划!F42) -> 0.6666 | H42: =IF(VLOOKUP(H$2,行为概览!$D$3:$K$33,8,0)="","",VLOOKUP(H$2,行为概览!$D$3:$K$33,8,0)*玩法行为规划!G42) | I42: =IF(VLOOKUP(I$2,行为概览!$D$3:$K$33,8,0)="","",VLOOKUP(I$2,行为概览!$D$3:$K$33,8,0)*玩法行为规划!H42) | J42: =IF(VLOOKUP(J$2,行为概览!$D$3:$K$33,8,0)="","",VLOOKUP(J$2,行为概览!$D$3:$K$33,8,0)*玩法行为规划!I42) | ... AE42: =IF(VLOOKUP(AE$2,行为概览!$D$3:$K$33,8,0)="","",VLOOKUP(AE$2,行为概览!$D$3:$K$33,8,0)*玩法行为规划!AD42) | AF42: =SUM(C42:AC42) -> 24.3832 | AG42: =INT(B42*AF42) -> 4876640 | AH42: =AJ47 -> 101270 | AI42: =IF(--RIGHT(A42,1)=0,SUM(AH32:AH51),"") -> 2013900 | AJ42: =20+50*A42^2 -> 80020 | AK42: =ROUND(AG42*升级节奏!G42/AJ47,2) -> 8.87 | AL42: =ROUND(AG42*升级节奏!G42/SUM($AJ$3:AJ47),2) -> 0.57 | AM42: =ROUND(AG42*升级节奏!G42,0) -> 898115 | AN42: =ROUND(SUM($AM$3:AM42)/SUM($AJ$3:AJ47),2) -> 3.65 | AO42: =ROUND(B42/60,0) -> 3333 | AP42: =ROUND(AJ42/AO42,0) -> 24
A43: 41 | B43: =升级节奏!D43 -> 205000 | C43: =IF(VLOOKUP(C$2,行为概览!$D$3:$K$33,8,0)="","",VLOOKUP(C$2,行为概览!$D$3:$K$33,8,0)*玩法行为规划!B43) -> 0.9999 | D43: =IF(VLOOKUP(D$2,行为概览!$D$3:$K$33,8,0)="","",VLOOKUP(D$2,行为概览!$D$3:$K$33,8,0)*玩法行为规划!C43) -> 1.1 | E43: =IF(VLOOKUP(E$2,行为概览!$D$3:$K$33,8,0)="","",VLOOKUP(E$2,行为概览!$D$3:$K$33,8,0)*玩法行为规划!D43) | F43: =IF(VLOOKUP(F$2,行为概览!$D$3:$K$33,8,0)="","",VLOOKUP(F$2,行为概览!$D$3:$K$33,8,0)*玩法行为规划!E43) -> 1.5 | G43: =IF(VLOOKUP(G$2,行为概览!$D$3:$K$33,8,0)="","",VLOOKUP(G$2,行为概览!$D$3:$K$33,8,0)*玩法行为规划!F43) -> 0.6666 | H43: =IF(VLOOKUP(H$2,行为概览!$D$3:$K$33,8,0)="","",VLOOKUP(H$2,行为概览!$D$3:$K$33,8,0)*玩法行为规划!G43) | I43: =IF(VLOOKUP(I$2,行为概览!$D$3:$K$33,8,0)="","",VLOOKUP(I$2,行为概览!$D$3:$K$33,8,0)*玩法行为规划!H43) | J43: =IF(VLOOKUP(J$2,行为概览!$D$3:$K$33,8,0)="","",VLOOKUP(J$2,行为概览!$D$3:$K$33,8,0)*玩法行为规划!I43) | ... AE43: =IF(VLOOKUP(AE$2,行为概览!$D$3:$K$33,8,0)="","",VLOOKUP(AE$2,行为概览!$D$3:$K$33,8,0)*玩法行为规划!AD43) | AF43: =SUM(C43:AC43) -> 24.3832 | AG43: =INT(B43*AF43) -> 4998556 | AH43: =AJ48 -> 105820 | AI43: =IF(--RIGHT(A43,1)=0,SUM(AH33:AH52),"") | AJ43: =20+50*A43^2 -> 84070 | AK43: =ROUND(AG43*升级节奏!G43/AJ48,2) -> 9.11 | AL43: =ROUND(AG43*升级节奏!G43/SUM($AJ$3:AJ48),2) -> 0.58 | AM43: =ROUND(AG43*升级节奏!G43,0) -> 964430 | AN43: =ROUND(SUM($AM$3:AM43)/SUM($AJ$3:AJ48),2) -> 3.99 | AO43: =ROUND(B43/60,0) -> 3417 | AP43: =ROUND(AJ43/AO43,0) -> 25
... A147: 145 | B147: =升级节奏!D147 -> 725000 | C147: =IF(VLOOKUP(C$2,行为概览!$D$3:$K$33,8,0)="","",VLOOKUP(C$2,行为概览!$D$3:$K$33,8,0)*玩法行为规划!B147) -> 0.9999 | D147: =IF(VLOOKUP(D$2,行为概览!$D$3:$K$33,8,0)="","",VLOOKUP(D$2,行为概览!$D$3:$K$33,8,0)*玩法行为规划!C147) -> 1.1 | E147: =IF(VLOOKUP(E$2,行为概览!$D$3:$K$33,8,0)="","",VLOOKUP(E$2,行为概览!$D$3:$K$33,8,0)*玩法行为规划!D147) | F147: =IF(VLOOKUP(F$2,行为概览!$D$3:$K$33,8,0)="","",VLOOKUP(F$2,行为概览!$D$3:$K$33,8,0)*玩法行为规划!E147) -> 1.5 | G147: =IF(VLOOKUP(G$2,行为概览!$D$3:$K$33,8,0)="","",VLOOKUP(G$2,行为概览!$D$3:$K$33,8,0)*玩法行为规划!F147) -> 0.6666 | H147: =IF(VLOOKUP(H$2,行为概览!$D$3:$K$33,8,0)="","",VLOOKUP(H$2,行为概览!$D$3:$K$33,8,0)*玩法行为规划!G147) | I147: =IF(VLOOKUP(I$2,行为概览!$D$3:$K$33,8,0)="","",VLOOKUP(I$2,行为概览!$D$3:$K$33,8,0)*玩法行为规划!H147) | J147: =IF(VLOOKUP(J$2,行为概览!$D$3:$K$33,8,0)="","",VLOOKUP(J$2,行为概览!$D$3:$K$33,8,0)*玩法行为规划!I147) | ... AE147: =IF(VLOOKUP(AE$2,行为概览!$D$3:$K$33,8,0)="","",VLOOKUP(AE$2,行为概览!$D$3:$K$33,8,0)*玩法行为规划!AD147) | AF147: =SUM(C147:AC147) -> 24.13315 | AG147: =INT(B147*AF147) -> 17496533 | AH147: =AJ152 -> 1125020 | AI147: =IF(--RIGHT(A147,1)=0,SUM(AH137:AH156),"") | AJ147: =20+50*A147^2 -> 1051270 | AK147: =ROUND(AG147*升级节奏!G147/AJ152,2) -> 465.43 | AL147: =ROUND(AG147*升级节奏!G147/SUM($AJ$3:AJ152),2) -> 9.22 | AM147: =ROUND(AG147*升级节奏!G147,0) -> 523620201 | AN147: =ROUND(SUM($AM$3:AM147)/SUM($AJ$3:AJ152),2) -> 327.96 | AO147: =ROUND(B147/60,0) -> 12083 | AP147: =ROUND(AJ147/AO147,0) -> 87
A148: 146 | B148: =升级节奏!D148 -> 730000 | C148: =IF(VLOOKUP(C$2,行为概览!$D$3:$K$33,8,0)="","",VLOOKUP(C$2,行为概览!$D$3:$K$33,8,0)*玩法行为规划!B148) -> 0.9999 | D148: =IF(VLOOKUP(D$2,行为概览!$D$3:$K$33,8,0)="","",VLOOKUP(D$2,行为概览!$D$3:$K$33,8,0)*玩法行为规划!C148) -> 1.1 | E148: =IF(VLOOKUP(E$2,行为概览!$D$3:$K$33,8,0)="","",VLOOKUP(E$2,行为概览!$D$3:$K$33,8,0)*玩法行为规划!D148) | F148: =IF(VLOOKUP(F$2,行为概览!$D$3:$K$33,8,0)="","",VLOOKUP(F$2,行为概览!$D$3:$K$33,8,0)*玩法行为规划!E148) -> 1.5 | G148: =IF(VLOOKUP(G$2,行为概览!$D$3:$K$33,8,0)="","",VLOOKUP(G$2,行为概览!$D$3:$K$33,8,0)*玩法行为规划!F148) -> 0.6666 | H148: =IF(VLOOKUP(H$2,行为概览!$D$3:$K$33,8,0)="","",VLOOKUP(H$2,行为概览!$D$3:$K$33,8,0)*玩法行为规划!G148) | I148: =IF(VLOOKUP(I$2,行为概览!$D$3:$K$33,8,0)="","",VLOOKUP(I$2,行为概览!$D$3:$K$33,8,0)*玩法行为规划!H148) | J148: =IF(VLOOKUP(J$2,行为概览!$D$3:$K$33,8,0)="","",VLOOKUP(J$2,行为概览!$D$3:$K$33,8,0)*玩法行为规划!I148) | ... AE148: =IF(VLOOKUP(AE$2,行为概览!$D$3:$K$33,8,0)="","",VLOOKUP(AE$2,行为概览!$D$3:$K$33,8,0)*玩法行为规划!AD148) | AF148: =SUM(C148:AC148) -> 24.13315 | AG148: =INT(B148*AF148) -> 17617199 | AH148: =AH147 -> 1125020 | AI148: =IF(--RIGHT(A148,1)=0,SUM(AH138:AH157),"") | AJ148: =20+50*A148^2 -> 1065820 | AK148: =ROUND(AG148*升级节奏!G148/AJ$152,2) -> 475.1 | AL148: =ROUND(AG148*升级节奏!G148/SUM($AJ$3:AJ153),2) -> 9.41 | AM148: =ROUND(AG148*升级节奏!G148,0) -> 534494073 | AN148: =ROUND(SUM($AM$3:AM148)/SUM($AJ$3:AJ153),2) -> 337.36 | AO148: =ROUND(B148/60,0) -> 12167 | AP148: =ROUND(AJ148/AO148,0) -> 88
A149: 147 | B149: =升级节奏!D149 -> 735000 | C149: =IF(VLOOKUP(C$2,行为概览!$D$3:$K$33,8,0)="","",VLOOKUP(C$2,行为概览!$D$3:$K$33,8,0)*玩法行为规划!B149) -> 0.9999 | D149: =IF(VLOOKUP(D$2,行为概览!$D$3:$K$33,8,0)="","",VLOOKUP(D$2,行为概览!$D$3:$K$33,8,0)*玩法行为规划!C149) -> 1.1 | E149: =IF(VLOOKUP(E$2,行为概览!$D$3:$K$33,8,0)="","",VLOOKUP(E$2,行为概览!$D$3:$K$33,8,0)*玩法行为规划!D149) | F149: =IF(VLOOKUP(F$2,行为概览!$D$3:$K$33,8,0)="","",VLOOKUP(F$2,行为概览!$D$3:$K$33,8,0)*玩法行为规划!E149) -> 1.5 | G149: =IF(VLOOKUP(G$2,行为概览!$D$3:$K$33,8,0)="","",VLOOKUP(G$2,行为概览!$D$3:$K$33,8,0)*玩法行为规划!F149) -> 0.6666 | H149: =IF(VLOOKUP(H$2,行为概览!$D$3:$K$33,8,0)="","",VLOOKUP(H$2,行为概览!$D$3:$K$33,8,0)*玩法行为规划!G149) | I149: =IF(VLOOKUP(I$2,行为概览!$D$3:$K$33,8,0)="","",VLOOKUP(I$2,行为概览!$D$3:$K$33,8,0)*玩法行为规划!H149) | J149: =IF(VLOOKUP(J$2,行为概览!$D$3:$K$33,8,0)="","",VLOOKUP(J$2,行为概览!$D$3:$K$33,8,0)*玩法行为规划!I149) | ... AE149: =IF(VLOOKUP(AE$2,行为概览!$D$3:$K$33,8,0)="","",VLOOKUP(AE$2,行为概览!$D$3:$K$33,8,0)*玩法行为规划!AD149) | AF149: =SUM(C149:AC149) -> 24.13315 | AG149: =INT(B149*AF149) -> 17737865 | AH149: =AH148 -> 1125020 | AI149: =IF(--RIGHT(A149,1)=0,SUM(AH139:AH158),"") | AJ149: =20+50*A149^2 -> 1080470 | AK149: =ROUND(AG149*升级节奏!G149/AJ$152,2) -> 484.9 | AL149: =ROUND(AG149*升级节奏!G149/SUM($AJ$3:AJ154),2) -> 9.6 | AM149: =ROUND(AG149*升级节奏!G149,0) -> 545517691 | AN149: =ROUND(SUM($AM$3:AM149)/SUM($AJ$3:AJ154),2) -> 346.96 | AO149: =ROUND(B149/60,0) -> 12250 | AP149: =ROUND(AJ149/AO149,0) -> 88
A150: 148 | B150: =升级节奏!D150 -> 740000 | C150: =IF(VLOOKUP(C$2,行为概览!$D$3:$K$33,8,0)="","",VLOOKUP(C$2,行为概览!$D$3:$K$33,8,0)*玩法行为规划!B150) -> 0.9999 | D150: =IF(VLOOKUP(D$2,行为概览!$D$3:$K$33,8,0)="","",VLOOKUP(D$2,行为概览!$D$3:$K$33,8,0)*玩法行为规划!C150) -> 1.1 | E150: =IF(VLOOKUP(E$2,行为概览!$D$3:$K$33,8,0)="","",VLOOKUP(E$2,行为概览!$D$3:$K$33,8,0)*玩法行为规划!D150) | F150: =IF(VLOOKUP(F$2,行为概览!$D$3:$K$33,8,0)="","",VLOOKUP(F$2,行为概览!$D$3:$K$33,8,0)*玩法行为规划!E150) -> 1.5 | G150: =IF(VLOOKUP(G$2,行为概览!$D$3:$K$33,8,0)="","",VLOOKUP(G$2,行为概览!$D$3:$K$33,8,0)*玩法行为规划!F150) -> 0.6666 | H150: =IF(VLOOKUP(H$2,行为概览!$D$3:$K$33,8,0)="","",VLOOKUP(H$2,行为概览!$D$3:$K$33,8,0)*玩法行为规划!G150) | I150: =IF(VLOOKUP(I$2,行为概览!$D$3:$K$33,8,0)="","",VLOOKUP(I$2,行为概览!$D$3:$K$33,8,0)*玩法行为规划!H150) | J150: =IF(VLOOKUP(J$2,行为概览!$D$3:$K$33,8,0)="","",VLOOKUP(J$2,行为概览!$D$3:$K$33,8,0)*玩法行为规划!I150) | ... AE150: =IF(VLOOKUP(AE$2,行为概览!$D$3:$K$33,8,0)="","",VLOOKUP(AE$2,行为概览!$D$3:$K$33,8,0)*玩法行为规划!AD150) | AF150: =SUM(C150:AC150) -> 24.13315 | AG150: =INT(B150*AF150) -> 17858531 | AH150: =AH149 -> 1125020 | AI150: =IF(--RIGHT(A150,1)=0,SUM(AH140:AH159),"") | AJ150: =20+50*A150^2 -> 1095220 | AK150: =ROUND(AG150*升级节奏!G150/AJ$152,2) -> 494.83 | AL150: =ROUND(AG150*升级节奏!G150/SUM($AJ$3:AJ155),2) -> 9.8 | AM150: =ROUND(AG150*升级节奏!G150,0) -> 556692081 | AN150: =ROUND(SUM($AM$3:AM150)/SUM($AJ$3:AJ155),2) -> 356.76 | AO150: =ROUND(B150/60,0) -> 12333 | AP150: =ROUND(AJ150/AO150,0) -> 89
A151: 149 | B151: =升级节奏!D151 -> 745000 | C151: =IF(VLOOKUP(C$2,行为概览!$D$3:$K$33,8,0)="","",VLOOKUP(C$2,行为概览!$D$3:$K$33,8,0)*玩法行为规划!B151) -> 0.9999 | D151: =IF(VLOOKUP(D$2,行为概览!$D$3:$K$33,8,0)="","",VLOOKUP(D$2,行为概览!$D$3:$K$33,8,0)*玩法行为规划!C151) -> 1.1 | E151: =IF(VLOOKUP(E$2,行为概览!$D$3:$K$33,8,0)="","",VLOOKUP(E$2,行为概览!$D$3:$K$33,8,0)*玩法行为规划!D151) | F151: =IF(VLOOKUP(F$2,行为概览!$D$3:$K$33,8,0)="","",VLOOKUP(F$2,行为概览!$D$3:$K$33,8,0)*玩法行为规划!E151) -> 1.5 | G151: =IF(VLOOKUP(G$2,行为概览!$D$3:$K$33,8,0)="","",VLOOKUP(G$2,行为概览!$D$3:$K$33,8,0)*玩法行为规划!F151) -> 0.6666 | H151: =IF(VLOOKUP(H$2,行为概览!$D$3:$K$33,8,0)="","",VLOOKUP(H$2,行为概览!$D$3:$K$33,8,0)*玩法行为规划!G151) | I151: =IF(VLOOKUP(I$2,行为概览!$D$3:$K$33,8,0)="","",VLOOKUP(I$2,行为概览!$D$3:$K$33,8,0)*玩法行为规划!H151) | J151: =IF(VLOOKUP(J$2,行为概览!$D$3:$K$33,8,0)="","",VLOOKUP(J$2,行为概览!$D$3:$K$33,8,0)*玩法行为规划!I151) | ... AE151: =IF(VLOOKUP(AE$2,行为概览!$D$3:$K$33,8,0)="","",VLOOKUP(AE$2,行为概览!$D$3:$K$33,8,0)*玩法行为规划!AD151) | AF151: =SUM(C151:AC151) -> 24.13315 | AG151: =INT(B151*AF151) -> 17979196 | AH151: =AH150 -> 1125020 | AI151: =IF(--RIGHT(A151,1)=0,SUM(AH141:AH160),"") | AJ151: =20+50*A151^2 -> 1110070 | AK151: =ROUND(AG151*升级节奏!G151/AJ$152,2) -> 504.9 | AL151: =ROUND(AG151*升级节奏!G151/SUM($AJ$3:AJ156),2) -> 10 | AM151: =ROUND(AG151*升级节奏!G151,0) -> 568018237 | AN151: =ROUND(SUM($AM$3:AM151)/SUM($AJ$3:AJ156),2) -> 366.76 | AO151: =ROUND(B151/60,0) -> 12417 | AP151: =ROUND(AJ151/AO151,0) -> 89
A152: 150 | B152: =升级节奏!D152 -> 750000 | C152: =IF(VLOOKUP(C$2,行为概览!$D$3:$K$33,8,0)="","",VLOOKUP(C$2,行为概览!$D$3:$K$33,8,0)*玩法行为规划!B152) -> 0.9999 | D152: =IF(VLOOKUP(D$2,行为概览!$D$3:$K$33,8,0)="","",VLOOKUP(D$2,行为概览!$D$3:$K$33,8,0)*玩法行为规划!C152) -> 1.1 | E152: =IF(VLOOKUP(E$2,行为概览!$D$3:$K$33,8,0)="","",VLOOKUP(E$2,行为概览!$D$3:$K$33,8,0)*玩法行为规划!D152) | F152: =IF(VLOOKUP(F$2,行为概览!$D$3:$K$33,8,0)="","",VLOOKUP(F$2,行为概览!$D$3:$K$33,8,0)*玩法行为规划!E152) -> 1.5 | G152: =IF(VLOOKUP(G$2,行为概览!$D$3:$K$33,8,0)="","",VLOOKUP(G$2,行为概览!$D$3:$K$33,8,0)*玩法行为规划!F152) -> 0.6666 | H152: =IF(VLOOKUP(H$2,行为概览!$D$3:$K$33,8,0)="","",VLOOKUP(H$2,行为概览!$D$3:$K$33,8,0)*玩法行为规划!G152) | I152: =IF(VLOOKUP(I$2,行为概览!$D$3:$K$33,8,0)="","",VLOOKUP(I$2,行为概览!$D$3:$K$33,8,0)*玩法行为规划!H152) | J152: =IF(VLOOKUP(J$2,行为概览!$D$3:$K$33,8,0)="","",VLOOKUP(J$2,行为概览!$D$3:$K$33,8,0)*玩法行为规划!I152) | ... AE152: =IF(VLOOKUP(AE$2,行为概览!$D$3:$K$33,8,0)="","",VLOOKUP(AE$2,行为概览!$D$3:$K$33,8,0)*玩法行为规划!AD152) | AF152: =SUM(C152:AC152) -> 24.13315 | AG152: =INT(B152*AF152) -> 18099862 | AH152: =AH151 -> 1125020 | AI152: =IF(--RIGHT(A152,1)=0,SUM(AH142:AH161),"") -> 12152970 | AJ152: =20+50*A152^2 -> 1125020 | AK152: =ROUND(AG152*升级节奏!G152/AJ$152,2) -> 515.1 | AL152: =ROUND(AG152*升级节奏!G152/SUM($AJ$3:AJ157),2) -> 10.2 | AM152: =ROUND(AG152*升级节奏!G152,0) -> 579497248 | AN152: =ROUND(SUM($AM$3:AM152)/SUM($AJ$3:AJ157),2) -> 376.96 | AO152: =ROUND(B152/60,0) -> 12500 | AP152: =ROUND(AJ152/AO152,0) -> 90

Sheet 银币
C1: 日常活动每日银币权重 | S1: 定时活动每日银币权重 | AD1: 节日活动每日银币权重
A2: 等级 | B2: 基准权重银币 | C2: 职业日常 | D2: 日常副本 | E2: 英雄试炼 | F2: 冰封王座 | G2: 考古 | H2: 运镖 | I2: 卡拉赞系列 | J2: 卡拉赞精英 | K2: 精英副本 | L2: 公会任务(周7轮) | M2: 暗夜马戏团(周20轮) | N2: 野外挂机/离线经验 | O2: 经验道具 | P2: 分享 | Q2: 双倍点数 | R2: 援助战斗和道具 | S2: 古神爪牙 | T2: 幼龙 | U2: 屠龙 | V2: 古神 | W2: 艾泽拉斯地理探索 | X2: 艾泽拉斯百科竞赛 | Y2: 职业闯关(周2次) | Z2: 竞技场（周5次） | AA2: 公会副本(周1次) | AB2: 帮派强盗 | AC2: 帮派采药 | AD2: 节日活动1 | AE2: 节日活动2 | AF2: 每日循环总量 | AG2: 每日循环收益 | AH2: 该等级获得循环收益 | AI2: 剧情任务收益 | AJ2: 剧情任务分段收益 | AK2: 剧情任务收益占比 | AL2: 该等级循环加一次性总收益 | AM2: 累计总收益 | AN2: 点技能消耗 | AO2: 技能累计消耗 | AP2: 盈余 | AQ2: 公会技能1类 | AR2: 公会技能2类
A3: 1 | B3: =升级节奏!E3 -> 1000 | C3: =IF(VLOOKUP(C$2,行为概览!$D$3:$L$33,9,0)="","",VLOOKUP(C$2,行为概览!$D$3:$L$33,9,0)*IF(玩法行为规划!B3>0,1,0)) -> 0 | D3: =IF(VLOOKUP(D$2,行为概览!$D$3:$L$33,9,0)="","",VLOOKUP(D$2,行为概览!$D$3:$L$33,9,0)*IF(玩法行为规划!C3>0,1,0)) -> 0 | E3: =IF(VLOOKUP(E$2,行为概览!$D$3:$L$33,9,0)="","",VLOOKUP(E$2,行为概览!$D$3:$L$33,9,0)*IF(玩法行为规划!D3>0,1,0)) -> 0 | F3: =IF(VLOOKUP(F$2,行为概览!$D$3:$L$33,9,0)="","",VLOOKUP(F$2,行为概览!$D$3:$L$33,9,0)*IF(玩法行为规划!E3>0,1,0)) -> 0 | G3: =IF(VLOOKUP(G$2,行为概览!$D$3:$L$33,9,0)="","",VLOOKUP(G$2,行为概览!$D$3:$L$33,9,0)*IF(玩法行为规划!F3>0,1,0)) | H3: =IF(VLOOKUP(H$2,行为概览!$D$3:$L$33,9,0)="","",VLOOKUP(H$2,行为概览!$D$3:$L$33,9,0)*IF(玩法行为规划!G3>0,1,0)) | I3: =IF(VLOOKUP(I$2,行为概览!$D$3:$L$33,9,0)="","",VLOOKUP(I$2,行为概览!$D$3:$L$33,9,0)*IF(玩法行为规划!H3>0,1,0)) | J3: =IF(VLOOKUP(J$2,行为概览!$D$3:$L$33,9,0)="","",VLOOKUP(J$2,行为概览!$D$3:$L$33,9,0)*IF(玩法行为规划!I3>0,1,0)) | ... AC3: =IF(VLOOKUP(AC$2,行为概览!$D$3:$L$33,9,0)="","",VLOOKUP(AC$2,行为概览!$D$3:$L$33,9,0)*IF(玩法行为规划!AB3>0,1,0)) | AD3: =IF(VLOOKUP(AD$2,行为概览!$D$3:$L$33,9,0)="","",VLOOKUP(AD$2,行为概览!$D$3:$L$33,9,0)*玩法行为规划!AC3) | AE3: =IF(VLOOKUP(AE$2,行为概览!$D$3:$L$33,9,0)="","",VLOOKUP(AE$2,行为概览!$D$3:$L$33,9,0)*玩法行为规划!AD3) | AF3: =SUM(C3:AC3) -> 5 | AG3: =B3*AF3 -> 5000 | AH3: =ROUND(AG3*升级节奏!G3,0) -> 0 | AI3: =ROUND(B3*(1+MAX(A3-40,0)*0.1),-2) -> 1000 | AJ3: =SUM(AI3:AI11) -> 45000 | AK3: =AI3/AL3 -> 1 | AL3: =AH3+AI3 -> 1000 | AM3: =SUM($AL$3:AL3) -> 1000 | AN3: =ROUND((B3*6+AH3)/30,-2) -> 200 | AO3: =SUM($AN$3:AN3)*7 -> 1400 | AP3: =AM3-AO3-AQ3-AR3 -> -700 | AQ3: =ROUND((B3*2+AH3)/10,-2) -> 200 | AR3: =ROUND((B3*2+AH3)/20,-2) -> 100
A4: 2 | B4: =升级节奏!E4 -> 2000 | C4: =IF(VLOOKUP(C$2,行为概览!$D$3:$L$33,9,0)="","",VLOOKUP(C$2,行为概览!$D$3:$L$33,9,0)*IF(玩法行为规划!B4>0,1,0)) -> 0 | D4: =IF(VLOOKUP(D$2,行为概览!$D$3:$L$33,9,0)="","",VLOOKUP(D$2,行为概览!$D$3:$L$33,9,0)*IF(玩法行为规划!C4>0,1,0)) -> 0 | E4: =IF(VLOOKUP(E$2,行为概览!$D$3:$L$33,9,0)="","",VLOOKUP(E$2,行为概览!$D$3:$L$33,9,0)*IF(玩法行为规划!D4>0,1,0)) -> 0 | F4: =IF(VLOOKUP(F$2,行为概览!$D$3:$L$33,9,0)="","",VLOOKUP(F$2,行为概览!$D$3:$L$33,9,0)*IF(玩法行为规划!E4>0,1,0)) -> 0 | G4: =IF(VLOOKUP(G$2,行为概览!$D$3:$L$33,9,0)="","",VLOOKUP(G$2,行为概览!$D$3:$L$33,9,0)*IF(玩法行为规划!F4>0,1,0)) | H4: =IF(VLOOKUP(H$2,行为概览!$D$3:$L$33,9,0)="","",VLOOKUP(H$2,行为概览!$D$3:$L$33,9,0)*IF(玩法行为规划!G4>0,1,0)) | I4: =IF(VLOOKUP(I$2,行为概览!$D$3:$L$33,9,0)="","",VLOOKUP(I$2,行为概览!$D$3:$L$33,9,0)*IF(玩法行为规划!H4>0,1,0)) | J4: =IF(VLOOKUP(J$2,行为概览!$D$3:$L$33,9,0)="","",VLOOKUP(J$2,行为概览!$D$3:$L$33,9,0)*IF(玩法行为规划!I4>0,1,0)) | ... AC4: =IF(VLOOKUP(AC$2,行为概览!$D$3:$L$33,9,0)="","",VLOOKUP(AC$2,行为概览!$D$3:$L$33,9,0)*IF(玩法行为规划!AB4>0,1,0)) | AD4: =IF(VLOOKUP(AD$2,行为概览!$D$3:$L$33,9,0)="","",VLOOKUP(AD$2,行为概览!$D$3:$L$33,9,0)*玩法行为规划!AC4) | AE4: =IF(VLOOKUP(AE$2,行为概览!$D$3:$L$33,9,0)="","",VLOOKUP(AE$2,行为概览!$D$3:$L$33,9,0)*玩法行为规划!AD4) | AF4: =SUM(C4:AC4) -> 5 | AG4: =B4*AF4 -> 10000 | AH4: =ROUND(AG4*升级节奏!G4,0) -> 0 | AI4: =ROUND(B4*(1+MAX(A4-40,0)*0.1),-2) -> 2000 | AK4: =AI4/AL4 -> 1 | AL4: =AH4+AI4 -> 2000 | AM4: =SUM($AL$3:AL4) -> 3000 | AN4: =ROUND((B4*6+AH4)/30,-2) -> 400 | AO4: =SUM($AN$3:AN4)*7 -> 4200 | AP4: =AM4-AO4-AQ4-AR4 -> -1800 | AQ4: =ROUND((B4*2+AH4)/10,-2) -> 400 | AR4: =ROUND((B4*2+AH4)/20,-2) -> 200
A5: 3 | B5: =升级节奏!E5 -> 3000 | C5: =IF(VLOOKUP(C$2,行为概览!$D$3:$L$33,9,0)="","",VLOOKUP(C$2,行为概览!$D$3:$L$33,9,0)*IF(玩法行为规划!B5>0,1,0)) -> 0 | D5: =IF(VLOOKUP(D$2,行为概览!$D$3:$L$33,9,0)="","",VLOOKUP(D$2,行为概览!$D$3:$L$33,9,0)*IF(玩法行为规划!C5>0,1,0)) -> 0 | E5: =IF(VLOOKUP(E$2,行为概览!$D$3:$L$33,9,0)="","",VLOOKUP(E$2,行为概览!$D$3:$L$33,9,0)*IF(玩法行为规划!D5>0,1,0)) -> 0 | F5: =IF(VLOOKUP(F$2,行为概览!$D$3:$L$33,9,0)="","",VLOOKUP(F$2,行为概览!$D$3:$L$33,9,0)*IF(玩法行为规划!E5>0,1,0)) -> 0 | G5: =IF(VLOOKUP(G$2,行为概览!$D$3:$L$33,9,0)="","",VLOOKUP(G$2,行为概览!$D$3:$L$33,9,0)*IF(玩法行为规划!F5>0,1,0)) | H5: =IF(VLOOKUP(H$2,行为概览!$D$3:$L$33,9,0)="","",VLOOKUP(H$2,行为概览!$D$3:$L$33,9,0)*IF(玩法行为规划!G5>0,1,0)) | I5: =IF(VLOOKUP(I$2,行为概览!$D$3:$L$33,9,0)="","",VLOOKUP(I$2,行为概览!$D$3:$L$33,9,0)*IF(玩法行为规划!H5>0,1,0)) | J5: =IF(VLOOKUP(J$2,行为概览!$D$3:$L$33,9,0)="","",VLOOKUP(J$2,行为概览!$D$3:$L$33,9,0)*IF(玩法行为规划!I5>0,1,0)) | ... AC5: =IF(VLOOKUP(AC$2,行为概览!$D$3:$L$33,9,0)="","",VLOOKUP(AC$2,行为概览!$D$3:$L$33,9,0)*IF(玩法行为规划!AB5>0,1,0)) | AD5: =IF(VLOOKUP(AD$2,行为概览!$D$3:$L$33,9,0)="","",VLOOKUP(AD$2,行为概览!$D$3:$L$33,9,0)*玩法行为规划!AC5) | AE5: =IF(VLOOKUP(AE$2,行为概览!$D$3:$L$33,9,0)="","",VLOOKUP(AE$2,行为概览!$D$3:$L$33,9,0)*玩法行为规划!AD5) | AF5: =SUM(C5:AC5) -> 5 | AG5: =B5*AF5 -> 15000 | AH5: =ROUND(AG5*升级节奏!G5,0) -> 0 | AI5: =ROUND(B5*(1+MAX(A5-40,0)*0.1),-2) -> 3000 | AK5: =AI5/AL5 -> 1 | AL5: =AH5+AI5 -> 3000 | AM5: =SUM($AL$3:AL5) -> 6000 | AN5: =ROUND((B5*6+AH5)/30,-2) -> 600 | AO5: =SUM($AN$3:AN5)*7 -> 8400 | AP5: =AM5-AO5-AQ5-AR5 -> -3300 | AQ5: =ROUND((B5*2+AH5)/10,-2) -> 600 | AR5: =ROUND((B5*2+AH5)/20,-2) -> 300
A6: 4 | B6: =升级节奏!E6 -> 4000 | C6: =IF(VLOOKUP(C$2,行为概览!$D$3:$L$33,9,0)="","",VLOOKUP(C$2,行为概览!$D$3:$L$33,9,0)*IF(玩法行为规划!B6>0,1,0)) -> 0 | D6: =IF(VLOOKUP(D$2,行为概览!$D$3:$L$33,9,0)="","",VLOOKUP(D$2,行为概览!$D$3:$L$33,9,0)*IF(玩法行为规划!C6>0,1,0)) -> 0 | E6: =IF(VLOOKUP(E$2,行为概览!$D$3:$L$33,9,0)="","",VLOOKUP(E$2,行为概览!$D$3:$L$33,9,0)*IF(玩法行为规划!D6>0,1,0)) -> 0 | F6: =IF(VLOOKUP(F$2,行为概览!$D$3:$L$33,9,0)="","",VLOOKUP(F$2,行为概览!$D$3:$L$33,9,0)*IF(玩法行为规划!E6>0,1,0)) -> 0 | G6: =IF(VLOOKUP(G$2,行为概览!$D$3:$L$33,9,0)="","",VLOOKUP(G$2,行为概览!$D$3:$L$33,9,0)*IF(玩法行为规划!F6>0,1,0)) | H6: =IF(VLOOKUP(H$2,行为概览!$D$3:$L$33,9,0)="","",VLOOKUP(H$2,行为概览!$D$3:$L$33,9,0)*IF(玩法行为规划!G6>0,1,0)) | I6: =IF(VLOOKUP(I$2,行为概览!$D$3:$L$33,9,0)="","",VLOOKUP(I$2,行为概览!$D$3:$L$33,9,0)*IF(玩法行为规划!H6>0,1,0)) | J6: =IF(VLOOKUP(J$2,行为概览!$D$3:$L$33,9,0)="","",VLOOKUP(J$2,行为概览!$D$3:$L$33,9,0)*IF(玩法行为规划!I6>0,1,0)) | ... AC6: =IF(VLOOKUP(AC$2,行为概览!$D$3:$L$33,9,0)="","",VLOOKUP(AC$2,行为概览!$D$3:$L$33,9,0)*IF(玩法行为规划!AB6>0,1,0)) | AD6: =IF(VLOOKUP(AD$2,行为概览!$D$3:$L$33,9,0)="","",VLOOKUP(AD$2,行为概览!$D$3:$L$33,9,0)*玩法行为规划!AC6) | AE6: =IF(VLOOKUP(AE$2,行为概览!$D$3:$L$33,9,0)="","",VLOOKUP(AE$2,行为概览!$D$3:$L$33,9,0)*玩法行为规划!AD6) | AF6: =SUM(C6:AC6) -> 5 | AG6: =B6*AF6 -> 20000 | AH6: =ROUND(AG6*升级节奏!G6,0) -> 0 | AI6: =ROUND(B6*(1+MAX(A6-40,0)*0.1),-2) -> 4000 | AK6: =AI6/AL6 -> 1 | AL6: =AH6+AI6 -> 4000 | AM6: =SUM($AL$3:AL6) -> 10000 | AN6: =ROUND((B6*6+AH6)/30,-2) -> 800 | AO6: =SUM($AN$3:AN6)*7 -> 14000 | AP6: =AM6-AO6-AQ6-AR6 -> -5200 | AQ6: =ROUND((B6*2+AH6)/10,-2) -> 800 | AR6: =ROUND((B6*2+AH6)/20,-2) -> 400
A7: 5 | B7: =升级节奏!E7 -> 5000 | C7: =IF(VLOOKUP(C$2,行为概览!$D$3:$L$33,9,0)="","",VLOOKUP(C$2,行为概览!$D$3:$L$33,9,0)*IF(玩法行为规划!B7>0,1,0)) -> 0 | D7: =IF(VLOOKUP(D$2,行为概览!$D$3:$L$33,9,0)="","",VLOOKUP(D$2,行为概览!$D$3:$L$33,9,0)*IF(玩法行为规划!C7>0,1,0)) -> 0 | E7: =IF(VLOOKUP(E$2,行为概览!$D$3:$L$33,9,0)="","",VLOOKUP(E$2,行为概览!$D$3:$L$33,9,0)*IF(玩法行为规划!D7>0,1,0)) -> 0 | F7: =IF(VLOOKUP(F$2,行为概览!$D$3:$L$33,9,0)="","",VLOOKUP(F$2,行为概览!$D$3:$L$33,9,0)*IF(玩法行为规划!E7>0,1,0)) -> 0 | G7: =IF(VLOOKUP(G$2,行为概览!$D$3:$L$33,9,0)="","",VLOOKUP(G$2,行为概览!$D$3:$L$33,9,0)*IF(玩法行为规划!F7>0,1,0)) | H7: =IF(VLOOKUP(H$2,行为概览!$D$3:$L$33,9,0)="","",VLOOKUP(H$2,行为概览!$D$3:$L$33,9,0)*IF(玩法行为规划!G7>0,1,0)) | I7: =IF(VLOOKUP(I$2,行为概览!$D$3:$L$33,9,0)="","",VLOOKUP(I$2,行为概览!$D$3:$L$33,9,0)*IF(玩法行为规划!H7>0,1,0)) | J7: =IF(VLOOKUP(J$2,行为概览!$D$3:$L$33,9,0)="","",VLOOKUP(J$2,行为概览!$D$3:$L$33,9,0)*IF(玩法行为规划!I7>0,1,0)) | ... AC7: =IF(VLOOKUP(AC$2,行为概览!$D$3:$L$33,9,0)="","",VLOOKUP(AC$2,行为概览!$D$3:$L$33,9,0)*IF(玩法行为规划!AB7>0,1,0)) | AD7: =IF(VLOOKUP(AD$2,行为概览!$D$3:$L$33,9,0)="","",VLOOKUP(AD$2,行为概览!$D$3:$L$33,9,0)*玩法行为规划!AC7) | AE7: =IF(VLOOKUP(AE$2,行为概览!$D$3:$L$33,9,0)="","",VLOOKUP(AE$2,行为概览!$D$3:$L$33,9,0)*玩法行为规划!AD7) | AF7: =SUM(C7:AC7) -> 5 | AG7: =B7*AF7 -> 25000 | AH7: =ROUND(AG7*升级节奏!G7,0) -> 0 | AI7: =ROUND(B7*(1+MAX(A7-40,0)*0.1),-2) -> 5000 | AK7: =AI7/AL7 -> 1 | AL7: =AH7+AI7 -> 5000 | AM7: =SUM($AL$3:AL7) -> 15000 | AN7: =ROUND((B7*6+AH7)/30,-2) -> 1000 | AO7: =SUM($AN$3:AN7)*7 -> 21000 | AP7: =AM7-AO7-AQ7-AR7 -> -7500 | AQ7: =ROUND((B7*2+AH7)/10,-2) -> 1000 | AR7: =ROUND((B7*2+AH7)/20,-2) -> 500
A8: 6 | B8: =升级节奏!E8 -> 6000 | C8: =IF(VLOOKUP(C$2,行为概览!$D$3:$L$33,9,0)="","",VLOOKUP(C$2,行为概览!$D$3:$L$33,9,0)*IF(玩法行为规划!B8>0,1,0)) -> 0 | D8: =IF(VLOOKUP(D$2,行为概览!$D$3:$L$33,9,0)="","",VLOOKUP(D$2,行为概览!$D$3:$L$33,9,0)*IF(玩法行为规划!C8>0,1,0)) -> 0 | E8: =IF(VLOOKUP(E$2,行为概览!$D$3:$L$33,9,0)="","",VLOOKUP(E$2,行为概览!$D$3:$L$33,9,0)*IF(玩法行为规划!D8>0,1,0)) -> 0 | F8: =IF(VLOOKUP(F$2,行为概览!$D$3:$L$33,9,0)="","",VLOOKUP(F$2,行为概览!$D$3:$L$33,9,0)*IF(玩法行为规划!E8>0,1,0)) -> 0 | G8: =IF(VLOOKUP(G$2,行为概览!$D$3:$L$33,9,0)="","",VLOOKUP(G$2,行为概览!$D$3:$L$33,9,0)*IF(玩法行为规划!F8>0,1,0)) | H8: =IF(VLOOKUP(H$2,行为概览!$D$3:$L$33,9,0)="","",VLOOKUP(H$2,行为概览!$D$3:$L$33,9,0)*IF(玩法行为规划!G8>0,1,0)) | I8: =IF(VLOOKUP(I$2,行为概览!$D$3:$L$33,9,0)="","",VLOOKUP(I$2,行为概览!$D$3:$L$33,9,0)*IF(玩法行为规划!H8>0,1,0)) | J8: =IF(VLOOKUP(J$2,行为概览!$D$3:$L$33,9,0)="","",VLOOKUP(J$2,行为概览!$D$3:$L$33,9,0)*IF(玩法行为规划!I8>0,1,0)) | ... AC8: =IF(VLOOKUP(AC$2,行为概览!$D$3:$L$33,9,0)="","",VLOOKUP(AC$2,行为概览!$D$3:$L$33,9,0)*IF(玩法行为规划!AB8>0,1,0)) | AD8: =IF(VLOOKUP(AD$2,行为概览!$D$3:$L$33,9,0)="","",VLOOKUP(AD$2,行为概览!$D$3:$L$33,9,0)*玩法行为规划!AC8) | AE8: =IF(VLOOKUP(AE$2,行为概览!$D$3:$L$33,9,0)="","",VLOOKUP(AE$2,行为概览!$D$3:$L$33,9,0)*玩法行为规划!AD8) | AF8: =SUM(C8:AC8) -> 5 | AG8: =B8*AF8 -> 30000 | AH8: =ROUND(AG8*升级节奏!G8,0) -> 0 | AI8: =ROUND(B8*(1+MAX(A8-40,0)*0.1),-2) -> 6000 | AK8: =AI8/AL8 -> 1 | AL8: =AH8+AI8 -> 6000 | AM8: =SUM($AL$3:AL8) -> 21000 | AN8: =ROUND((B8*6+AH8)/30,-2) -> 1200 | AO8: =SUM($AN$3:AN8)*7 -> 29400 | AP8: =AM8-AO8-AQ8-AR8 -> -10200 | AQ8: =ROUND((B8*2+AH8)/10,-2) -> 1200 | AR8: =ROUND((B8*2+AH8)/20,-2) -> 600
A9: 7 | B9: =升级节奏!E9 -> 7000 | C9: =IF(VLOOKUP(C$2,行为概览!$D$3:$L$33,9,0)="","",VLOOKUP(C$2,行为概览!$D$3:$L$33,9,0)*IF(玩法行为规划!B9>0,1,0)) -> 0 | D9: =IF(VLOOKUP(D$2,行为概览!$D$3:$L$33,9,0)="","",VLOOKUP(D$2,行为概览!$D$3:$L$33,9,0)*IF(玩法行为规划!C9>0,1,0)) -> 0 | E9: =IF(VLOOKUP(E$2,行为概览!$D$3:$L$33,9,0)="","",VLOOKUP(E$2,行为概览!$D$3:$L$33,9,0)*IF(玩法行为规划!D9>0,1,0)) -> 0 | F9: =IF(VLOOKUP(F$2,行为概览!$D$3:$L$33,9,0)="","",VLOOKUP(F$2,行为概览!$D$3:$L$33,9,0)*IF(玩法行为规划!E9>0,1,0)) -> 0 | G9: =IF(VLOOKUP(G$2,行为概览!$D$3:$L$33,9,0)="","",VLOOKUP(G$2,行为概览!$D$3:$L$33,9,0)*IF(玩法行为规划!F9>0,1,0)) | H9: =IF(VLOOKUP(H$2,行为概览!$D$3:$L$33,9,0)="","",VLOOKUP(H$2,行为概览!$D$3:$L$33,9,0)*IF(玩法行为规划!G9>0,1,0)) | I9: =IF(VLOOKUP(I$2,行为概览!$D$3:$L$33,9,0)="","",VLOOKUP(I$2,行为概览!$D$3:$L$33,9,0)*IF(玩法行为规划!H9>0,1,0)) | J9: =IF(VLOOKUP(J$2,行为概览!$D$3:$L$33,9,0)="","",VLOOKUP(J$2,行为概览!$D$3:$L$33,9,0)*IF(玩法行为规划!I9>0,1,0)) | ... AC9: =IF(VLOOKUP(AC$2,行为概览!$D$3:$L$33,9,0)="","",VLOOKUP(AC$2,行为概览!$D$3:$L$33,9,0)*IF(玩法行为规划!AB9>0,1,0)) | AD9: =IF(VLOOKUP(AD$2,行为概览!$D$3:$L$33,9,0)="","",VLOOKUP(AD$2,行为概览!$D$3:$L$33,9,0)*玩法行为规划!AC9) | AE9: =IF(VLOOKUP(AE$2,行为概览!$D$3:$L$33,9,0)="","",VLOOKUP(AE$2,行为概览!$D$3:$L$33,9,0)*玩法行为规划!AD9) | AF9: =SUM(C9:AC9) -> 5 | AG9: =B9*AF9 -> 35000 | AH9: =ROUND(AG9*升级节奏!G9,0) -> 0 | AI9: =ROUND(B9*(1+MAX(A9-40,0)*0.1),-2) -> 7000 | AK9: =AI9/AL9 -> 1 | AL9: =AH9+AI9 -> 7000 | AM9: =SUM($AL$3:AL9) -> 28000 | AN9: =ROUND((B9*6+AH9)/30,-2) -> 1400 | AO9: =SUM($AN$3:AN9)*7 -> 39200 | AP9: =AM9-AO9-AQ9-AR9 -> -13300 | AQ9: =ROUND((B9*2+AH9)/10,-2) -> 1400 | AR9: =ROUND((B9*2+AH9)/20,-2) -> 700
A10: 8 | B10: =升级节奏!E10 -> 8000 | C10: =IF(VLOOKUP(C$2,行为概览!$D$3:$L$33,9,0)="","",VLOOKUP(C$2,行为概览!$D$3:$L$33,9,0)*IF(玩法行为规划!B10>0,1,0)) -> 0 | D10: =IF(VLOOKUP(D$2,行为概览!$D$3:$L$33,9,0)="","",VLOOKUP(D$2,行为概览!$D$3:$L$33,9,0)*IF(玩法行为规划!C10>0,1,0)) -> 0 | E10: =IF(VLOOKUP(E$2,行为概览!$D$3:$L$33,9,0)="","",VLOOKUP(E$2,行为概览!$D$3:$L$33,9,0)*IF(玩法行为规划!D10>0,1,0)) -> 0 | F10: =IF(VLOOKUP(F$2,行为概览!$D$3:$L$33,9,0)="","",VLOOKUP(F$2,行为概览!$D$3:$L$33,9,0)*IF(玩法行为规划!E10>0,1,0)) -> 0 | G10: =IF(VLOOKUP(G$2,行为概览!$D$3:$L$33,9,0)="","",VLOOKUP(G$2,行为概览!$D$3:$L$33,9,0)*IF(玩法行为规划!F10>0,1,0)) | H10: =IF(VLOOKUP(H$2,行为概览!$D$3:$L$33,9,0)="","",VLOOKUP(H$2,行为概览!$D$3:$L$33,9,0)*IF(玩法行为规划!G10>0,1,0)) | I10: =IF(VLOOKUP(I$2,行为概览!$D$3:$L$33,9,0)="","",VLOOKUP(I$2,行为概览!$D$3:$L$33,9,0)*IF(玩法行为规划!H10>0,1,0)) | J10: =IF(VLOOKUP(J$2,行为概览!$D$3:$L$33,9,0)="","",VLOOKUP(J$2,行为概览!$D$3:$L$33,9,0)*IF(玩法行为规划!I10>0,1,0)) | ... AC10: =IF(VLOOKUP(AC$2,行为概览!$D$3:$L$33,9,0)="","",VLOOKUP(AC$2,行为概览!$D$3:$L$33,9,0)*IF(玩法行为规划!AB10>0,1,0)) | AD10: =IF(VLOOKUP(AD$2,行为概览!$D$3:$L$33,9,0)="","",VLOOKUP(AD$2,行为概览!$D$3:$L$33,9,0)*玩法行为规划!AC10) | AE10: =IF(VLOOKUP(AE$2,行为概览!$D$3:$L$33,9,0)="","",VLOOKUP(AE$2,行为概览!$D$3:$L$33,9,0)*玩法行为规划!AD10) | AF10: =SUM(C10:AC10) -> 5 | AG10: =B10*AF10 -> 40000 | AH10: =ROUND(AG10*升级节奏!G10,0) -> 0 | AI10: =ROUND(B10*(1+MAX(A10-40,0)*0.1),-2) -> 8000 | AK10: =AI10/AL10 -> 1 | AL10: =AH10+AI10 -> 8000 | AM10: =SUM($AL$3:AL10) -> 36000 | AN10: =ROUND((B10*6+AH10)/30,-2) -> 1600 | AO10: =SUM($AN$3:AN10)*7 -> 50400 | AP10: =AM10-AO10-AQ10-AR10 -> -16800 | AQ10: =ROUND((B10*2+AH10)/10,-2) -> 1600 | AR10: =ROUND((B10*2+AH10)/20,-2) -> 800
A11: 9 | B11: =升级节奏!E11 -> 9000 | C11: =IF(VLOOKUP(C$2,行为概览!$D$3:$L$33,9,0)="","",VLOOKUP(C$2,行为概览!$D$3:$L$33,9,0)*IF(玩法行为规划!B11>0,1,0)) -> 0 | D11: =IF(VLOOKUP(D$2,行为概览!$D$3:$L$33,9,0)="","",VLOOKUP(D$2,行为概览!$D$3:$L$33,9,0)*IF(玩法行为规划!C11>0,1,0)) -> 0 | E11: =IF(VLOOKUP(E$2,行为概览!$D$3:$L$33,9,0)="","",VLOOKUP(E$2,行为概览!$D$3:$L$33,9,0)*IF(玩法行为规划!D11>0,1,0)) -> 0 | F11: =IF(VLOOKUP(F$2,行为概览!$D$3:$L$33,9,0)="","",VLOOKUP(F$2,行为概览!$D$3:$L$33,9,0)*IF(玩法行为规划!E11>0,1,0)) -> 0 | G11: =IF(VLOOKUP(G$2,行为概览!$D$3:$L$33,9,0)="","",VLOOKUP(G$2,行为概览!$D$3:$L$33,9,0)*IF(玩法行为规划!F11>0,1,0)) | H11: =IF(VLOOKUP(H$2,行为概览!$D$3:$L$33,9,0)="","",VLOOKUP(H$2,行为概览!$D$3:$L$33,9,0)*IF(玩法行为规划!G11>0,1,0)) | I11: =IF(VLOOKUP(I$2,行为概览!$D$3:$L$33,9,0)="","",VLOOKUP(I$2,行为概览!$D$3:$L$33,9,0)*IF(玩法行为规划!H11>0,1,0)) | J11: =IF(VLOOKUP(J$2,行为概览!$D$3:$L$33,9,0)="","",VLOOKUP(J$2,行为概览!$D$3:$L$33,9,0)*IF(玩法行为规划!I11>0,1,0)) | ... AC11: =IF(VLOOKUP(AC$2,行为概览!$D$3:$L$33,9,0)="","",VLOOKUP(AC$2,行为概览!$D$3:$L$33,9,0)*IF(玩法行为规划!AB11>0,1,0)) | AD11: =IF(VLOOKUP(AD$2,行为概览!$D$3:$L$33,9,0)="","",VLOOKUP(AD$2,行为概览!$D$3:$L$33,9,0)*玩法行为规划!AC11) | AE11: =IF(VLOOKUP(AE$2,行为概览!$D$3:$L$33,9,0)="","",VLOOKUP(AE$2,行为概览!$D$3:$L$33,9,0)*玩法行为规划!AD11) | AF11: =SUM(C11:AC11) -> 5 | AG11: =B11*AF11 -> 45000 | AH11: =ROUND(AG11*升级节奏!G11,0) -> 0 | AI11: =ROUND(B11*(1+MAX(A11-40,0)*0.1),-2) -> 9000 | AK11: =AI11/AL11 -> 1 | AL11: =AH11+AI11 -> 9000 | AM11: =SUM($AL$3:AL11) -> 45000 | AN11: =ROUND((B11*6+AH11)/30,-2) -> 1800 | AO11: =SUM($AN$3:AN11)*7 -> 63000 | AP11: =AM11-AO11-AQ11-AR11 -> -20700 | AQ11: =ROUND((B11*2+AH11)/10,-2) -> 1800 | AR11: =ROUND((B11*2+AH11)/20,-2) -> 900
A12: 10 | B12: =升级节奏!E12 -> 10000 | C12: =IF(VLOOKUP(C$2,行为概览!$D$3:$L$33,9,0)="","",VLOOKUP(C$2,行为概览!$D$3:$L$33,9,0)*IF(玩法行为规划!B12>0,1,0)) -> 0 | D12: =IF(VLOOKUP(D$2,行为概览!$D$3:$L$33,9,0)="","",VLOOKUP(D$2,行为概览!$D$3:$L$33,9,0)*IF(玩法行为规划!C12>0,1,0)) -> 0 | E12: =IF(VLOOKUP(E$2,行为概览!$D$3:$L$33,9,0)="","",VLOOKUP(E$2,行为概览!$D$3:$L$33,9,0)*IF(玩法行为规划!D12>0,1,0)) -> 0 | F12: =IF(VLOOKUP(F$2,行为概览!$D$3:$L$33,9,0)="","",VLOOKUP(F$2,行为概览!$D$3:$L$33,9,0)*IF(玩法行为规划!E12>0,1,0)) -> 0 | G12: =IF(VLOOKUP(G$2,行为概览!$D$3:$L$33,9,0)="","",VLOOKUP(G$2,行为概览!$D$3:$L$33,9,0)*IF(玩法行为规划!F12>0,1,0)) | H12: =IF(VLOOKUP(H$2,行为概览!$D$3:$L$33,9,0)="","",VLOOKUP(H$2,行为概览!$D$3:$L$33,9,0)*IF(玩法行为规划!G12>0,1,0)) | I12: =IF(VLOOKUP(I$2,行为概览!$D$3:$L$33,9,0)="","",VLOOKUP(I$2,行为概览!$D$3:$L$33,9,0)*IF(玩法行为规划!H12>0,1,0)) | J12: =IF(VLOOKUP(J$2,行为概览!$D$3:$L$33,9,0)="","",VLOOKUP(J$2,行为概览!$D$3:$L$33,9,0)*IF(玩法行为规划!I12>0,1,0)) | ... AC12: =IF(VLOOKUP(AC$2,行为概览!$D$3:$L$33,9,0)="","",VLOOKUP(AC$2,行为概览!$D$3:$L$33,9,0)*IF(玩法行为规划!AB12>0,1,0)) | AD12: =IF(VLOOKUP(AD$2,行为概览!$D$3:$L$33,9,0)="","",VLOOKUP(AD$2,行为概览!$D$3:$L$33,9,0)*玩法行为规划!AC12) | AE12: =IF(VLOOKUP(AE$2,行为概览!$D$3:$L$33,9,0)="","",VLOOKUP(AE$2,行为概览!$D$3:$L$33,9,0)*玩法行为规划!AD12) | AF12: =SUM(C12:AC12) -> 5.5 | AG12: =B12*AF12 -> 55000 | AH12: =ROUND(AG12*升级节奏!G12,0) -> 0 | AI12: =ROUND(B12*(1+MAX(A12-40,0)*0.1),-2) -> 10000 | AJ12: =IF(--RIGHT(A12,1)=0,SUM(AI12:AI21),"") -> 145000 | AK12: =AI12/AL12 -> 1 | AL12: =AH12+AI12 -> 10000 | AM12: =SUM($AL$3:AL12) -> 55000 | AN12: =ROUND((B12*6+AH12)/30,-2) -> 2000 | AO12: =SUM($AN$3:AN12)*7 -> 77000 | AP12: =AM12-AO12-AQ12-AR12 -> -25000 | AQ12: =ROUND((B12*2+AH12)/10,-2) -> 2000 | AR12: =ROUND((B12*2+AH12)/20,-2) -> 1000
A13: 11 | B13: =升级节奏!E13 -> 11000 | C13: =IF(VLOOKUP(C$2,行为概览!$D$3:$L$33,9,0)="","",VLOOKUP(C$2,行为概览!$D$3:$L$33,9,0)*IF(玩法行为规划!B13>0,1,0)) -> 0 | D13: =IF(VLOOKUP(D$2,行为概览!$D$3:$L$33,9,0)="","",VLOOKUP(D$2,行为概览!$D$3:$L$33,9,0)*IF(玩法行为规划!C13>0,1,0)) -> 0 | E13: =IF(VLOOKUP(E$2,行为概览!$D$3:$L$33,9,0)="","",VLOOKUP(E$2,行为概览!$D$3:$L$33,9,0)*IF(玩法行为规划!D13>0,1,0)) -> 0 | F13: =IF(VLOOKUP(F$2,行为概览!$D$3:$L$33,9,0)="","",VLOOKUP(F$2,行为概览!$D$3:$L$33,9,0)*IF(玩法行为规划!E13>0,1,0)) -> 0 | G13: =IF(VLOOKUP(G$2,行为概览!$D$3:$L$33,9,0)="","",VLOOKUP(G$2,行为概览!$D$3:$L$33,9,0)*IF(玩法行为规划!F13>0,1,0)) | H13: =IF(VLOOKUP(H$2,行为概览!$D$3:$L$33,9,0)="","",VLOOKUP(H$2,行为概览!$D$3:$L$33,9,0)*IF(玩法行为规划!G13>0,1,0)) | I13: =IF(VLOOKUP(I$2,行为概览!$D$3:$L$33,9,0)="","",VLOOKUP(I$2,行为概览!$D$3:$L$33,9,0)*IF(玩法行为规划!H13>0,1,0)) | J13: =IF(VLOOKUP(J$2,行为概览!$D$3:$L$33,9,0)="","",VLOOKUP(J$2,行为概览!$D$3:$L$33,9,0)*IF(玩法行为规划!I13>0,1,0)) | ... AC13: =IF(VLOOKUP(AC$2,行为概览!$D$3:$L$33,9,0)="","",VLOOKUP(AC$2,行为概览!$D$3:$L$33,9,0)*IF(玩法行为规划!AB13>0,1,0)) | AD13: =IF(VLOOKUP(AD$2,行为概览!$D$3:$L$33,9,0)="","",VLOOKUP(AD$2,行为概览!$D$3:$L$33,9,0)*玩法行为规划!AC13) | AE13: =IF(VLOOKUP(AE$2,行为概览!$D$3:$L$33,9,0)="","",VLOOKUP(AE$2,行为概览!$D$3:$L$33,9,0)*玩法行为规划!AD13) | AF13: =SUM(C13:AC13) -> 5.5 | AG13: =B13*AF13 -> 60500 | AH13: =ROUND(AG13*升级节奏!G13,0) -> 0 | AI13: =ROUND(B13*(1+MAX(A13-40,0)*0.1),-2) -> 11000 | AJ13: =IF(--RIGHT(A13,1)=0,SUM(AI13:AI22),"") | AK13: =AI13/AL13 -> 1 | AL13: =AH13+AI13 -> 11000 | AM13: =SUM($AL$3:AL13) -> 66000 | AN13: =ROUND((B13*6+AH13)/30,-2) -> 2200 | AO13: =SUM($AN$3:AN13)*7 -> 92400 | AP13: =AM13-AO13-AQ13-AR13 -> -29700 | AQ13: =ROUND((B13*2+AH13)/10,-2) -> 2200 | AR13: =ROUND((B13*2+AH13)/20,-2) -> 1100
A14: 12 | B14: =升级节奏!E14 -> 12000 | C14: =IF(VLOOKUP(C$2,行为概览!$D$3:$L$33,9,0)="","",VLOOKUP(C$2,行为概览!$D$3:$L$33,9,0)*IF(玩法行为规划!B14>0,1,0)) -> 0 | D14: =IF(VLOOKUP(D$2,行为概览!$D$3:$L$33,9,0)="","",VLOOKUP(D$2,行为概览!$D$3:$L$33,9,0)*IF(玩法行为规划!C14>0,1,0)) -> 0 | E14: =IF(VLOOKUP(E$2,行为概览!$D$3:$L$33,9,0)="","",VLOOKUP(E$2,行为概览!$D$3:$L$33,9,0)*IF(玩法行为规划!D14>0,1,0)) -> 0 | F14: =IF(VLOOKUP(F$2,行为概览!$D$3:$L$33,9,0)="","",VLOOKUP(F$2,行为概览!$D$3:$L$33,9,0)*IF(玩法行为规划!E14>0,1,0)) -> 0 | G14: =IF(VLOOKUP(G$2,行为概览!$D$3:$L$33,9,0)="","",VLOOKUP(G$2,行为概览!$D$3:$L$33,9,0)*IF(玩法行为规划!F14>0,1,0)) | H14: =IF(VLOOKUP(H$2,行为概览!$D$3:$L$33,9,0)="","",VLOOKUP(H$2,行为概览!$D$3:$L$33,9,0)*IF(玩法行为规划!G14>0,1,0)) | I14: =IF(VLOOKUP(I$2,行为概览!$D$3:$L$33,9,0)="","",VLOOKUP(I$2,行为概览!$D$3:$L$33,9,0)*IF(玩法行为规划!H14>0,1,0)) | J14: =IF(VLOOKUP(J$2,行为概览!$D$3:$L$33,9,0)="","",VLOOKUP(J$2,行为概览!$D$3:$L$33,9,0)*IF(玩法行为规划!I14>0,1,0)) | ... AC14: =IF(VLOOKUP(AC$2,行为概览!$D$3:$L$33,9,0)="","",VLOOKUP(AC$2,行为概览!$D$3:$L$33,9,0)*IF(玩法行为规划!AB14>0,1,0)) | AD14: =IF(VLOOKUP(AD$2,行为概览!$D$3:$L$33,9,0)="","",VLOOKUP(AD$2,行为概览!$D$3:$L$33,9,0)*玩法行为规划!AC14) | AE14: =IF(VLOOKUP(AE$2,行为概览!$D$3:$L$33,9,0)="","",VLOOKUP(AE$2,行为概览!$D$3:$L$33,9,0)*玩法行为规划!AD14) | AF14: =SUM(C14:AC14) -> 5.5 | AG14: =B14*AF14 -> 66000 | AH14: =ROUND(AG14*升级节奏!G14,0) -> 0 | AI14: =ROUND(B14*(1+MAX(A14-40,0)*0.1),-2) -> 12000 | AJ14: =IF(--RIGHT(A14,1)=0,SUM(AI14:AI23),"") | AK14: =AI14/AL14 -> 1 | AL14: =AH14+AI14 -> 12000 | AM14: =SUM($AL$3:AL14) -> 78000 | AN14: =ROUND((B14*6+AH14)/30,-2) -> 2400 | AO14: =SUM($AN$3:AN14)*7 -> 109200 | AP14: =AM14-AO14-AQ14-AR14 -> -34800 | AQ14: =ROUND((B14*2+AH14)/10,-2) -> 2400 | AR14: =ROUND((B14*2+AH14)/20,-2) -> 1200
A15: 13 | B15: =升级节奏!E15 -> 13000 | C15: =IF(VLOOKUP(C$2,行为概览!$D$3:$L$33,9,0)="","",VLOOKUP(C$2,行为概览!$D$3:$L$33,9,0)*IF(玩法行为规划!B15>0,1,0)) -> 0 | D15: =IF(VLOOKUP(D$2,行为概览!$D$3:$L$33,9,0)="","",VLOOKUP(D$2,行为概览!$D$3:$L$33,9,0)*IF(玩法行为规划!C15>0,1,0)) -> 0 | E15: =IF(VLOOKUP(E$2,行为概览!$D$3:$L$33,9,0)="","",VLOOKUP(E$2,行为概览!$D$3:$L$33,9,0)*IF(玩法行为规划!D15>0,1,0)) -> 0 | F15: =IF(VLOOKUP(F$2,行为概览!$D$3:$L$33,9,0)="","",VLOOKUP(F$2,行为概览!$D$3:$L$33,9,0)*IF(玩法行为规划!E15>0,1,0)) -> 0 | G15: =IF(VLOOKUP(G$2,行为概览!$D$3:$L$33,9,0)="","",VLOOKUP(G$2,行为概览!$D$3:$L$33,9,0)*IF(玩法行为规划!F15>0,1,0)) | H15: =IF(VLOOKUP(H$2,行为概览!$D$3:$L$33,9,0)="","",VLOOKUP(H$2,行为概览!$D$3:$L$33,9,0)*IF(玩法行为规划!G15>0,1,0)) | I15: =IF(VLOOKUP(I$2,行为概览!$D$3:$L$33,9,0)="","",VLOOKUP(I$2,行为概览!$D$3:$L$33,9,0)*IF(玩法行为规划!H15>0,1,0)) | J15: =IF(VLOOKUP(J$2,行为概览!$D$3:$L$33,9,0)="","",VLOOKUP(J$2,行为概览!$D$3:$L$33,9,0)*IF(玩法行为规划!I15>0,1,0)) | ... AC15: =IF(VLOOKUP(AC$2,行为概览!$D$3:$L$33,9,0)="","",VLOOKUP(AC$2,行为概览!$D$3:$L$33,9,0)*IF(玩法行为规划!AB15>0,1,0)) | AD15: =IF(VLOOKUP(AD$2,行为概览!$D$3:$L$33,9,0)="","",VLOOKUP(AD$2,行为概览!$D$3:$L$33,9,0)*玩法行为规划!AC15) | AE15: =IF(VLOOKUP(AE$2,行为概览!$D$3:$L$33,9,0)="","",VLOOKUP(AE$2,行为概览!$D$3:$L$33,9,0)*玩法行为规划!AD15) | AF15: =SUM(C15:AC15) -> 5.5 | AG15: =B15*AF15 -> 71500 | AH15: =ROUND(AG15*升级节奏!G15,0) -> 0 | AI15: =ROUND(B15*(1+MAX(A15-40,0)*0.1),-2) -> 13000 | AJ15: =IF(--RIGHT(A15,1)=0,SUM(AI15:AI24),"") | AK15: =AI15/AL15 -> 1 | AL15: =AH15+AI15 -> 13000 | AM15: =SUM($AL$3:AL15) -> 91000 | AN15: =ROUND((B15*6+AH15)/30,-2) -> 2600 | AO15: =SUM($AN$3:AN15)*7 -> 127400 | AP15: =AM15-AO15-AQ15-AR15 -> -40300 | AQ15: =ROUND((B15*2+AH15)/10,-2) -> 2600 | AR15: =ROUND((B15*2+AH15)/20,-2) -> 1300
A16: 14 | B16: =升级节奏!E16 -> 14000 | C16: =IF(VLOOKUP(C$2,行为概览!$D$3:$L$33,9,0)="","",VLOOKUP(C$2,行为概览!$D$3:$L$33,9,0)*IF(玩法行为规划!B16>0,1,0)) -> 0 | D16: =IF(VLOOKUP(D$2,行为概览!$D$3:$L$33,9,0)="","",VLOOKUP(D$2,行为概览!$D$3:$L$33,9,0)*IF(玩法行为规划!C16>0,1,0)) -> 0 | E16: =IF(VLOOKUP(E$2,行为概览!$D$3:$L$33,9,0)="","",VLOOKUP(E$2,行为概览!$D$3:$L$33,9,0)*IF(玩法行为规划!D16>0,1,0)) -> 0 | F16: =IF(VLOOKUP(F$2,行为概览!$D$3:$L$33,9,0)="","",VLOOKUP(F$2,行为概览!$D$3:$L$33,9,0)*IF(玩法行为规划!E16>0,1,0)) -> 0 | G16: =IF(VLOOKUP(G$2,行为概览!$D$3:$L$33,9,0)="","",VLOOKUP(G$2,行为概览!$D$3:$L$33,9,0)*IF(玩法行为规划!F16>0,1,0)) | H16: =IF(VLOOKUP(H$2,行为概览!$D$3:$L$33,9,0)="","",VLOOKUP(H$2,行为概览!$D$3:$L$33,9,0)*IF(玩法行为规划!G16>0,1,0)) | I16: =IF(VLOOKUP(I$2,行为概览!$D$3:$L$33,9,0)="","",VLOOKUP(I$2,行为概览!$D$3:$L$33,9,0)*IF(玩法行为规划!H16>0,1,0)) | J16: =IF(VLOOKUP(J$2,行为概览!$D$3:$L$33,9,0)="","",VLOOKUP(J$2,行为概览!$D$3:$L$33,9,0)*IF(玩法行为规划!I16>0,1,0)) | ... AC16: =IF(VLOOKUP(AC$2,行为概览!$D$3:$L$33,9,0)="","",VLOOKUP(AC$2,行为概览!$D$3:$L$33,9,0)*IF(玩法行为规划!AB16>0,1,0)) | AD16: =IF(VLOOKUP(AD$2,行为概览!$D$3:$L$33,9,0)="","",VLOOKUP(AD$2,行为概览!$D$3:$L$33,9,0)*玩法行为规划!AC16) | AE16: =IF(VLOOKUP(AE$2,行为概览!$D$3:$L$33,9,0)="","",VLOOKUP(AE$2,行为概览!$D$3:$L$33,9,0)*玩法行为规划!AD16) | AF16: =SUM(C16:AC16) -> 5.5 | AG16: =B16*AF16 -> 77000 | AH16: =ROUND(AG16*升级节奏!G16,0) -> 0 | AI16: =ROUND(B16*(1+MAX(A16-40,0)*0.1),-2) -> 14000 | AJ16: =IF(--RIGHT(A16,1)=0,SUM(AI16:AI25),"") | AK16: =AI16/AL16 -> 1 | AL16: =AH16+AI16 -> 14000 | AM16: =SUM($AL$3:AL16) -> 105000 | AN16: =ROUND((B16*6+AH16)/30,-2) -> 2800 | AO16: =SUM($AN$3:AN16)*7 -> 147000 | AP16: =AM16-AO16-AQ16-AR16 -> -46200 | AQ16: =ROUND((B16*2+AH16)/10,-2) -> 2800 | AR16: =ROUND((B16*2+AH16)/20,-2) -> 1400
A17: 15 | B17: =升级节奏!E17 -> 15000 | C17: =IF(VLOOKUP(C$2,行为概览!$D$3:$L$33,9,0)="","",VLOOKUP(C$2,行为概览!$D$3:$L$33,9,0)*IF(玩法行为规划!B17>0,1,0)) -> 4 | D17: =IF(VLOOKUP(D$2,行为概览!$D$3:$L$33,9,0)="","",VLOOKUP(D$2,行为概览!$D$3:$L$33,9,0)*IF(玩法行为规划!C17>0,1,0)) -> 0 | E17: =IF(VLOOKUP(E$2,行为概览!$D$3:$L$33,9,0)="","",VLOOKUP(E$2,行为概览!$D$3:$L$33,9,0)*IF(玩法行为规划!D17>0,1,0)) -> 0 | F17: =IF(VLOOKUP(F$2,行为概览!$D$3:$L$33,9,0)="","",VLOOKUP(F$2,行为概览!$D$3:$L$33,9,0)*IF(玩法行为规划!E17>0,1,0)) -> 0 | G17: =IF(VLOOKUP(G$2,行为概览!$D$3:$L$33,9,0)="","",VLOOKUP(G$2,行为概览!$D$3:$L$33,9,0)*IF(玩法行为规划!F17>0,1,0)) | H17: =IF(VLOOKUP(H$2,行为概览!$D$3:$L$33,9,0)="","",VLOOKUP(H$2,行为概览!$D$3:$L$33,9,0)*IF(玩法行为规划!G17>0,1,0)) | I17: =IF(VLOOKUP(I$2,行为概览!$D$3:$L$33,9,0)="","",VLOOKUP(I$2,行为概览!$D$3:$L$33,9,0)*IF(玩法行为规划!H17>0,1,0)) | J17: =IF(VLOOKUP(J$2,行为概览!$D$3:$L$33,9,0)="","",VLOOKUP(J$2,行为概览!$D$3:$L$33,9,0)*IF(玩法行为规划!I17>0,1,0)) | ... AC17: =IF(VLOOKUP(AC$2,行为概览!$D$3:$L$33,9,0)="","",VLOOKUP(AC$2,行为概览!$D$3:$L$33,9,0)*IF(玩法行为规划!AB17>0,1,0)) | AD17: =IF(VLOOKUP(AD$2,行为概览!$D$3:$L$33,9,0)="","",VLOOKUP(AD$2,行为概览!$D$3:$L$33,9,0)*玩法行为规划!AC17) | AE17: =IF(VLOOKUP(AE$2,行为概览!$D$3:$L$33,9,0)="","",VLOOKUP(AE$2,行为概览!$D$3:$L$33,9,0)*玩法行为规划!AD17) | AF17: =SUM(C17:AC17) -> 9.5 | AG17: =B17*AF17 -> 142500 | AH17: =ROUND(AG17*升级节奏!G17,0) -> 0 | AI17: =ROUND(B17*(1+MAX(A17-40,0)*0.1),-2) -> 15000 | AJ17: =IF(--RIGHT(A17,1)=0,SUM(AI17:AI26),"") | AK17: =AI17/AL17 -> 1 | AL17: =AH17+AI17 -> 15000 | AM17: =SUM($AL$3:AL17) -> 120000 | AN17: =ROUND((B17*6+AH17)/30,-2) -> 3000 | AO17: =SUM($AN$3:AN17)*7 -> 168000 | AP17: =AM17-AO17-AQ17-AR17 -> -52500 | AQ17: =ROUND((B17*2+AH17)/10,-2) -> 3000 | AR17: =ROUND((B17*2+AH17)/20,-2) -> 1500
A18: 16 | B18: =升级节奏!E18 -> 16000 | C18: =IF(VLOOKUP(C$2,行为概览!$D$3:$L$33,9,0)="","",VLOOKUP(C$2,行为概览!$D$3:$L$33,9,0)*IF(玩法行为规划!B18>0,1,0)) -> 4 | D18: =IF(VLOOKUP(D$2,行为概览!$D$3:$L$33,9,0)="","",VLOOKUP(D$2,行为概览!$D$3:$L$33,9,0)*IF(玩法行为规划!C18>0,1,0)) -> 0 | E18: =IF(VLOOKUP(E$2,行为概览!$D$3:$L$33,9,0)="","",VLOOKUP(E$2,行为概览!$D$3:$L$33,9,0)*IF(玩法行为规划!D18>0,1,0)) -> 0 | F18: =IF(VLOOKUP(F$2,行为概览!$D$3:$L$33,9,0)="","",VLOOKUP(F$2,行为概览!$D$3:$L$33,9,0)*IF(玩法行为规划!E18>0,1,0)) -> 0 | G18: =IF(VLOOKUP(G$2,行为概览!$D$3:$L$33,9,0)="","",VLOOKUP(G$2,行为概览!$D$3:$L$33,9,0)*IF(玩法行为规划!F18>0,1,0)) | H18: =IF(VLOOKUP(H$2,行为概览!$D$3:$L$33,9,0)="","",VLOOKUP(H$2,行为概览!$D$3:$L$33,9,0)*IF(玩法行为规划!G18>0,1,0)) | I18: =IF(VLOOKUP(I$2,行为概览!$D$3:$L$33,9,0)="","",VLOOKUP(I$2,行为概览!$D$3:$L$33,9,0)*IF(玩法行为规划!H18>0,1,0)) | J18: =IF(VLOOKUP(J$2,行为概览!$D$3:$L$33,9,0)="","",VLOOKUP(J$2,行为概览!$D$3:$L$33,9,0)*IF(玩法行为规划!I18>0,1,0)) | ... AC18: =IF(VLOOKUP(AC$2,行为概览!$D$3:$L$33,9,0)="","",VLOOKUP(AC$2,行为概览!$D$3:$L$33,9,0)*IF(玩法行为规划!AB18>0,1,0)) | AD18: =IF(VLOOKUP(AD$2,行为概览!$D$3:$L$33,9,0)="","",VLOOKUP(AD$2,行为概览!$D$3:$L$33,9,0)*玩法行为规划!AC18) | AE18: =IF(VLOOKUP(AE$2,行为概览!$D$3:$L$33,9,0)="","",VLOOKUP(AE$2,行为概览!$D$3:$L$33,9,0)*玩法行为规划!AD18) | AF18: =SUM(C18:AC18) -> 9.5 | AG18: =B18*AF18 -> 152000 | AH18: =ROUND(AG18*升级节奏!G18,0) -> 0 | AI18: =ROUND(B18*(1+MAX(A18-40,0)*0.1),-2) -> 16000 | AJ18: =IF(--RIGHT(A18,1)=0,SUM(AI18:AI27),"") | AK18: =AI18/AL18 -> 1 | AL18: =AH18+AI18 -> 16000 | AM18: =SUM($AL$3:AL18) -> 136000 | AN18: =ROUND((B18*6+AH18)/30,-2) -> 3200 | AO18: =SUM($AN$3:AN18)*7 -> 190400 | AP18: =AM18-AO18-AQ18-AR18 -> -59200 | AQ18: =ROUND((B18*2+AH18)/10,-2) -> 3200 | AR18: =ROUND((B18*2+AH18)/20,-2) -> 1600
